Workbook
Name Valuation_Date: Inputs!$D$10
Name Price: Inputs!$D$11
Name Shares_Diluted: Inputs!$D$15
Name Base_FYE: Inputs!$D$16
Name Midyear: Inputs!$D$17
Name Days_Per_Year: Inputs!$D$18
Name Beta_Unlevered: Inputs!$D$136
Name Rf_Source: Inputs!$D$158
Name CAPM_Method: Inputs!$D$160
Name Kd_Method: Inputs!$D$164
Name Terminal_Method: Inputs!$D$171
Name Terminal_Growth: Inputs!$D$172
Name Exit_Multiple: Inputs!$D$173
Name DA_Method: Inputs!$D$180
Name Capex_Mode: Inputs!$D$181
Name Rf: WACC!$D$12
Name Ke: WACC!$D$30
Name Tax_Rate: WACC!$D$44
Name WACC: WACC!$D$54
Name Enterprise_Value: DCF!$D$30
Name Equity_Value: DCF!$D$52
Name DCF_Per_Share: DCF!$D$54
Name DDM_Per_Share: DDM!$D$25
Name Blended_Value: Summary!$D$14
Name Master_Check: Checks!$D$40

Sheet Cover
B2: Misr Fertilizers Production Company (MFPC.CA): Valuation workbook
B3: Discounted cash flow valuation with cross-checks. Analytical only; not investment advice. Inputs are as entered; macro rates from the frozen snapshot listed on Sources.
B4: Blue = hardcoded input | Black = formula
B6: Valuation
D7: Value | F7: Notes
B8: Company | D8: Misr Fertilizers Production Company
B9: Ticker | D9: MFPC.CA
B10: Valuation date | C10: date | D10: =Inputs!$D$10
B11: Share price | C11: EGP | D11: =Inputs!$D$11
B12: Price date | C12: date | D12: =Inputs!$D$12
B13: Prepared by | D13: Ahmed Wael Metwally
B14: Rates snapshot | D14: seed-2026-09-23 | F14: Frozen 2026-09-24T07:01:32.500Z
B15: Terminal method | D15: gordon
B16: Master check (all checks TRUE) | D16: =Checks!$D$40
B18: Contents
D19: Sheet | F19: Notes
B20: Cover | D20: Cover
B21: Summary | D21: Summary
B22: Inputs | D22: Inputs
B23: Sources | D23: Sources
B24: Historical | D24: Historical
B25: Normalization | D25: Normalization
B26: Operating Model | D26: Operating Model
B27: WACC | D27: WACC
B28: DCF | D28: DCF
B29: USD Check | D29: USD Check
B30: DDM | D30: DDM
B31: Comps Precedents SOTP | D31: Comps Precedents SOTP
... B34: Checks | D34: Checks

Sheet Summary
B2: MOPCO: Summary
B3: Value per share by method, blend weights, implied upside and key assumptions. Values are live formulas from the model sheets.
B4: Blue = hardcoded input | Black = formula
B6: Value per share by method
D7: Value per share | E7: Entered weight | F7: Effective weight | G7: Notes
B8: DCF (FCFF) | C8: EGP | D8: =DCF!$D$54 | E8: =Inputs!$D$241 | F8: =IF(AND(ISNUMBER($D$8),$E$8>0),$E$8/SUMPRODUCT(ISNUMBER($D$8:$D$12)*($E$8:$E$12)),0)
B9: Dividend discount model (two-stage) | C9: EGP | D9: =DDM!$D$25 | E9: =Inputs!$D$242 | F9: =IF(AND(ISNUMBER($D$9),$E$9>0),$E$9/SUMPRODUCT(ISNUMBER($D$8:$D$12)*($E$8:$E$12)),0)
B10: Trading comparables (median EV/EBITDA) | C10: EGP | D10: ="n/a" | E10: =Inputs!$D$243 | F10: =IF(AND(ISNUMBER($D$10),$E$10>0),$E$10/SUMPRODUCT(ISNUMBER($D$8:$D$12)*($E$8:$E$12)),0) | G10: Excluded when no inputs are entered.
B11: Precedent transactions (median EV/EBITDA) | C11: EGP | D11: ="n/a" | E11: =Inputs!$D$244 | F11: =IF(AND(ISNUMBER($D$11),$E$11>0),$E$11/SUMPRODUCT(ISNUMBER($D$8:$D$12)*($E$8:$E$12)),0) | G11: Excluded when no inputs are entered.
B12: Sum of the parts | C12: EGP | D12: ="n/a" | E12: =Inputs!$D$245 | F12: =IF(AND(ISNUMBER($D$12),$E$12>0),$E$12/SUMPRODUCT(ISNUMBER($D$8:$D$12)*($E$8:$E$12)),0) | G12: Excluded when no inputs are entered.
B13: Entered weights sum | C13: % | E13: =SUM($E$8:$E$12)
B14: Blended value per share | C14: EGP | D14: =SUMPRODUCT($D$8:$D$12,$F$8:$F$12)
B15: Share price (2026-07-01) | C15: EGP | D15: =Inputs!$D$11
B16: Implied upside | C16: % | D16: =$D$14/$D$15-1
B17: Band | D17: =IF(ABS($D$16)<=Inputs!$D$249,"In line with market price",IF($D$16>0,"Above market price","Below market price"))
B19: Implied multiples (DCF)
D20: Value | G20: Notes
B21: EV / normalized EBITDA FY2025A | C21: x | D21: =DCF!$D$59
B22: EV / EBITDA FY2026E | C22: x | D22: =DCF!$D$60
B23: P/E FY2025A | C23: x | D23: =DCF!$D$61
B24: P/E FY2026E | C24: x | D24: =DCF!$D$62
B25: PV of terminal value / EV | C25: % | D25: =DCF!$D$31
B27: Key assumptions
D28: Value | G28: Notes
B29: WACC | C29: % | D29: =WACC!$D$54
B30: Cost of equity | C30: % | D30: =WACC!$D$30
B31: Risk-free rate | C31: % | D31: =WACC!$D$12 | G31: eg.bond10ySecondary, as of 2026-05-21, status stale
B32: Levered beta | C32: x | D32: =WACC!$D$21
B33: Terminal growth | C33: % | D33: =Inputs!$D$172
B34: Terminal method | D34: =Inputs!$D$171
B35: Employee and board distributions, % of prior-year profit | C35: % | D35: =Inputs!$D$201*Inputs!$D$200
B37: Football field (value per share)
D38: Low | E38: Mid | F38: High | G38: Notes
B39: DCF (FCFF): WACC ± 1 step × g ± 1 step | C39: EGP | D39: =MIN(Sensitivity!$E$22:$G$24) | E39: =DCF!$D$54 | F39: =MAX(Sensitivity!$E$22:$G$24)
B40: Dividend discount model | C40: EGP | D40: =MIN(DDM!$D$25,DDM!$D$27) | E40: =DDM!$D$25 | F40: =MAX(DDM!$D$25,DDM!$D$27)
B41: Scenarios (Bear to Bull) | C41: EGP | D41: =Scenarios!$D$60 | E41: =Scenarios!$D$20 | F41: =Scenarios!$D$134
B42: Monte Carlo P5 to P95 (engine output, seed 20260923) | C42: EGP | D42: =Inputs!$D$294 | E42: =Inputs!$D$295 | F42: =Inputs!$D$296 | G42: Simulation is run by the engine; not reproduced in the workbook
B43: Share price | C43: EGP | E43: =Inputs!$D$11

Sheet Inputs
B2: MOPCO: Inputs
B3: Every hardcoded number used by the workbook. Company data from the audited statements; rates from the frozen snapshot; assumptions as set by the analyst.
B4: Blue = hardcoded input | Black = formula
B6: Company and timeline
D7: Value | J7: Notes
B8: Company | D8: Misr Fertilizers Production Company | J8: Sourced fact
B9: Ticker | D9: MFPC.CA | J9: Sourced fact
B10: Valuation date | C10: date | D10: 46205 | J10: Analyst assumption. Mandatory.
B11: Share price | C11: EGP | D11: 36 | J11: Sourced fact: EFG Hermes research page (user input; EGX has no free official price feed)
B12: Price date | C12: date | D12: 46204 | J12: Sourced fact. Mandatory.
B13: Basic shares | C13: shares | D13: 2868140263 | J13: Sourced fact. After the 2025 bonus issue; EPS for both years computed on this count.
B14: Dilutive items | C14: shares | D14: 0 | J14: None disclosed
B15: Diluted shares | C15: shares | D15: =$D$13+$D$14
B16: Base fiscal year end | C16: date | D16: 46022 | J16: Sourced fact: latest audited year end
B17: Mid-year discounting (1 = on, 0 = off) | C17: flag | D17: 1 | J17: Analyst assumption
B18: Days per year (unit conversion) | C18: days | D18: 365 | J18: Unit conversion for years from valuation date and working-capital days
B19: Projection years | C19: years | D19: 5 | J19: Structural: one column per projection year
B21: Income statement
C22: EGP | D22: 2024A | E22: 2025A | J22: Notes
B23: Net sales | C23: EGP | D23: 19650320858 | E23: 26844075576 | J23: Sourced fact: audited statements
B24: of which export sales | C24: EGP | D24: 15069860384 | E24: 21466612052 | J24: Sourced fact: audited statements
B25: Cost of sales | C25: EGP | D25: -10802884928 | E25: -13307578650 | J25: Sourced fact: audited statements
B26: Gross profit | C26: EGP | D26: 8847435930 | E26: 13536496926 | J26: Sourced fact: audited statements
B27: Other income | C27: EGP | D27: 173469168 | E27: 273707416 | J27: Sourced fact: audited statements
B28: of which provisions no longer required | C28: EGP | D28: 19299728 | E28: 160216876 | J28: Sourced fact: audited statements
B29: Selling and marketing | C29: EGP | D29: -531853525 | E29: -526930783 | J29: Sourced fact: audited statements
B30: General and administrative | C30: EGP | D30: -591253894 | E30: -648542515 | J30: Sourced fact: audited statements
B31: Capital gains | C31: EGP | D31: 3619907 | E31: 13156038 | J31: Sourced fact: audited statements
B32: Other expenses | C32: EGP | D32: -233949210 | E32: -44594149 | J32: Sourced fact: audited statements
B33: Impairment reversal | C33: EGP | D33: 310962888 | E33: 0 | J33: Sourced fact: audited statements
B34: ECL reversal / (charge) | C34: EGP | D34: -390502424 | E34: 357037587 | J34: Sourced fact: audited statements
... B53: EPS as reported | C53: EGP | D53: 5.27 | E53: 3.94 | J53: Sourced fact: audited statements
B55: Balance sheet
C56: EGP | D56: 2024A | E56: 2025A | J56: Notes
B57: Fixed assets and projects under construction | C57: EGP | D57: 34632006997 | E57: 38192488081 | J57: Sourced fact: audited statements
B58: Other assets and projects | C58: EGP | D58: 68215075 | E58: 79638512 | J58: Sourced fact: audited statements
B59: Right-of-use assets | C59: EGP | D59: 88041967 | E59: 72034336 | J59: Sourced fact: audited statements
B60: Goodwill | C60: EGP | D60: 0 | E60: 0 | J60: Sourced fact: audited statements
B61: Associates (equity method) | C61: EGP | D61: 2407651 | E61: 2424170 | J61: Sourced fact: audited statements
B62: Amortized-cost investments (non-current) | C62: EGP | D62: 5562646156 | E62: 10659141927 | J62: Sourced fact: audited statements
B63: Restricted / pledged deposits (non-current) | C63: EGP | D63: 1131212791 | E63: 1010115488 | J63: Sourced fact: audited statements
B64: Deferred tax asset | C64: EGP | D64: 0 | E64: 0 | J64: Sourced fact: audited statements
B65: Other non-current assets | C65: EGP | D65: 0 | E65: 0 | J65: Sourced fact: audited statements
B66: Inventory | C66: EGP | D66: 1713951385 | E66: 1927396704 | J66: Sourced fact: audited statements
B67: Accounts receivable | C67: EGP | D67: 541148818 | E67: 1446674104 | J67: Sourced fact: audited statements
B68: Amortized-cost investments (current) | C68: EGP | D68: 3827217186 | E68: 734010745 | J68: Sourced fact: audited statements
... B100: Total liabilities | C100: EGP | D100: 12624286542 | E100: 13387262693 | J100: Sourced fact: audited statements
B102: Cash flow statement
C103: EGP | D103: 2024A | E103: 2025A | J103: Notes
B104: Cash from operations before distributions and taxes | C104: EGP | D104: 11871965105 | E104: 14242562977 | J104: Sourced fact: audited statements
B105: Dividends paid to employees and board | C105: EGP | D105: -977311347 | E105: -1545237364 | J105: Sourced fact: audited statements
B106: Income taxes paid | C106: EGP | D106: -2735903582 | E106: -2997048224 | J106: Sourced fact: audited statements
B107: Employee benefits paid | C107: EGP | D107: -7650510 | E107: -14889098 | J107: Sourced fact: audited statements
B108: Other operating cash flows | C108: EGP | D108: 0 | E108: 0 | J108: Sourced fact: audited statements
B109: Net cash from operating activities | C109: EGP | D109: 8151099666 | E109: 9685388291 | J109: Sourced fact: audited statements
B110: Interest received | C110: EGP | D110: 1520913784 | E110: 2046816410 | J110: Sourced fact: audited statements
B111: Capex | C111: EGP | D111: -1275986560 | E111: -5848069006 | J111: Sourced fact: audited statements
B112: Dividends paid to shareholders | C112: EGP | D112: -11955401802 | E112: -7277190123 | J112: Sourced fact: audited statements
B113: Lease payments | C113: EGP | D113: -33209307 | E113: -37991816 | J113: Sourced fact: audited statements
B114: Net change in cash | C114: EGP | D114: -3639978381 | E114: -3553233614 | J114: Sourced fact: audited statements
B116: Normalization adjustments (removed from reported operating profit)
D117: Include (1/0) | J117: Notes
B118: ECL reversal / (charge) | C118: flag | D118: 1 | J118: Analyst assumption. Expected credit loss movements are non-recurring. Amount from the FY2025 income statement.
B119: Provisions no longer required (inside other income) | C119: flag | D119: 1 | J119: Analyst assumption. Release of prior-year provisions does not recur. Amount from the FY2025 income statement.
B120: Capital gains / (losses) on disposals | C120: flag | D120: 1 | J120: Analyst assumption. Disposal gains are not part of recurring operations. Amount from the FY2025 income statement.
B122: Rates used (frozen snapshot seed-2026-09-23)
D123: Value | J123: Notes
B124: EGP 10Y government bond, secondary-market YTM [eg.bond10ySecondary] | C124: % | D124: 0.2158 | J124: Sourced fact: Cbonds, as of 2026-05-21, status stale
B125: EGP T-bond auction, 3y fixed coupon (accepted weighted average yield) [eg.tbondAuction.3y] | C125: % | D125: 0.23147 | J125: Sourced fact: Central Bank of Egypt, T-bond auction results, as of 2026-07-13, status stale. Not used by the selected methods.
B126: Inflation-based riskfree rate, EGP [damodaran.rf.egp] | C126: % | D126: 0.10204428 | J126: Estimate: Damodaran Online (NYU Stern), as of 2026-07-01, status ok. Not used by the selected methods.
B127: US Treasury 10Y [us.treasury10y] | C127: % | D127: 0.051 | J127: Sourced fact: US Treasury (intraday, owner research), as of 2026-09-23, status ok
B128: Expected inflation 2026-2031, Egypt [damodaran.expectedInflation.egp] | C128: % | D128: 0.082166667 | J128: Estimate: Damodaran Online (NYU Stern), as of 2026-07-01, status ok. Not used by the selected methods.
B129: Expected inflation, USD [damodaran.expectedInflation.usd] | C129: % | D129: 0.0235 | J129: Estimate: Damodaran Online (NYU Stern), as of 2026-07-01, status ok. Not used by the selected methods.
B130: Mature-market equity risk premium [damodaran.matureErp] | C130: % | D130: 0.042 | J130: Estimate: Damodaran Online (NYU Stern), as of 2026-07-01, status ok
B131: Egypt country risk premium [damodaran.egypt.crp] | C131: % | D131: 0.092806228 | J131: Estimate: Damodaran Online (NYU Stern), as of 2026-07-01, status ok
B132: Egypt rating-based default spread [damodaran.egypt.defaultSpread] | C132: % | D132: 0.05970183 | J132: Estimate: Damodaran Online (NYU Stern), as of 2026-07-01, status ok
B133: Corporate income tax rate [eg.cit] | C133: % | D133: 0.225 | J133: Sourced fact: Income Tax Law 91/2005, as of 2026-09-23, status ok
B134: USD/EGP [eg.usdEgp] | C134: EGP/USD | D134: 51.9 | J134: Sourced fact: Market close (owner research), as of 2026-09-21, status ok
B135: CBE overnight lending rate [cbe.overnightLending] | C135: % | D135: 0.2 | J135: Sourced fact: Central Bank of Egypt, as of 2026-08-20, status stale. Not used by the selected methods.
B136: Unlevered beta (corrected for cash) | C136: x | D136: 1.0605126 | J136: Estimate: Damodaran emerging markets, industry "Chemical (Basic)", dataset 2026-01-05
B138: Synthetic rating table (damodaran.synthetic.small, sorted by lower coverage bound)
D139: Coverage above | E139: Rating | F139: Spread | J139: Notes
D140: -100000 | E140: D2/D | F140: 0.19 | J140: Estimate: Damodaran ratings.xls
D141: 0.5 | E141: C2/C | F141: 0.16 | J141: Estimate: Damodaran ratings.xls
D142: 0.8 | E142: Ca2/CC | F142: 0.1261 | J142: Estimate: Damodaran ratings.xls
D143: 1.25 | E143: Caa/CCC | F143: 0.0885 | J143: Estimate: Damodaran ratings.xls
D144: 1.5 | E144: B3/B- | F144: 0.0509 | J144: Estimate: Damodaran ratings.xls
D145: 2 | E145: B2/B | F145: 0.0321 | J145: Estimate: Damodaran ratings.xls
D146: 2.5 | E146: B1/B+ | F146: 0.0275 | J146: Estimate: Damodaran ratings.xls
D147: 3 | E147: Ba2/BB | F147: 0.0184 | J147: Estimate: Damodaran ratings.xls
D148: 3.5 | E148: Ba1/BB+ | F148: 0.0138 | J148: Estimate: Damodaran ratings.xls
D149: 4 | E149: Baa2/BBB | F149: 0.0111 | J149: Estimate: Damodaran ratings.xls
D150: 4.5 | E150: A3/A- | F150: 0.0089 | J150: Estimate: Damodaran ratings.xls
D151: 6 | E151: A2/A | F151: 0.0078 | J151: Estimate: Damodaran ratings.xls
... D154: 12.5 | E154: Aaa/AAA | F154: 0.004 | J154: Estimate: Damodaran ratings.xls
B156: Cost of capital
D157: Value | J157: Notes
B158: Risk-free source (eg_10y_secondary / cbe_auction / damodaran_egp / fisher_us10y) | C158: text | D158: eg_10y_secondary | J158: Analyst assumption
B159: Auction yield used when source = cbe_auction | C159: % | D159: =Inputs!$D$125 | J159: Registry id eg.tbondAuction.3y
B160: CAPM method (local_rf / A / B / C) | C160: text | D160: local_rf | J160: Analyst assumption
...

Sheet Sources
B2: MOPCO: Sources
B3: Every registry value in the frozen rates snapshot seed-2026-09-23, with source, date and status; and the source of the company data.
B4: Blue = hardcoded input | Black = formula
B6: Company data
D7: Value | O7: Notes
B8: Financial statements | D8: Audited financial statements for the year ended 31 December 2025 (with FY2024 comparatives). All amounts in EGP.
B9: Auditor | D9: Crowe - Dr. A. M. Hegazy & Co.
B10: Audit report date | C10: date | D10: 46090
B11: Share price source | D11: EFG Hermes research page (user input; EGX has no free official price feed)
B12: Associate | D12: 25% stake in Damietta Green Ammonia, accounted for by the equity method. | O12: Audited FY2025 financial statements
B13: Capital commitments | D13: Outstanding capital commitments: EGP 939m + USD 4m + EUR 101m. | O13: Audited FY2025 financial statements
B14: Expansion project | D14: Urea/ammonia expansion project spend to date approximately EGP 5.9bn. | O14: Audited FY2025 financial statements
B15: Employee profit share | D15: Articles of association pay 10% of cash dividends to employees, capped at annual salaries. | O15: Audited FY2025 financial statements
B16: Borrowings | D16: Bank borrowings are nil at 31-Dec-2025 and 31-Dec-2024. Interest-bearing debt consists of lease liabilities only. | O16: Audited FY2025 financial statements
B17: Historical years | D17: FY2021 to FY2023 not supplied as audited data and left empty. | O17: Owner instruction
B18: Segments | D18: Urea / ammonia segment figures are in the segment note of the audited statements but were not supplied in the fixture data; SOTP requires user entry. | O18: Owner instruction
B20: Rates registry (snapshot seed-2026-09-23)
C21: Label | D21: Id | E21: Value | F21: Unit | G21: Nature | H21: Source | I21: URL | J21: As of | K21: Method | L21: Status | M21: Used in model | N21: Flag | O21: Notes
B22: CBE overnight deposit rate | D22: cbe.overnightDeposit | E22: 0.19 | F22: pct | G22: official | H22: Central Bank of Egypt | I22: https://www.cbe.org.eg/en/ | J22: 46254 | K22: manual | L22: stale | M22: No | N22: =IF(AND($M$22="Yes",$L$22<>"ok"),"Flagged: "&$L$22,"") | O22: MPC 20-Aug-2026: rates held. Next MPC 24-Sep-2026; must be re-verified after that meeting.
B23: CBE overnight lending rate | D23: cbe.overnightLending | E23: 0.2 | F23: pct | G23: official | H23: Central Bank of Egypt | I23: https://www.cbe.org.eg/en/ | J23: 46254 | K23: manual | L23: stale | M23: No | N23: =IF(AND($M$23="Yes",$L$23<>"ok"),"Flagged: "&$L$23,"")
B24: CBE main operation rate | D24: cbe.mainOperation | E24: 0.195 | F24: pct | G24: official | H24: Central Bank of Egypt | I24: https://www.cbe.org.eg/en/ | J24: 46254 | K24: manual | L24: stale | M24: No | N24: =IF(AND($M$24="Yes",$L$24<>"ok"),"Flagged: "&$L$24,"")
B25: CBE discount rate | D25: cbe.discountRate | E25: 0.195 | F25: pct | G25: official | H25: Central Bank of Egypt | I25: https://www.cbe.org.eg/en/monetary-policy/mpc-meetings-schedule | J25: 46254 | K25: manual | L25: stale | M25: No | N25: =IF(AND($M$25="Yes",$L$25<>"ok"),"Flagged: "&$L$25,"")
B26: CBE inflation target | D26: cbe.inflationTarget | E26: 7% ±2pp, Q4 2026 (CBE guidance now points to 2H 2027) | F26: text | G26: official | H26: Central Bank of Egypt | I26: https://www.cbe.org.eg/en/monetary-policy/inflation-target | J26: 46254 | K26: manual | L26: ok | M26: No | N26: =IF(AND($M$26="Yes",$L$26<>"ok"),"Flagged: "&$L$26,"")
B27: CBE inflation target (point, for USD-check inflation fade) | D27: cbe.inflationTargetPoint | E27: 0.07 | F27: pct | G27: official | H27: Central Bank of Egypt | I27: https://www.cbe.org.eg/en/monetary-policy/inflation-target | J27: 46254 | K27: manual | L27: ok | M27: No | N27: =IF(AND($M$27="Yes",$L$27<>"ok"),"Flagged: "&$L$27,"") | O27: Point of the 7% ±2pp target. The CBE homepage on 23-Sep-2026 shows "7.0% (±2 percentage points) on average in 2026 Q4".
B28: CBE MPC meeting dates | D28: cbe.mpcCalendar | E28: 2026-08-20, 2026-09-24 | F28: date_list | G28: official | H28: Central Bank of Egypt, MPC meetings schedule | I28: https://www.cbe.org.eg/en/monetary-policy/mpc-meetings-schedule | J28: 46288 | K28: manual | L28: unconfirmed | M28: No | N28: =IF(AND($M$28="Yes",$L$28<>"ok"),"Flagged: "&$L$28,"") | O28: 20-Aug-2026 confirmed by the CBE homepage news item "MPC decides to keep key policy rates unchanged". 24-Sep-2026 from owner research. The CBE schedule page renders dates with JavaScript and could not be read on 23-Sep-2026; remaining 2026 and 2027 dates are unconfirmed.
B29: Urban headline CPI inflation, y/y | D29: eg.cpiUrbanHeadline | E29: 0.145 | F29: pct | G29: official | H29: CAPMAS (reported by CBE) | I29: https://www.cbe.org.eg/en/monetary-policy/inflation | J29: 46265 | K29: manual | L29: ok | M29: No | N29: =IF(AND($M$29="Yes",$L$29<>"ok"),"Flagged: "&$L$29,"") | O29: August 2026, released 10-Sep-2026.
B30: Core CPI inflation, y/y | D30: eg.cpiCore | E30: 0.149 | F30: pct | G30: official | H30: Central Bank of Egypt | I30: https://www.cbe.org.eg/en/monetary-policy/inflation | J30: 46265 | K30: manual | L30: ok | M30: No | N30: =IF(AND($M$30="Yes",$L$30<>"ok"),"Flagged: "&$L$30,"")
B31: Nationwide CPI inflation, y/y | D31: eg.cpiNationwide | E31: 0.127 | F31: pct | G31: official | H31: CAPMAS | I31: TO_VERIFY | J31: 46265 | K31: manual | L31: ok | M31: No | N31: =IF(AND($M$31="Yes",$L$31<>"ok"),"Flagged: "&$L$31,"")
B32: USD/EGP | D32: eg.usdEgp | E32: 51.9 | F32: EGP_per_USD | G32: market_quote | H32: Market close (owner research) | I32: TO_VERIFY | J32: 46286 | K32: manual | L32: ok | M32: Yes | N32: =IF(AND($M$32="Yes",$L$32<>"ok"),"Flagged: "&$L$32,"") | O32: Approximate market close 21-Sep-2026. The Worker replaces it with the CBE official rate (https://www.cbe.org.eg/en/economic-research/statistics/cbe-exchange-rates).
B33: EGP 10Y government bond, secondary-market YTM | D33: eg.bond10ySecondary | E33: 0.2158 | F33: pct | G33: market_quote | H33: Cbonds | I33: TO_VERIFY | J33: 46163 | K33: manual | L33: stale | M33: Yes | N33: =IF(AND($M$33="Yes",$L$33<>"ok"),"Flagged: "&$L$33,"") | O33: Last quote available to the owner is 21-May-2026. Manual refresh required.
B34: EGP T-bond auction, 3y fixed coupon (accepted weighted average yield) | D34: eg.tbondAuction.3y | E34: 0.23147 | F34: pct | G34: official | H34: Central Bank of Egypt, T-bond auction results | I34: https://www.cbe.org.eg/en/auctions/egp-t-bonds-fixed-coupon | J34: 46216 | K34: manual | L34: stale | M34: No | N34: =IF(AND($M$34="Yes",$L$34<>"ok"),"Flagged: "&$L$34,"") | O34: Auction of 13-Jul-2026. Recent auctions were 2Y and 3Y only.
B35: US Treasury 10Y | D35: us.treasury10y | E35: 0.051 | F35: pct | G35: market_quote | H35: US Treasury (intraday, owner research) | I35: https://home.treasury.gov/resource-center/data-chart-center/interest-rates/TextView?type=daily_treasury_yield_curve | J35: 46288 | K35: manual | L35: ok | M35: Yes | N35: =IF(AND($M$35="Yes",$L$35<>"ok"),"Flagged: "&$L$35,"") | O35: Approximate intraday level 23-Sep-2026. The Worker replaces it with the Treasury daily par yield (10-year).
B36: Egypt sovereign rating, Moody's | D36: eg.rating.moodys | E36: Caa1 (positive) | F36: rating | G36: official | H36: Moody's Ratings | I36: https://ratings.moodys.com/ratings-news/462631 | J36: 46115 | K36: manual | L36: ok | M36: No | N36: =IF(AND($M$36="Yes",$L$36<>"ok"),"Flagged: "&$L$36,"")
B37: Egypt sovereign rating, S&P | D37: eg.rating.sp | E37: B (stable) | F37: rating | G37: official | H37: S&P Global Ratings press release; secondary: Ahram Online 11-Apr-2026 | I37: TO_VERIFY | J37: 46123 | K37: manual | L37: ok | M37: No | N37: =IF(AND($M$37="Yes",$L$37<>"ok"),"Flagged: "&$L$37,"") | O37: Affirmation at B/B, stable. Candidate primary URL from a search index, not opened (HTTP 403 on 23-Sep-2026): https://www.spglobal.com/ratings/en/regulatory/article/-/view/type/HTML/id/3544107. The pre-v2 engine showed "B-", which is wrong.
B38: Egypt sovereign rating, Fitch | D38: eg.rating.fitch | E38: B (stable) | F38: rating | G38: official | H38: Fitch Ratings (via Ahram Online, 11-Oct-2025) | I38: https://english.ahram.org.eg/News/554751.aspx | J38: 45941 | K38: manual | L38: unconfirmed | M38: No | N38: =IF(AND($M$38="Yes",$L$38<>"ok"),"Flagged: "&$L$38,"") | O38: Last confirmed action Oct-2025. No 2026 Fitch action found on 23-Sep-2026; fitchratings.com not checked successfully.
B39: Corporate income tax rate | D39: eg.cit | E39: 0.225 | F39: pct | G39: statutory | H39: Income Tax Law 91/2005 | I39: TO_VERIFY | J39: 46288 | K39: manual | L39: ok | M39: Yes | N39: =IF(AND($M$39="Yes",$L$39<>"ok"),"Flagged: "&$L$39,"")
B40: Dividend withholding tax, EGX-listed | D40: eg.dividendWht.listed | E40: 0.05 | F40: pct | G40: statutory | H40: Law 151 of 2026 | I40: TO_VERIFY | J40: 46232 | K40: manual | L40: ok | M40: No | N40: =IF(AND($M$40="Yes",$L$40<>"ok"),"Flagged: "&$L$40,"") | O40: Effective 29-Jul-2026.
B41: Dividend withholding tax, unlisted | D41: eg.dividendWht.unlisted | E41: 0.1 | F41: pct | G41: statutory | H41: Law 151 of 2026 | I41: TO_VERIFY | J41: 46232 | K41: manual | L41: ok | M41: No | N41: =IF(AND($M$41="Yes",$L$41<>"ok"),"Flagged: "&$L$41,"")
B42: Participation exemption | D42: eg.participationExemption | E42: 100% exempt if holding ≥25% for ≥2 years | F42: text | G42: statutory | H42: Law 151 of 2026 | I42: TO_VERIFY | J42: 46232 | K42: manual | L42: ok | M42: No | N42: =IF(AND($M$42="Yes",$L$42<>"ok"),"Flagged: "&$L$42,"")
B43: EGX stamp duty per side | D43: eg.stampDuty.perSide | E43: 0.0005 | F43: pct | G43: statutory | H43: Law 151 of 2026 | I43: TO_VERIFY | J43: 46232 | K43: manual | L43: ok | M43: No | N43: =IF(AND($M$43="Yes",$L$43<>"ok"),"Flagged: "&$L$43,"") | O43: 0.05% per side on EGX trades; 0.025% per side for same-session trades; withheld by MCDR from the 29-Jul-2026 session. The pre-v2 engine used 0.125%, which is wrong.
B44: Capital gains tax, listed shares | D44: eg.cgt.listedShares | E44: Exempt (replaced by stamp duty) | F44: text | G44: statutory | H44: Law 151 of 2026 | I44: TO_VERIFY | J44: 46232 | K44: manual | L44: ok | M44: No | N44: =IF(AND($M$44="Yes",$L$44<>"ok"),"Flagged: "&$L$44,"")
B45: Mature-market equity risk premium | D45: damodaran.matureErp | E45: 0.042 | F45: pct | G45: estimate | H45: Damodaran Online (NYU Stern) | I45: https://pages.stern.nyu.edu/~adamodar/pc/datasets/ctrypremJuly26.xlsx | J45: 46204 | K45: manual | L45: ok | M45: Yes | N45: =IF(AND($M$45="Yes",$L$45<>"ok"),"Flagged: "&$L$45,"") | O45: Workbook "ERPs by country"!E3 = 0.042. Secondary sources conflict (4.17% vs 4.20%); the workbook value is used.
B46: Equity / bond volatility scalar | D46: damodaran.volatilityScalar | E46: 1.5544955 | F46: ratio | G46: estimate | H46: Damodaran Online (NYU Stern) | I46: https://pages.stern.nyu.edu/~adamodar/pc/datasets/ctrypremJuly26.xlsx | J46: 46204 | K46: manual | L46: ok | M46: No | N46: =IF(AND($M$46="Yes",$L$46<>"ok"),"Flagged: "&$L$46,"") | O46: Workbook "ERPs by country"!E6 (from "Relative Equity Volatility"!D7).
B47: Egypt rating used by Damodaran | D47: damodaran.egypt.rating | E47: Caa1 | F47: rating | G47: estimate | H47: Damodaran Online (NYU Stern) | I47: https://pages.stern.nyu.edu/~adamodar/pc/datasets/ctrypremJuly26.xlsx | J47: 46204 | K47: manual | L47: ok | M47: No | N47: =IF(AND($M$47="Yes",$L$47<>"ok"),"Flagged: "&$L$47,"") | O47: Moody's rating column.
B48: Egypt rating-based default spread | D48: damodaran.egypt.defaultSpread | E48: 0.05970183 | F48: pct | G48: estimate | H48: Damodaran Online (NYU Stern) | I48: https://pages.stern.nyu.edu/~adamodar/pc/datasets/ctrypremJuly26.xlsx | J48: 46204 | K48: manual | L48: ok | M48: Yes | N48: =IF(AND($M$48="Yes",$L$48<>"ok"),"Flagged: "&$L$48,"")
B49: Egypt country risk premium | D49: damodaran.egypt.crp | E49: 0.092806228 | F49: pct | G49: estimate | H49: Damodaran Online (NYU Stern) | I49: https://pages.stern.nyu.edu/~adamodar/pc/datasets/ctrypremJuly26.xlsx | J49: 46204 | K49: manual | L49: ok | M49: Yes | N49: =IF(AND($M$49="Yes",$L$49<>"ok"),"Flagged: "&$L$49,"")
B50: Egypt total equity risk premium | D50: damodaran.egypt.totalErp | E50: 0.13480623 | F50: pct | G50: estimate | H50: Damodaran Online (NYU Stern) | I50: https://pages.stern.nyu.edu/~adamodar/pc/datasets/ctrypremJuly26.xlsx | J50: 46204 | K50: manual | L50: ok | M50: No | N50: =IF(AND($M$50="Yes",$L$50<>"ok"),"Flagged: "&$L$50,"")
B51: Inflation-based riskfree rate, EGP | D51: damodaran.rf.egp | E51: 0.10204428 | F51: pct | G51: estimate | H51: Damodaran Online (NYU Stern) | I51: https://pages.stern.nyu.edu/~adamodar/pc/blog/DiffInflationRiskfree26.xlsx | J51: 46204 | K51: manual | L51: ok | M51: No | N51: =IF(AND($M$51="Yes",$L$51<>"ok"),"Flagged: "&$L$51,"") | O51: Damodaran "Inflation-based riskfree rates, by currency - July 2026": USD riskfree adjusted for the expected inflation differential (2026-2031).
B52: Riskfree rate, USD (Damodaran, July 2026) | D52: damodaran.rf.usd | E52: 0.0423 | F52: pct | G52: estimate | H52: Damodaran Online (NYU Stern) | I52: https://pages.stern.nyu.edu/~adamodar/pc/blog/DiffInflationRiskfree26.xlsx | J52: 46204 | K52: manual | L52: ok | M52: No | N52: =IF(AND($M$52="Yes",$L$52<>"ok"),"Flagged: "&$L$52,"")
B53: Expected inflation 2026-2031, Egypt | D53: damodaran.expectedInflation.egp | E53: 0.082166667 | F53: pct | G53: estimate | H53: Damodaran Online (NYU Stern) | I53: https://pages.stern.nyu.edu/~adamodar/pc/blog/DiffInflationRiskfree26.xlsx | J53: 46204 | K53: manual | L53: ok | M53: No | N53: =IF(AND($M$53="Yes",$L$53<>"ok"),"Flagged: "&$L$53,"")
B54: Expected inflation, USD | D54: damodaran.expectedInflation.usd | E54: 0.0235 | F54: pct | G54: estimate | H54: Damodaran Online (NYU Stern) | I54: https://pages.stern.nyu.edu/~adamodar/pc/blog/DiffInflationRiskfree26.xlsx | J54: 46204 | K54: manual | L54: ok | M54: No | N54: =IF(AND($M$54="Yes",$L$54<>"ok"),"Flagged: "&$L$54,"")
B55: Emerging-market industry betas (unlevered, corrected for cash) | D55: damodaran.betas.emerging | E55: Table, 96 rows | F55: table | G55: estimate | H55: Damodaran Online (NYU Stern) | I55: https://pages.stern.nyu.edu/~adamodar/pc/datasets/betaemerg.xls | J55: 46027 | K55: manual | L55: ok | M55: Yes | N55: =IF(AND($M$55="Yes",$L$55<>"ok"),"Flagged: "&$L$55,"") | O55: Dataset "Date updated" cell = 2026-01-05; updated annually in January. 96 industries.
B56: Synthetic rating table, large non-financial firms | D56: damodaran.synthetic.large | E56: Table, 15 rows | F56: table | G56: estimate | H56: Damodaran Online (NYU Stern) | I56: https://pages.stern.nyu.edu/~adamodar/pc/ratings.xls | J56: 46023 | K56: manual | L56: ok | M56: No | N56: =IF(AND($M$56="Yes",$L$56<>"ok"),"Flagged: "&$L$56,"") | O56: ratings.html: "Data used is as of January 2026". Spreads in percent.
B57: Synthetic rating table, smaller and riskier firms | D57: damodaran.synthetic.small | E57: Table, 15 rows | F57: table | G57: estimate | H57: Damodaran Online (NYU Stern) | I57: https://pages.stern.nyu.edu/~adamodar/pc/ratings.xls | J57: 46023 | K57: manual | L57: ok | M57: Yes | N57: =IF(AND($M$57="Yes",$L$57<>"ok"),"Flagged: "&$L$57,"") | O57: ratings.html: "Data used is as of January 2026". Spreads in percent.

Sheet Historical
B2: MOPCO: Historical analysis
B3: Audited years available: 2024, 2025. Earlier years were not supplied and are not filled. N/A where two years are required.
B4: Blue = hardcoded input | Black = formula
B6: Ratios
D7: 2024A | E7: 2025A | G7: Notes
B8: Revenue growth | C8: % | D8: N/A | E8: =Inputs!$E$23/Inputs!$D$23-1
B9: Gross margin | C9: % | D9: =Inputs!$D$26/Inputs!$D$23 | E9: =Inputs!$E$26/Inputs!$E$23
B10: EBITDA margin (reported) | C10: % | D10: =(Inputs!$D$36+Inputs!$D$51+Inputs!$D$52)/Inputs!$D$23 | E10: =(Inputs!$E$36+Inputs!$E$51+Inputs!$E$52)/Inputs!$E$23
B11: Net margin | C11: % | D11: =Inputs!$D$49/Inputs!$D$23 | E11: =Inputs!$E$49/Inputs!$E$23
B12: Effective tax rate | C12: % | D12: =-Inputs!$D$48/Inputs!$D$45 | E12: =-Inputs!$E$48/Inputs!$E$45
B13: Return on equity (year-end equity) | C13: % | D13: =Inputs!$D$49/Inputs!$D$83 | E13: =Inputs!$E$49/Inputs!$E$83
B14: Current ratio | C14: x | D14: =(Inputs!$D$66+Inputs!$D$67+Inputs!$D$68+Inputs!$D$69+Inputs!$D$70+Inputs!$D$71+Inputs!$D$72+Inputs!$D$73+Inputs!$D$74)/(Inputs!$D$90+Inputs!$D$91+Inputs!$D$92+Inputs!$D$93+Inputs!$D$94+Inputs!$D$95+Inputs!$D$96+Inputs!$D$97+Inputs!$D$98+Inputs!$D$99) | E14: =(Inputs!$E$66+Inputs!$E$67+Inputs!$E$68+Inputs!$E$69+Inputs!$E$70+Inputs!$E$71+Inputs!$E$72+Inputs!$E$73+Inputs!$E$74)/(Inputs!$E$90+Inputs!$E$91+Inputs!$E$92+Inputs!$E$93+Inputs!$E$94+Inputs!$E$95+Inputs!$E$96+Inputs!$E$97+Inputs!$E$98+Inputs!$E$99)
B15: Net cash (cash and investments less debt and leases) | C15: EGP | D15: =Inputs!$D$74+Inputs!$D$69+Inputs!$D$68+Inputs!$D$62-Inputs!$D$90-Inputs!$D$91-(Inputs!$D$84+Inputs!$D$85+Inputs!$D$86) | E15: =Inputs!$E$74+Inputs!$E$69+Inputs!$E$68+Inputs!$E$62-Inputs!$E$90-Inputs!$E$91-(Inputs!$E$84+Inputs!$E$85+Inputs!$E$86)
B17: Piotroski F-score (latest year versus prior year; ratios on year-end total assets)
D18: Current | E18: Prior | F18: Score | G18: Notes
B19: Return on assets positive | D19: =Inputs!$E$49/Inputs!$E$75 | F19: =IF($D$19>0,1,0)
B20: Operating cash flow positive | D20: =Inputs!$E$109 | F20: =IF($D$20>0,1,0)
B21: Return on assets improved | D21: =Inputs!$E$49/Inputs!$E$75 | E21: =Inputs!$D$49/Inputs!$D$75 | F21: =IF($D$21>$E$21,1,0)
B22: Cash flow / assets above ROA (accruals) | D22: =Inputs!$E$109/Inputs!$E$75 | E22: =Inputs!$E$49/Inputs!$E$75 | F22: =IF($D$22>$E$22,1,0)
B23: Long-term leverage lower | D23: =(Inputs!$E$84+Inputs!$E$85+Inputs!$E$86)/Inputs!$E$75 | E23: =(Inputs!$D$84+Inputs!$D$85+Inputs!$D$86)/Inputs!$D$75 | F23: =IF($D$23<$E$23,1,0)
B24: Current ratio higher | D24: =(Inputs!$E$66+Inputs!$E$67+Inputs!$E$68+Inputs!$E$69+Inputs!$E$70+Inputs!$E$71+Inputs!$E$72+Inputs!$E$73+Inputs!$E$74)/(Inputs!$E$90+Inputs!$E$91+Inputs!$E$92+Inputs!$E$93+Inputs!$E$94+Inputs!$E$95+Inputs!$E$96+Inputs!$E$97+Inputs!$E$98+Inputs!$E$99) | E24: =(Inputs!$D$66+Inputs!$D$67+Inputs!$D$68+Inputs!$D$69+Inputs!$D$70+Inputs!$D$71+Inputs!$D$72+Inputs!$D$73+Inputs!$D$74)/(Inputs!$D$90+Inputs!$D$91+Inputs!$D$92+Inputs!$D$93+Inputs!$D$94+Inputs!$D$95+Inputs!$D$96+Inputs!$D$97+Inputs!$D$98+Inputs!$D$99) | F24: =IF($D$24>$E$24,1,0)
B25: No equity issued (shares restated; bonus issues are not dilution) | D25: =Inputs!$D$13 | E25: =Inputs!$D$13 | F25: =IF($D$25<=$E$25,1,0)
B26: Gross margin higher | D26: =Inputs!$E$26/Inputs!$E$23 | E26: =Inputs!$D$26/Inputs!$D$23 | F26: =IF($D$26>$E$26,1,0)
B27: Asset turnover higher | D27: =Inputs!$E$23/Inputs!$E$75 | E27: =Inputs!$D$23/Inputs!$D$75 | F27: =IF($D$27>$E$27,1,0)
B28: F-score | C28: of 9 | F28: =SUM($F$19:$F$27)
B30: Altman Z''-EM (Altman 2005, emerging markets)
D31: 2024A | E31: 2025A | G31: Notes
B32: X1 working capital / total assets | C32: x | D32: =((Inputs!$D$66+Inputs!$D$67+Inputs!$D$68+Inputs!$D$69+Inputs!$D$70+Inputs!$D$71+Inputs!$D$72+Inputs!$D$73+Inputs!$D$74)-(Inputs!$D$90+Inputs!$D$91+Inputs!$D$92+Inputs!$D$93+Inputs!$D$94+Inputs!$D$95+Inputs!$D$96+Inputs!$D$97+Inputs!$D$98+Inputs!$D$99))/Inputs!$D$75 | E32: =((Inputs!$E$66+Inputs!$E$67+Inputs!$E$68+Inputs!$E$69+Inputs!$E$70+Inputs!$E$71+Inputs!$E$72+Inputs!$E$73+Inputs!$E$74)-(Inputs!$E$90+Inputs!$E$91+Inputs!$E$92+Inputs!$E$93+Inputs!$E$94+Inputs!$E$95+Inputs!$E$96+Inputs!$E$97+Inputs!$E$98+Inputs!$E$99))/Inputs!$E$75
B33: X2 retained earnings / total assets | C33: x | D33: =Inputs!$D$79/Inputs!$D$75 | E33: =Inputs!$E$79/Inputs!$E$75
B34: X3 EBIT / total assets | C34: x | D34: =Inputs!$D$36/Inputs!$D$75 | E34: =Inputs!$E$36/Inputs!$E$75
B35: X4 book equity / total liabilities | C35: x | D35: =Inputs!$D$83/Inputs!$D$100 | E35: =Inputs!$E$83/Inputs!$E$100
B36: Z''-EM score | C36: x | D36: =Inputs!$D$259+Inputs!$D$260*$D$32+Inputs!$D$261*$D$33+Inputs!$D$262*$D$34+Inputs!$D$263*$D$35 | E36: =Inputs!$D$259+Inputs!$D$260*$E$32+Inputs!$D$261*$E$33+Inputs!$D$262*$E$34+Inputs!$D$263*$E$35
B37: Zone | D37: =IF($D$36>Inputs!$D$264,"Safe",IF($D$36>=Inputs!$D$265,"Grey","Distress")) | E37: =IF($E$36>Inputs!$D$264,"Safe",IF($E$36>=Inputs!$D$265,"Grey","Distress"))
B39: DuPont (FY2025; average balances)
D40: Value | G40: Notes
B41: Net margin | C41: % | D41: =Inputs!$E$49/Inputs!$E$23
B42: Asset turnover | C42: x | D42: =Inputs!$E$23/AVERAGE(Inputs!$D$75,Inputs!$E$75)
B43: Equity multiplier | C43: x | D43: =AVERAGE(Inputs!$D$75,Inputs!$E$75)/AVERAGE(Inputs!$D$83,Inputs!$E$83)
B44: ROE (3-step) | C44: % | D44: =$D$41*$D$42*$D$43
B45: Tax burden (net profit / PBT) | C45: x | D45: =Inputs!$E$49/Inputs!$E$45
B46: Interest burden (PBT / EBIT) | C46: x | D46: =Inputs!$E$45/Inputs!$E$36 | G46: Above 1 when finance income exceeds finance costs
B47: EBIT margin | C47: % | D47: =Inputs!$E$36/Inputs!$E$23
B48: ROE (5-step) | C48: % | D48: =$D$45*$D$46*$D$47*$D$42*$D$43

Sheet Normalization
B2: MOPCO: Normalization
B3: Reported FY2025 operating profit to normalized EBIT and EBITDA. Each adjustment is an analyst assumption and can be switched off on Inputs.
B4: Blue = hardcoded input | Black = formula
B6: FY2025A
D7: Amount | E7: Include | F7: Removed | G7: Notes
B8: Reported operating profit | C8: EGP | D8: =Inputs!$E$36 | G8: Sourced fact
B9: Less: ECL reversal / (charge) | C9: EGP | D9: =Inputs!$E$34 | E9: =Inputs!$D$118 | F9: =$D$9*$E$9 | G9: Analyst assumption. Expected credit loss movements are non-recurring. Amount from the FY2025 income statement.
B10: Less: Provisions no longer required (inside other income) | C10: EGP | D10: =Inputs!$E$28 | E10: =Inputs!$D$119 | F10: =$D$10*$E$10 | G10: Analyst assumption. Release of prior-year provisions does not recur. Amount from the FY2025 income statement.
B11: Less: Capital gains / (losses) on disposals | C11: EGP | D11: =Inputs!$E$31 | E11: =Inputs!$D$120 | F11: =$D$11*$E$11 | G11: Analyst assumption. Disposal gains are not part of recurring operations. Amount from the FY2025 income statement.
B12: Total removed | C12: EGP | F12: =$F$9+$F$10+$F$11
B13: Normalized EBIT | C13: EGP | D13: =$D$8-$F$12
B14: Add: depreciation | C14: EGP | D14: =Inputs!$E$51 | G14: Sourced fact (notes)
B15: Add: amortization | C15: EGP | D15: =Inputs!$E$52 | G15: Sourced fact (notes)
B16: Normalized EBITDA | C16: EGP | D16: =$D$13+$D$14+$D$15
B17: Reported EBITDA (operating profit + D&A) | C17: EGP | D17: =$D$8+$D$14+$D$15
B19: Finance income and FX translation gains or losses are non-operating: excluded from FCFF; the related balance-sheet items enter the equity bridge.

Sheet Operating Model
B2: MOPCO: Operating model
B3: Revenue to EBITDA, EBIT, NOPAT, working capital, PP&E roll-forward, distributions and FCFF. Drivers from Inputs; base year from the audited statements.
B4: Blue = hardcoded input | Black = formula
B6: Operating model
C7: Unit | D7: 2025A | E7: 2026E | F7: 2027E | G7: 2028E | H7: 2029E | I7: 2030E | J7: Terminal | K7: Notes
B8: Revenue growth | C8: % | D8: =Inputs!$E$23/Inputs!$D$23-1 | E8: =Inputs!$D$182 | F8: =Inputs!$E$182 | G8: =Inputs!$F$182 | H8: =Inputs!$G$182 | I8: =Inputs!$H$182 | J8: =Inputs!$D$172 | K8: Inputs; terminal year = terminal growth
B9: Revenue | C9: EGP | D9: =Inputs!$E$23 | E9: =$D$9*(1+$E$8) | F9: =$E$9*(1+$F$8) | G9: =$F$9*(1+$G$8) | H9: =$G$9*(1+$H$8) | I9: =$H$9*(1+$I$8) | J9: =$I$9*(1+$J$8) | K9: Prior year × (1 + growth)
B10: Gross margin before D&A | C10: % | D10: =(Inputs!$E$26+Inputs!$E$51+Inputs!$E$52)/$D$9 | E10: =Inputs!$D$183 | F10: =Inputs!$E$183 | G10: =Inputs!$F$183 | H10: =Inputs!$G$183 | I10: =Inputs!$H$183 | J10: =Inputs!$I$183 | K10: All D&A assumed in cost of sales
B11: Gross profit before D&A | C11: EGP | D11: =$D$9*$D$10 | E11: =$E$9*$E$10 | F11: =$F$9*$F$10 | G11: =$G$9*$G$10 | H11: =$H$9*$H$10 | I11: =$I$9*$I$10 | J11: =$J$9*$J$10
B12: SG&A | C12: % revenue | D12: =-(Inputs!$E$29+Inputs!$E$30)/$D$9 | E12: =Inputs!$D$184 | F12: =Inputs!$E$184 | G12: =Inputs!$F$184 | H12: =Inputs!$G$184 | I12: =Inputs!$H$184 | J12: =Inputs!$I$184
B13: SG&A | C13: EGP | D13: =-(Inputs!$E$29+Inputs!$E$30) | E13: =$E$9*$E$12 | F13: =$F$9*$F$12 | G13: =$G$9*$G$12 | H13: =$H$9*$H$12 | I13: =$I$9*$I$12 | J13: =$J$9*$J$12
B14: Other operating (net) | C14: % revenue | D14: =(Normalization!$D$13-Inputs!$E$26-Inputs!$E$29-Inputs!$E$30)/$D$9 | E14: =Inputs!$D$185 | F14: =Inputs!$E$185 | G14: =Inputs!$F$185 | H14: =Inputs!$G$185 | I14: =Inputs!$H$185 | J14: =Inputs!$I$185 | K14: Normalized: after removing non-recurring items
B15: Other operating income (net) | C15: EGP | D15: =Normalization!$D$13-Inputs!$E$26-Inputs!$E$29-Inputs!$E$30 | E15: =$E$9*$E$14 | F15: =$F$9*$F$14 | G15: =$G$9*$G$14 | H15: =$H$9*$H$14 | I15: =$I$9*$I$14 | J15: =$J$9*$J$14
B16: EBITDA | C16: EGP | D16: =$D$11-$D$13+$D$15 | E16: =$E$11-$E$13+$E$15 | F16: =$F$11-$F$13+$F$15 | G16: =$G$11-$G$13+$G$15 | H16: =$H$11-$H$13+$H$15 | I16: =$I$11-$I$13+$I$15 | J16: =$J$11-$J$13+$J$15 | K16: Base year = normalized EBITDA
B17: Opening PP&E | C17: EGP | E17: =Inputs!$E$57 | F17: =$E$22 | G17: =$F$22 | H17: =$G$22 | I17: =$H$22 | J17: =$I$22
B18: Depreciation | C18: EGP | D18: =Inputs!$E$51 | E18: =IF(Inputs!$D$180="ppe_rollforward",Inputs!$D$187*$E$17,$E$9*Inputs!$D$186) | F18: =IF(Inputs!$D$180="ppe_rollforward",Inputs!$E$187*$F$17,$F$9*Inputs!$E$186) | G18: =IF(Inputs!$D$180="ppe_rollforward",Inputs!$F$187*$G$17,$G$9*Inputs!$F$186) | H18: =IF(Inputs!$D$180="ppe_rollforward",Inputs!$G$187*$H$17,$H$9*Inputs!$G$186) | I18: =IF(Inputs!$D$180="ppe_rollforward",Inputs!$H$187*$I$17,$I$9*Inputs!$H$186) | J18: =IF(Inputs!$D$180="ppe_rollforward",Inputs!$I$187*$J$17,$J$9*Inputs!$I$186) | K18: Roll-forward: rate × opening PP&E; % revenue mode: D&A % × revenue
B19: Amortization | C19: EGP | D19: =Inputs!$E$52 | E19: =IF(Inputs!$D$180="ppe_rollforward",$E$9*Inputs!$D$188,0) | F19: =IF(Inputs!$D$180="ppe_rollforward",$F$9*Inputs!$E$188,0) | G19: =IF(Inputs!$D$180="ppe_rollforward",$G$9*Inputs!$F$188,0) | H19: =IF(Inputs!$D$180="ppe_rollforward",$H$9*Inputs!$G$188,0) | I19: =IF(Inputs!$D$180="ppe_rollforward",$I$9*Inputs!$H$188,0) | J19: =IF(Inputs!$D$180="ppe_rollforward",$J$9*Inputs!$I$188,0)
B20: D&A | C20: EGP | D20: =$D$18+$D$19 | E20: =$E$18+$E$19 | F20: =$F$18+$F$19 | G20: =$G$18+$G$19 | H20: =$H$18+$H$19 | I20: =$I$18+$I$19 | J20: =$J$18+$J$19
B21: Capex | C21: EGP | D21: =-Inputs!$E$111 | E21: =IF(Inputs!$D$181="absolute",Inputs!$D$190,$E$9*Inputs!$D$189) | F21: =IF(Inputs!$D$181="absolute",Inputs!$E$190,$F$9*Inputs!$E$189) | G21: =IF(Inputs!$D$181="absolute",Inputs!$F$190,$G$9*Inputs!$F$189) | H21: =IF(Inputs!$D$181="absolute",Inputs!$G$190,$H$9*Inputs!$G$189) | I21: =IF(Inputs!$D$181="absolute",Inputs!$H$190,$I$9*Inputs!$H$189) | J21: =$J$9*Inputs!$I$189 | K21: Terminal year: % revenue (value-driver consistent)
B22: Closing PP&E | C22: EGP | D22: =Inputs!$E$57 | E22: =$E$17+$E$21-$E$18 | F22: =$F$17+$F$21-$F$18 | G22: =$G$17+$G$21-$G$18 | H22: =$H$17+$H$21-$H$18 | I22: =$I$17+$I$21-$I$18 | J22: =$J$17+$J$21-$J$18 | K22: Opening + capex − depreciation
B23: EBIT | C23: EGP | D23: =$D$16-$D$20 | E23: =$E$16-$E$20 | F23: =$F$16-$F$20 | G23: =$G$16-$G$20 | H23: =$H$16-$H$20 | I23: =$I$16-$I$20 | J23: =$J$16-$J$20 | K23: Base year = normalized EBIT
B24: Tax rate on EBIT | C24: % | D24: =Inputs!$D$133 | E24: =Inputs!$D$196 | F24: =Inputs!$E$196 | G24: =Inputs!$F$196 | H24: =Inputs!$G$196 | I24: =Inputs!$H$196 | J24: =Inputs!$I$196
B25: Tax on EBIT | C25: EGP | D25: =$D$23*$D$24 | E25: =$E$23*$E$24 | F25: =$F$23*$F$24 | G25: =$G$23*$G$24 | H25: =$H$23*$H$24 | I25: =$I$23*$I$24 | J25: =$J$23*$J$24
B26: NOPAT | C26: EGP | D26: =$D$23-$D$25 | E26: =$E$23-$E$25 | F26: =$F$23-$F$25 | G26: =$G$23-$G$25 | H26: =$H$23-$H$25 | I26: =$I$23-$I$25 | J26: =$J$23-$J$25
B27: Cash cost of sales | C27: EGP | D27: =$D$9*(1-$D$10) | E27: =$E$9*(1-$E$10) | F27: =$F$9*(1-$F$10) | G27: =$G$9*(1-$G$10) | H27: =$H$9*(1-$H$10) | I27: =$I$9*(1-$I$10) | J27: =$J$9*(1-$J$10) | K27: Revenue × (1 − gross margin before D&A)
B28: Receivable days | C28: days | D28: =Inputs!$E$67/$D$9*Inputs!$D$18 | E28: =Inputs!$D$191 | F28: =Inputs!$E$191 | G28: =Inputs!$F$191 | H28: =Inputs!$G$191 | I28: =Inputs!$H$191 | J28: =Inputs!$I$191
B29: Accounts receivable | C29: EGP | D29: =Inputs!$E$67 | E29: =$E$9*$E$28/Inputs!$D$18 | F29: =$F$9*$F$28/Inputs!$D$18 | G29: =$G$9*$G$28/Inputs!$D$18 | H29: =$H$9*$H$28/Inputs!$D$18 | I29: =$I$9*$I$28/Inputs!$D$18 | J29: =$J$9*$J$28/Inputs!$D$18
B30: Inventory days | C30: days | D30: =Inputs!$E$66/$D$27*Inputs!$D$18 | E30: =Inputs!$D$192 | F30: =Inputs!$E$192 | G30: =Inputs!$F$192 | H30: =Inputs!$G$192 | I30: =Inputs!$H$192 | J30: =Inputs!$I$192
B31: Inventory | C31: EGP | D31: =Inputs!$E$66 | E31: =$E$27*$E$30/Inputs!$D$18 | F31: =$F$27*$F$30/Inputs!$D$18 | G31: =$G$27*$G$30/Inputs!$D$18 | H31: =$H$27*$H$30/Inputs!$D$18 | I31: =$I$27*$I$30/Inputs!$D$18 | J31: =$J$27*$J$30/Inputs!$D$18
B32: Payable days | C32: days | D32: =Inputs!$E$93/$D$27*Inputs!$D$18 | E32: =Inputs!$D$193 | F32: =Inputs!$E$193 | G32: =Inputs!$F$193 | H32: =Inputs!$G$193 | I32: =Inputs!$H$193 | J32: =Inputs!$I$193
B33: Trade payables | C33: EGP | D33: =Inputs!$E$93 | E33: =$E$27*$E$32/Inputs!$D$18 | F33: =$F$27*$F$32/Inputs!$D$18 | G33: =$G$27*$G$32/Inputs!$D$18 | H33: =$H$27*$H$32/Inputs!$D$18 | I33: =$I$27*$I$32/Inputs!$D$18 | J33: =$J$27*$J$32/Inputs!$D$18
B34: Other operating current assets | C34: % revenue | D34: =(Inputs!$E$70+Inputs!$E$72+Inputs!$E$71)/$D$9 | E34: =Inputs!$D$194 | F34: =Inputs!$E$194 | G34: =Inputs!$F$194 | H34: =Inputs!$G$194 | I34: =Inputs!$H$194 | J34: =Inputs!$I$194
B35: Other operating current assets | C35: EGP | D35: =Inputs!$E$70+Inputs!$E$72+Inputs!$E$71 | E35: =$E$9*$E$34 | F35: =$F$9*$F$34 | G35: =$G$9*$G$34 | H35: =$H$9*$H$34 | I35: =$I$9*$I$34 | J35: =$J$9*$J$34 | K35: Debtors and other debit balances, supplier advances, due from related parties
B36: Other operating current liabilities | C36: % revenue | D36: =(Inputs!$E$94+Inputs!$E$95+Inputs!$E$97+Inputs!$E$98+Inputs!$E$99)/$D$9 | E36: =Inputs!$D$195 | F36: =Inputs!$E$195 | G36: =Inputs!$F$195 | H36: =Inputs!$G$195 | I36: =Inputs!$H$195 | J36: =Inputs!$I$195
B37: Other operating current liabilities | C37: EGP | D37: =Inputs!$E$94+Inputs!$E$95+Inputs!$E$97+Inputs!$E$98+Inputs!$E$99 | E37: =$E$9*$E$36 | F37: =$F$9*$F$36 | G37: =$G$9*$G$36 | H37: =$H$9*$H$36 | I37: =$I$9*$I$36 | J37: =$J$9*$J$36 | K37: Creditors and other credit balances, customer advances, provisions, due to related parties
B38: Operating net working capital | C38: EGP | D38: =$D$29+$D$31+$D$35-$D$33-$D$37 | E38: =$E$29+$E$31+$E$35-$E$33-$E$37 | F38: =$F$29+$F$31+$F$35-$F$33-$F$37 | G38: =$G$29+$G$31+$G$35-$G$33-$G$37 | H38: =$H$29+$H$31+$H$35-$H$33-$H$37 | I38: =$I$29+$I$31+$I$35-$I$33-$I$37 | J38: =$J$29+$J$31+$J$35-$J$33-$J$37
B39: Change in net working capital | C39: EGP | E39: =$E$38-$D$38 | F39: =$F$38-$E$38 | G39: =$G$38-$F$38 | H39: =$H$38-$G$38 | I39: =$I$38-$H$38 | J39: =$J$38-$I$38
B40: Net profit (forecast: NOPAT + after-tax net finance income) | C40: EGP | D40: =Inputs!$E$49 | E40: =$E$26+Inputs!$D$202*(1-$E$24) | F40: =$F$26+Inputs!$D$202*(1-$F$24) | G40: =$G$26+Inputs!$D$202*(1-$G$24) | H40: =$H$26+Inputs!$D$202*(1-$H$24) | I40: =$I$26+Inputs!$D$202*(1-$I$24) | J40: =$J$26+Inputs!$D$202*(1-$J$24) | K40: Distribution base and forward P/E only
B41: Employee and board distributions | C41: EGP | E41: =IF(Inputs!$D$200=1,Inputs!$D$201*$D$40,0) | F41: =IF(Inputs!$D$200=1,Inputs!$D$201*$E$40,0) | G41: =IF(Inputs!$D$200=1,Inputs!$D$201*$F$40,0) | H41: =IF(Inputs!$D$200=1,Inputs!$D$201*$G$40,0) | I41: =IF(Inputs!$D$200=1,Inputs!$D$201*$H$40,0) | J41: =IF(Inputs!$D$200=1,Inputs!$D$201*$I$40,0) | K41: % of prior-year net profit
B42: Free cash flow to the firm (FCFF) | C42: EGP | E42: =$E$26+$E$20-$E$21-$E$39-$E$41 | F42: =$F$26+$F$20-$F$21-$F$39-$F$41 | G42: =$G$26+$G$20-$G$21-$G$39-$G$41 | H42: =$H$26+$H$20-$H$21-$H$39-$H$41 | I42: =$I$26+$I$20-$I$21-$I$39-$I$41 | J42: =$J$26+$J$20-$J$21-$J$39-$J$41 | K42: NOPAT + D&A − capex − change in NWC − distributions

Sheet WACC
B2: MOPCO: Cost of capital
B3: Risk-free rate, bottom-up beta, cost of equity, cost of debt and weights. All rates from the frozen snapshot on Inputs.
B4: Blue = hardcoded input | Black = formula
B6: Risk-free rate
D7: Value | E7: Notes
B8: (a) EGP 10Y secondary YTM | C8: % | D8: =Inputs!$D$124 | E8: As of 2026-05-21, status stale
B9: (b) CBE auction yield (selected tenor) | C9: % | D9: =Inputs!$D$159
B10: (c) Damodaran inflation-based EGP riskfree | C10: % | D10: =Inputs!$D$126
B11: (d) US 10Y converted with expected inflation (Fisher) | C11: % | D11: =(1+Inputs!$D$127)*(1+Inputs!$D$128)/(1+Inputs!$D$129)-1
B12: Risk-free rate used | C12: % | D12: =IF(Inputs!$D$158="eg_10y_secondary",$D$8,IF(Inputs!$D$158="cbe_auction",$D$9,IF(Inputs!$D$158="damodaran_egp",$D$10,$D$11))) | E12: Source: eg_10y_secondary
B13: Clean risk-free rate (1 = yes) | C13: flag | D13: =IF(OR(Inputs!$D$158="damodaran_egp",Inputs!$D$158="fisher_us10y"),1,0) | E13: Local government yields already contain sovereign default risk
B15: Beta (bottom-up)
D16: Value | E16: Notes
B17: Unlevered beta (corrected for cash) | C17: x | D17: =Inputs!$D$136 | E17: Industry: Chemical (Basic); dataset 2026-01-05
B18: Interest-bearing debt (bank, bonds, leases) | C18: EGP | D18: =Inputs!$E$90+Inputs!$E$84+Inputs!$E$85+Inputs!$E$91+Inputs!$E$86 | E18: Book value as market-value proxy
B19: Market value of equity | C19: EGP | D19: =Inputs!$D$11*Inputs!$D$15 | E19: Price × diluted shares
B20: D/E | C20: x | D20: =$D$18/$D$19
B21: Levered beta | C21: x | D21: =$D$17*(1+(1-Inputs!$D$163)*$D$20) | E21: βU × (1 + (1 − t) × D/E)
B23: Cost of equity
D24: Value | E24: Notes
B25: Mature-market ERP | C25: % | D25: =Inputs!$D$130
B26: Egypt country risk premium | C26: % | D26: =Inputs!$D$131
B27: Size / illiquidity premium | C27: % | D27: =Inputs!$D$162
B28: Premium multiplied by beta | C28: % | D28: =IF(Inputs!$D$160="B",$D$25+$D$26,$D$25) | E28: Method B loads CRP into the beta premium
B29: Premium added outside beta | C29: % | D29: =IF(Inputs!$D$160="A",$D$26,IF(Inputs!$D$160="C",Inputs!$D$161*$D$26,0))+$D$27 | E29: Method A: CRP; C: λ × CRP; local_rf and B: none
B30: Cost of equity (Ke) | C30: % | D30: =$D$12+$D$21*$D$28+$D$29 | E30: Method local_rf
B32: Cost of debt
D33: Value | E33: Notes
B34: Debt and lease interest (employee-benefit interest excluded) | C34: EGP | D34: =-(Inputs!$E$38+Inputs!$E$39)
B35: Interest coverage (normalized EBIT / interest) | C35: x | D35: =IF($D$34>0,Normalization!$D$13/$D$34,"no interest")
B36: Synthetic rating table row | C36: row | D36: =IF($D$34>0,MATCH($D$35,Inputs!$D$140:$D$154,1),ROWS(Inputs!$D$140:$D$154)) | E36: Largest lower coverage bound not above the coverage
B37: Synthetic rating | C37: text | D37: =INDEX(Inputs!$E$140:$E$154,$D$36)
B38: Company default spread | C38: % | D38: =INDEX(Inputs!$F$140:$F$154,$D$36)
B39: Country default spread (added when Rf is clean) | C39: % | D39: =Inputs!$D$132
B40: Kd, synthetic | C40: % | D40: =$D$12+$D$38+$D$13*$D$39
B41: Kd, CBE lending + spread | C41: % | D41: =Inputs!$D$135+Inputs!$D$165
B42: Kd, actual (interest / average interest-bearing debt) | C42: % | D42: =IFERROR($D$34/(AVERAGE($D$18,Inputs!$D$90+Inputs!$D$84+Inputs!$D$85+Inputs!$D$91+Inputs!$D$86)),"n/a")
B43: Pre-tax cost of debt used | C43: % | D43: =IF(Inputs!$D$164="synthetic",$D$40,IF(Inputs!$D$164="cbe_plus_spread",$D$41,$D$42)) | E43: Method synthetic
B44: Tax rate | C44: % | D44: =Inputs!$D$133
B45: After-tax cost of debt | C45: % | D45: =$D$43*(1-$D$44)
B46: Company spread for the USD check (0 unless synthetic) | C46: % | D46: =IF(Inputs!$D$164="synthetic",$D$38,0)
B47: Kd moves with Rf (1 = synthetic) | C47: flag | D47: =IF(Inputs!$D$164="synthetic",1,0)
B48: Kd component independent of Rf | C48: % | D48: =IF(Inputs!$D$164="synthetic",$D$38+$D$13*$D$39,$D$43)
B50: Weights and WACC
D51: Value | E51: Notes
B52: E/V | C52: % | D52: =IF(Inputs!$D$166="target",1-Inputs!$D$167,$D$19/($D$19+$D$18))
B53: D/V | C53: % | D53: =IF(Inputs!$D$166="target",Inputs!$D$167,$D$18/($D$19+$D$18))
B54: WACC | C54: % | D54: =$D$52*$D$30+$D$53*$D$45
B55: Risk-free rate eg.bond10ySecondary is stale (as of 2026-05-21).

Sheet DCF
B2: MOPCO: DCF
B3: Stub year and mid-year timing from the valuation date; Gordon and exit-multiple terminal values; equity bridge from the latest balance sheet (cash flows between the year end and the valuation date are not captured).
B4: Blue = hardcoded input | Black = formula
B6: Discounting (valuation date, stub, mid-year)
C7: Unit | D7: 2026E | E7: 2027E | F7: 2028E | G7: 2029E | H7: 2030E | I7: Notes
B8: Fiscal year ended | C8: date | D8: =DATE(YEAR(Inputs!$D$16)+1,MONTH(Inputs!$D$16),DAY(Inputs!$D$16)) | E8: =DATE(YEAR($D$8)+1,MONTH($D$8),DAY($D$8)) | F8: =DATE(YEAR($E$8)+1,MONTH($E$8),DAY($E$8)) | G8: =DATE(YEAR($F$8)+1,MONTH($F$8),DAY($F$8)) | H8: =DATE(YEAR($G$8)+1,MONTH($G$8),DAY($G$8))
B9: Period start | C9: date | D9: =MAX(Inputs!$D$10,Inputs!$D$16) | E9: =$D$8 | F9: =$E$8 | G9: =$F$8 | H9: =$G$8
B10: Share of year cash flow included | C10: % | D10: =IF(Inputs!$D$10>Inputs!$D$16,YEARFRAC(Inputs!$D$10,$D$8,1),1) | E10: =YEARFRAC($E$9,$E$8,1) | F10: =YEARFRAC($F$9,$F$8,1) | G10: =YEARFRAC($G$9,$G$8,1) | H10: =YEARFRAC($H$9,$H$8,1) | I10: Year 1 = YEARFRAC(valuation date, first fiscal year end, actual/actual)
B11: Date for discounting | C11: date | D11: =IF(Inputs!$D$17=1,AVERAGE($D$9,$D$8),$D$8) | E11: =IF(Inputs!$D$17=1,AVERAGE($E$9,$E$8),$E$8) | F11: =IF(Inputs!$D$17=1,AVERAGE($F$9,$F$8),$F$8) | G11: =IF(Inputs!$D$17=1,AVERAGE($G$9,$G$8),$G$8) | H11: =IF(Inputs!$D$17=1,AVERAGE($H$9,$H$8),$H$8) | I11: Mid-point of the period when mid-year is on, else period end
B12: Years from valuation date | C12: years | D12: =($D$11-Inputs!$D$10)/Inputs!$D$18 | E12: =($E$11-Inputs!$D$10)/Inputs!$D$18 | F12: =($F$11-Inputs!$D$10)/Inputs!$D$18 | G12: =($G$11-Inputs!$D$10)/Inputs!$D$18 | H12: =($H$11-Inputs!$D$10)/Inputs!$D$18
B13: Discount factor | C13: x | D13: =(1+WACC!$D$54)^(-$D$12) | E13: =(1+WACC!$D$54)^(-$E$12) | F13: =(1+WACC!$D$54)^(-$F$12) | G13: =(1+WACC!$D$54)^(-$G$12) | H13: =(1+WACC!$D$54)^(-$H$12)
B14: FCFF | C14: EGP | D14: ='Operating Model'!$E$42 | E14: ='Operating Model'!$F$42 | F14: ='Operating Model'!$G$42 | G14: ='Operating Model'!$H$42 | H14: ='Operating Model'!$I$42 | I14: Operating Model
B15: FCFF included | C15: EGP | D15: =$D$14*$D$10 | E15: =$E$14*$E$10 | F15: =$F$14*$F$10 | G15: =$G$14*$G$10 | H15: =$H$14*$H$10
B16: Present value | C16: EGP | D16: =$D$15*$D$13 | E16: =$E$15*$E$13 | F16: =$F$15*$F$13 | G16: =$G$15*$G$13 | H16: =$H$15*$H$13
B18: Terminal value
D19: Value | I19: Notes
B20: Sum of present values | C20: EGP | D20: =SUM($D$16:$H$16)
B21: Years to final period end | C21: years | D21: =($H$8-Inputs!$D$10)/Inputs!$D$18 | I21: Terminal value discounted from the final period end
B22: Terminal discount factor | C22: x | D22: =(1+WACC!$D$54)^(-$D$21)
B23: Terminal-year FCFF | C23: EGP | D23: ='Operating Model'!$J$42
B24: Gordon terminal value | C24: EGP | D24: =IF(Inputs!$D$172<WACC!$D$54,$D$23/(WACC!$D$54-Inputs!$D$172),"n/a: g ≥ WACC") | I24: FCFF(n+1) / (WACC − g)
B25: PV of Gordon terminal value | C25: EGP | D25: =IFERROR($D$24*$D$22,"n/a")
B26: Final-year EBITDA | C26: EGP | D26: ='Operating Model'!$I$16
B27: Exit-multiple terminal value | C27: EGP | D27: =$D$26*Inputs!$D$173 | I27: EBITDA(n) × exit multiple
B28: PV of exit-multiple terminal value | C28: EGP | D28: =$D$27*$D$22
B29: PV of terminal value used | C29: EGP | D29: =IF(Inputs!$D$171="gordon",$D$25,$D$28) | I29: Method: gordon
B30: Enterprise value | C30: EGP | D30: =$D$20+$D$29
B31: PV of terminal value / EV | C31: % | D31: =$D$29/$D$30
B32: Implied exit multiple from Gordon | C32: x | D32: =IFERROR($D$24/$D$26,"n/a")
B33: Implied growth from exit value | C33: % | D33: =WACC!$D$54-$D$23/$D$27 | I33: WACC − FCFF(n+1) / exit TV
B34: RONIC | C34: % | D34: =IF(ISNUMBER(Inputs!$D$175),Inputs!$D$175,WACC!$D$54)
B35: Reinvestment rate implied by g / RONIC | C35: % | D35: =Inputs!$D$172/$D$34
B36: Terminal-year reinvestment rate in the forecast | C36: % | D36: =('Operating Model'!$J$21-'Operating Model'!$J$20+'Operating Model'!$J$39)/'Operating Model'!$J$26 | I36: (Capex − D&A + change in NWC) / NOPAT
B38: Enterprise value to equity value (balance sheet 2025-12-31)
D39: Value | I39: Notes
B40: Add: cash and cash equivalents | C40: EGP | D40: =Inputs!$E$74 | I40: Balance sheet
B41: Add: FVTPL securities | C41: EGP | D41: =Inputs!$E$69 | I41: Balance sheet
B42: Add: amortized-cost investments (current) | C42: EGP | D42: =Inputs!$E$68 | I42: Balance sheet
B43: Add: amortized-cost investments (non-current) | C43: EGP | D43: =Inputs!$E$62 | I43: Balance sheet
B44: Add: associates | C44: EGP | D44: =IF(ISNUMBER(Inputs!$D$205),Inputs!$D$205,Inputs!$E$61) | I44: Balance sheet
B45: Less: bank debt and bonds | C45: EGP | D45: =-(Inputs!$E$90+Inputs!$E$84+Inputs!$E$85) | I45: Balance sheet
B46: Less: lease liabilities (EAS 49) | C46: EGP | D46: =-(Inputs!$E$91+Inputs!$E$86) | I46: Balance sheet
B47: Less: employee benefit obligations | C47: EGP | D47: =-IF(Inputs!$D$203=1,(Inputs!$E$96+Inputs!$E$88)*IF(Inputs!$D$204=1,1-Inputs!$D$133,1),0) | I47: Balance sheet
B48: Less: minority interest | C48: EGP | D48: =-Inputs!$E$81 | I48: Balance sheet
B49: Less: preferred equity | C49: EGP | D49: =-Inputs!$E$82 | I49: Balance sheet
B50: Memo: restricted / pledged deposits (excluded) | C50: EGP | D50: =Inputs!$E$73+Inputs!$E$63 | I50: Not available to shareholders; not added
B51: Bridge total | C51: EGP | D51: =SUM($D$40:$D$49)
B52: Equity value | C52: EGP | D52: =$D$30+$D$51
B53: Diluted shares | C53: shares | D53: =Inputs!$D$15
B54: DCF value per share | C54: EGP | D54: =$D$52/$D$53
B55: Upside versus price | C55: % | D55: =$D$54/Inputs!$D$11-1
B57: Implied multiples
D58: Value | I58: Notes
B59: EV / normalized EBITDA FY2025A | C59: x | D59: =$D$30/Normalization!$D$16
B60: EV / EBITDA FY2026E | C60: x | D60: =$D$30/'Operating Model'!$E$16
B61: Equity value / net profit FY2025A | C61: x | D61: =$D$52/Inputs!$E$49
B62: Equity value / net profit FY2026E | C62: x | D62: =$D$52/'Operating Model'!$E$40

Sheet USD Check
B2: MOPCO: USD consistency check
B3: EGP cash flows converted at inflation-parity forward rates and discounted at a USD cost of capital. A consistency check of the EGP discount rate, not a second answer.
B4: Blue = hardcoded input | Black = formula
B6: Forward exchange rates
C7: Unit | D7: 2026E | E7: 2027E | F7: 2028E | G7: 2029E | H7: 2030E | I7: Notes
B8: EGP inflation | C8: % | D8: =Inputs!$D$225 | E8: =Inputs!$E$225 | F8: =Inputs!$F$225 | G8: =Inputs!$G$225 | H8: =Inputs!$H$225
B9: USD inflation | C9: % | D9: =Inputs!$D$226 | E9: =Inputs!$E$226 | F9: =Inputs!$F$226 | G9: =Inputs!$G$226 | H9: =Inputs!$H$226
B10: Inflation differential | C10: % | D10: =(1+$D$8)/(1+$D$9)-1 | E10: =(1+$E$8)/(1+$E$9)-1 | F10: =(1+$F$8)/(1+$F$9)-1 | G10: =(1+$G$8)/(1+$G$9)-1 | H10: =(1+$H$8)/(1+$H$9)-1
B11: Forward USD/EGP | C11: EGP/USD | D11: =Inputs!$D$134*(1+$D$8)/(1+$D$9) | E11: =$D$11*(1+$E$8)/(1+$E$9) | F11: =$E$11*(1+$F$8)/(1+$F$9) | G11: =$F$11*(1+$G$8)/(1+$G$9) | H11: =$G$11*(1+$H$8)/(1+$H$9) | I11: S0 × Π (1 + π EGP) / (1 + π USD)
B12: FCFF included, USD | C12: USD | D12: =DCF!$D$10*'Operating Model'!$E$42/$D$11 | E12: =DCF!$E$10*'Operating Model'!$F$42/$E$11 | F12: =DCF!$F$10*'Operating Model'!$G$42/$F$11 | G12: =DCF!$G$10*'Operating Model'!$H$42/$G$11 | H12: =DCF!$H$10*'Operating Model'!$I$42/$H$11
B14: USD cost of capital (method A in USD)
D15: Value | I15: Notes
B16: US 10Y Treasury | C16: % | D16: =Inputs!$D$127
B17: Cost of equity, USD | C17: % | D17: =$D$16+WACC!$D$21*WACC!$D$25+WACC!$D$26+WACC!$D$27 | I17: US 10Y + βL × ERP + CRP + size premium
B18: Cost of debt, USD (pre-tax) | C18: % | D18: =$D$16+WACC!$D$46+WACC!$D$39 | I18: US 10Y + company spread + country default spread
B19: WACC, USD | C19: % | D19: =WACC!$D$52*$D$17+WACC!$D$53*$D$18*(1-WACC!$D$44)
B21: USD valuation
C22: Unit | D22: 2026E | E22: 2027E | F22: 2028E | G22: 2029E | H22: 2030E | I22: Notes
B23: Discount factor, USD | C23: x | D23: =(1+$D$19)^(-DCF!$D$12) | E23: =(1+$D$19)^(-DCF!$E$12) | F23: =(1+$D$19)^(-DCF!$F$12) | G23: =(1+$D$19)^(-DCF!$G$12) | H23: =(1+$D$19)^(-DCF!$H$12)
B24: Present value, USD | C24: USD | D24: =$D$12*$D$23 | E24: =$E$12*$E$23 | F24: =$F$12*$F$23 | G24: =$G$12*$G$23 | H24: =$H$12*$H$23
B26: USD bridge and comparison
D27: Value | I27: Notes
B28: Forward USD/EGP, terminal year | C28: EGP/USD | D28: =$H$11*(1+$H$8)/(1+$H$9)
B29: Terminal growth, USD | C29: % | D29: =(1+Inputs!$D$172)*(1+$H$9)/(1+$H$8)-1 | I29: Same real growth as the EGP terminal growth
B30: Sum of present values, USD | C30: USD | D30: =SUM($D$24:$H$24)
B31: Terminal value, USD | C31: USD | D31: =IF(Inputs!$D$171="gordon",'Operating Model'!$J$42/$D$28/($D$19-$D$29),'Operating Model'!$I$16/$H$11*Inputs!$D$173)
B32: PV of terminal value, USD | C32: USD | D32: =$D$31*(1+$D$19)^(-DCF!$D$21)
B33: Enterprise value, USD | C33: USD | D33: =$D$30+$D$32
B34: Bridge, USD (EGP bridge / spot) | C34: USD | D34: =DCF!$D$51/Inputs!$D$134
B35: Equity value, USD | C35: USD | D35: =$D$33+$D$34
B36: USD equity value converted at spot | C36: EGP | D36: =$D$35*Inputs!$D$134
B37: Equity value, EGP DCF | C37: EGP | D37: =DCF!$D$52
B38: Gap (USD-derived / EGP - 1) | C38: % | D38: =$D$36/$D$37-1
B39: Risk-free differential (EGP Rf - US 10Y) | C39: pp | D39: =WACC!$D$12-$D$16
B40: Average inflation differential | C40: pp | D40: =AVERAGE($D$10:$H$10)
B42: =IF(ABS($D$38)<=Inputs!$D$255,"The USD valuation converted at spot is within "&TEXT(ABS($D$38),"0.0%")&" of the EGP valuation. The EGP discount rate and the inflation path used for forward FX rates are broadly consistent.","The USD valuation converted at spot is "&TEXT(ABS($D$38),"0.0%")&IF($D$38>0," above"," below")&" the EGP valuation. The EGP risk-free rate exceeds the US 10Y by "&SUBSTITUTE(TEXT($D$39,"0.00%"),"%","pp")&", while the forward FX rates assume an average inflation differential of "&SUBSTITUTE(TEXT($D$40,"0.00%"),"%","pp")&"; the EGP discount rate implies "&IF($D$38>0,"more","less")&" depreciation than the inflation path.")

Sheet DDM
B2: MOPCO: Dividend discount model
B3: Shareholder dividends only (employee and board distributions excluded). Two-stage model (headline) and H-model, discounted at the cost of equity.
B4: Blue = hardcoded input | Black = formula
B6: Inputs
D7: Value | I7: Notes
B8: DPS (base year) | C8: EGP | D8: =IF(ISNUMBER(Inputs!$D$217),Inputs!$D$217,-Inputs!$E$112/Inputs!$D$13) | I8: FY2025 dividends paid to shareholders / basic shares
B9: Cost of equity | C9: % | D9: =WACC!$D$30
B10: High-growth rate | C10: % | D10: =Inputs!$D$218
B11: Stable growth | C11: % | D11: =Inputs!$D$220
B12: High-growth years | C12: years | D12: =Inputs!$D$219 | I12: Columns below are laid out for this number of years
B14: Dividends
D15: Year 1 | E15: Year 2 | F15: Year 3 | G15: Year 4 | H15: Year 5 | I15: Notes
B16: Dividend per share | C16: EGP | D16: =$D$8*(1+$D$10) | E16: =$D$16*(1+$D$10) | F16: =$E$16*(1+$D$10) | G16: =$F$16*(1+$D$10) | H16: =$G$16*(1+$D$10)
B17: Discount factor | C17: x | D17: =1/(1+$D$9) | E17: =$D$17/(1+$D$9) | F17: =$E$17/(1+$D$9) | G17: =$F$17/(1+$D$9) | H17: =$G$17/(1+$D$9)
B18: Present value | C18: EGP | D18: =$D$16*$D$17 | E18: =$E$16*$E$17 | F18: =$F$16*$F$17 | G18: =$G$16*$G$17 | H18: =$H$16*$H$17
B20: Value per share
D21: Value | I21: Notes
B22: PV of high-growth dividends | C22: EGP | D22: =SUM($D$18:$H$18)
B23: Terminal value at end of high growth | C23: EGP | D23: =IF($D$9>$D$11,$H$16*(1+$D$11)/($D$9-$D$11),"n/a: Ke ≤ g")
B24: PV of terminal value | C24: EGP | D24: =IFERROR($D$23*$H$17,"n/a")
B25: Two-stage value per share | C25: EGP | D25: =IFERROR($D$22+$D$24,"n/a")
B26: H (half-life of high growth) | C26: years | D26: =$D$12*Inputs!$D$221
B27: H-model value per share | C27: EGP | D27: =IF($D$9>$D$11,$D$8*(1+$D$11)/($D$9-$D$11)+$D$8*$D$26*($D$10-$D$11)/($D$9-$D$11),"n/a")
B29: Sustainability
D30: Value | I30: Notes
B31: ROE (net profit / average equity) | C31: % | D31: =Inputs!$E$49/AVERAGE(Inputs!$D$83,Inputs!$E$83)
B32: Payout (shareholder dividends / net profit) | C32: % | D32: =-Inputs!$E$112/Inputs!$E$49
B33: Sustainable growth (ROE × retention) | C33: % | D33: =$D$31*(1-$D$32)
B34: Stable growth within sustainable growth | C34: check | D34: =$D$11<=$D$33 | I34: FALSE = warning: stable growth exceeds ROE × retention
B35: Payout at or below 100% | C35: check | D35: =$D$32<=1

Sheet Comps Precedents SOTP
B2: MOPCO: Comparables, precedents and SOTP
B3: Multiples computed from the raw peer and transaction inputs on Inputs; implied values use the equity bridge of the DCF sheet. Methods without inputs are excluded from the blend.
B4: Blue = hardcoded input | Black = formula
B6: Trading comparables
B7: No peers entered on Inputs. No multiple is computed and the method is excluded from the blend.
B9: Precedent transactions
B10: No transactions entered on Inputs. The method is excluded from the blend.
B12: Sum of the parts
B13: No segments entered on Inputs. The method is excluded from the blend.
B15: Broker targets (reference only)
B16: No broker targets entered.

Sheet Scenarios
B2: MOPCO: Scenarios
B3: Bear, Base and Bull are explicit driver sets on Inputs; each is a full re-run of the operating model and DCF below. Probabilities must sum to 100%.
B4: Blue = hardcoded input | Black = formula
B6: Scenario summary
D7: Bear | E7: Base | F7: Bull | K7: Notes
B8: Probability | C8: % | D8: =Inputs!$D$209 | E8: =Inputs!$E$209 | F8: =Inputs!$F$209
B9: Revenue growth delta (every year) | C9: pp | D9: =Inputs!$D$210 | E9: =Inputs!$E$210 | F9: =Inputs!$F$210
B10: Gross margin delta | C10: pp | D10: =Inputs!$D$211 | E10: =Inputs!$E$211 | F10: =Inputs!$F$211
B11: WACC delta | C11: pp | D11: =Inputs!$D$212 | E11: =Inputs!$E$212 | F11: =Inputs!$F$212
B12: Terminal growth delta | C12: pp | D12: =Inputs!$D$213 | E12: =Inputs!$E$213 | F12: =Inputs!$F$213
B13: WACC used | C13: % | D13: =Scenarios!$D$27 | E13: =Scenarios!$D$64 | F13: =Scenarios!$D$101
B14: Terminal growth used | C14: % | D14: =Scenarios!$D$28 | E14: =Scenarios!$D$65 | F14: =Scenarios!$D$102
B15: Enterprise value | C15: EGP | D15: =Scenarios!$D$58 | E15: =Scenarios!$D$95 | F15: =Scenarios!$D$132
B16: Equity value | C16: EGP | D16: =Scenarios!$D$59 | E16: =Scenarios!$D$96 | F16: =Scenarios!$D$133
B17: Value per share | C17: EGP | D17: =Scenarios!$D$60 | E17: =Scenarios!$D$97 | F17: =Scenarios!$D$134
B18: Upside versus price | C18: % | D18: =IFERROR(Scenarios!$D$60/Inputs!$D$11-1,"n/a") | E18: =IFERROR(Scenarios!$D$97/Inputs!$D$11-1,"n/a") | F18: =IFERROR(Scenarios!$D$134/Inputs!$D$11-1,"n/a")
B19: Probability sum | C19: % | D19: =SUM($D$8:$F$8)
B20: Probability-weighted value per share | C20: EGP | D20: =SUMPRODUCT($D$8:$F$8,$D$17:$F$17)
B25: Bear case: operating model and DCF
C26: Unit | D26: 2025A | E26: 2026E | F26: 2027E | G26: 2028E | H26: 2029E | I26: 2030E | J26: Terminal | K26: Notes
B27: Bear: WACC used | C27: % | D27: =WACC!$D$54+Inputs!$D$212
B28: Bear: terminal growth used | C28: % | D28: =Inputs!$D$172+Inputs!$D$213
B29: Bear: Revenue | C29: EGP | D29: =Inputs!$E$23 | E29: =$D$29*(1+(Inputs!$D$182+Inputs!$D$210)) | F29: =$E$29*(1+(Inputs!$E$182+Inputs!$D$210)) | G29: =$F$29*(1+(Inputs!$F$182+Inputs!$D$210)) | H29: =$G$29*(1+(Inputs!$G$182+Inputs!$D$210)) | I29: =$H$29*(1+(Inputs!$H$182+Inputs!$D$210)) | J29: =$I$29*(1+(Inputs!$D$172+Inputs!$D$213))
B30: Bear: Gross profit before D&A | C30: EGP | D30: =$D$29*((Inputs!$E$26+Inputs!$E$51+Inputs!$E$52)/$D$29) | E30: =$E$29*(Inputs!$D$183+Inputs!$D$211) | F30: =$F$29*(Inputs!$E$183+Inputs!$D$211) | G30: =$G$29*(Inputs!$F$183+Inputs!$D$211) | H30: =$H$29*(Inputs!$G$183+Inputs!$D$211) | I30: =$I$29*(Inputs!$H$183+Inputs!$D$211) | J30: =$J$29*(Inputs!$I$183+Inputs!$D$211)
B31: Bear: SG&A | C31: EGP | D31: =-(Inputs!$E$29+Inputs!$E$30) | E31: =$E$29*Inputs!$D$184 | F31: =$F$29*Inputs!$E$184 | G31: =$G$29*Inputs!$F$184 | H31: =$H$29*Inputs!$G$184 | I31: =$I$29*Inputs!$H$184 | J31: =$J$29*Inputs!$I$184
B32: Bear: Other operating income (net) | C32: EGP | D32: =Normalization!$D$13-Inputs!$E$26-Inputs!$E$29-Inputs!$E$30 | E32: =$E$29*Inputs!$D$185 | F32: =$F$29*Inputs!$E$185 | G32: =$G$29*Inputs!$F$185 | H32: =$H$29*Inputs!$G$185 | I32: =$I$29*Inputs!$H$185 | J32: =$J$29*Inputs!$I$185
B33: Bear: EBITDA | C33: EGP | D33: =$D$30-$D$31+$D$32 | E33: =$E$30-$E$31+$E$32 | F33: =$F$30-$F$31+$F$32 | G33: =$G$30-$G$31+$G$32 | H33: =$H$30-$H$31+$H$32 | I33: =$I$30-$I$31+$I$32 | J33: =$J$30-$J$31+$J$32
B34: Bear: Opening PP&E | C34: EGP | E34: =Inputs!$E$57 | F34: =$E$39 | G34: =$F$39 | H34: =$G$39 | I34: =$H$39 | J34: =$I$39
B35: Bear: Depreciation | C35: EGP | D35: =Inputs!$E$51 | E35: =IF(Inputs!$D$180="ppe_rollforward",Inputs!$D$187*$E$34,$E$29*Inputs!$D$186) | F35: =IF(Inputs!$D$180="ppe_rollforward",Inputs!$E$187*$F$34,$F$29*Inputs!$E$186) | G35: =IF(Inputs!$D$180="ppe_rollforward",Inputs!$F$187*$G$34,$G$29*Inputs!$F$186) | H35: =IF(Inputs!$D$180="ppe_rollforward",Inputs!$G$187*$H$34,$H$29*Inputs!$G$186) | I35: =IF(Inputs!$D$180="ppe_rollforward",Inputs!$H$187*$I$34,$I$29*Inputs!$H$186) | J35: =IF(Inputs!$D$180="ppe_rollforward",Inputs!$I$187*$J$34,$J$29*Inputs!$I$186)
B36: Bear: Amortization | C36: EGP | D36: =Inputs!$E$52 | E36: =IF(Inputs!$D$180="ppe_rollforward",$E$29*Inputs!$D$188,0) | F36: =IF(Inputs!$D$180="ppe_rollforward",$F$29*Inputs!$E$188,0) | G36: =IF(Inputs!$D$180="ppe_rollforward",$G$29*Inputs!$F$188,0) | H36: =IF(Inputs!$D$180="ppe_rollforward",$H$29*Inputs!$G$188,0) | I36: =IF(Inputs!$D$180="ppe_rollforward",$I$29*Inputs!$H$188,0) | J36: =IF(Inputs!$D$180="ppe_rollforward",$J$29*Inputs!$I$188,0)
B37: Bear: D&A | C37: EGP | D37: =$D$35+$D$36 | E37: =$E$35+$E$36 | F37: =$F$35+$F$36 | G37: =$G$35+$G$36 | H37: =$H$35+$H$36 | I37: =$I$35+$I$36 | J37: =$J$35+$J$36
B38: Bear: Capex | C38: EGP | D38: =-Inputs!$E$111 | E38: =IF(Inputs!$D$181="absolute",Inputs!$D$190,$E$29*Inputs!$D$189) | F38: =IF(Inputs!$D$181="absolute",Inputs!$E$190,$F$29*Inputs!$E$189) | G38: =IF(Inputs!$D$181="absolute",Inputs!$F$190,$G$29*Inputs!$F$189) | H38: =IF(Inputs!$D$181="absolute",Inputs!$G$190,$H$29*Inputs!$G$189) | I38: =IF(Inputs!$D$181="absolute",Inputs!$H$190,$I$29*Inputs!$H$189) | J38: =$J$29*Inputs!$I$189
B39: Bear: Closing PP&E | C39: EGP | D39: =Inputs!$E$57 | E39: =$E$34+$E$38-$E$35 | F39: =$F$34+$F$38-$F$35 | G39: =$G$34+$G$38-$G$35 | H39: =$H$34+$H$38-$H$35 | I39: =$I$34+$I$38-$I$35 | J39: =$J$34+$J$38-$J$35
B40: Bear: EBIT | C40: EGP | D40: =$D$33-$D$37 | E40: =$E$33-$E$37 | F40: =$F$33-$F$37 | G40: =$G$33-$G$37 | H40: =$H$33-$H$37 | I40: =$I$33-$I$37 | J40: =$J$33-$J$37
B41: Bear: Tax rate on EBIT | C41: % | D41: =Inputs!$D$133 | E41: =Inputs!$D$196 | F41: =Inputs!$E$196 | G41: =Inputs!$F$196 | H41: =Inputs!$G$196 | I41: =Inputs!$H$196 | J41: =Inputs!$I$196
B42: Bear: Tax on EBIT | C42: EGP | D42: =$D$40*$D$41 | E42: =$E$40*$E$41 | F42: =$F$40*$F$41 | G42: =$G$40*$G$41 | H42: =$H$40*$H$41 | I42: =$I$40*$I$41 | J42: =$J$40*$J$41
B43: Bear: NOPAT | C43: EGP | D43: =$D$40-$D$42 | E43: =$E$40-$E$42 | F43: =$F$40-$F$42 | G43: =$G$40-$G$42 | H43: =$H$40-$H$42 | I43: =$I$40-$I$42 | J43: =$J$40-$J$42
B44: Bear: Cash cost of sales | C44: EGP | D44: =$D$29*(1-((Inputs!$E$26+Inputs!$E$51+Inputs!$E$52)/$D$29)) | E44: =$E$29*(1-(Inputs!$D$183+Inputs!$D$211)) | F44: =$F$29*(1-(Inputs!$E$183+Inputs!$D$211)) | G44: =$G$29*(1-(Inputs!$F$183+Inputs!$D$211)) | H44: =$H$29*(1-(Inputs!$G$183+Inputs!$D$211)) | I44: =$I$29*(1-(Inputs!$H$183+Inputs!$D$211)) | J44: =$J$29*(1-(Inputs!$I$183+Inputs!$D$211))
B45: Bear: Accounts receivable | C45: EGP | D45: =Inputs!$E$67 | E45: =$E$29*Inputs!$D$191/Inputs!$D$18 | F45: =$F$29*Inputs!$E$191/Inputs!$D$18 | G45: =$G$29*Inputs!$F$191/Inputs!$D$18 | H45: =$H$29*Inputs!$G$191/Inputs!$D$18 | I45: =$I$29*Inputs!$H$191/Inputs!$D$18 | J45: =$J$29*Inputs!$I$191/Inputs!$D$18
B46: Bear: Inventory | C46: EGP | D46: =Inputs!$E$66 | E46: =$E$44*Inputs!$D$192/Inputs!$D$18 | F46: =$F$44*Inputs!$E$192/Inputs!$D$18 | G46: =$G$44*Inputs!$F$192/Inputs!$D$18 | H46: =$H$44*Inputs!$G$192/Inputs!$D$18 | I46: =$I$44*Inputs!$H$192/Inputs!$D$18 | J46: =$J$44*Inputs!$I$192/Inputs!$D$18
B47: Bear: Trade payables | C47: EGP | D47: =Inputs!$E$93 | E47: =$E$44*Inputs!$D$193/Inputs!$D$18 | F47: =$F$44*Inputs!$E$193/Inputs!$D$18 | G47: =$G$44*Inputs!$F$193/Inputs!$D$18 | H47: =$H$44*Inputs!$G$193/Inputs!$D$18 | I47: =$I$44*Inputs!$H$193/Inputs!$D$18 | J47: =$J$44*Inputs!$I$193/Inputs!$D$18
B48: Bear: Other operating current assets | C48: EGP | D48: =Inputs!$E$70+Inputs!$E$72+Inputs!$E$71 | E48: =$E$29*Inputs!$D$194 | F48: =$F$29*Inputs!$E$194 | G48: =$G$29*Inputs!$F$194 | H48: =$H$29*Inputs!$G$194 | I48: =$I$29*Inputs!$H$194 | J48: =$J$29*Inputs!$I$194
B49: Bear: Other operating current liabilities | C49: EGP | D49: =Inputs!$E$94+Inputs!$E$95+Inputs!$E$97+Inputs!$E$98+Inputs!$E$99 | E49: =$E$29*Inputs!$D$195 | F49: =$F$29*Inputs!$E$195 | G49: =$G$29*Inputs!$F$195 | H49: =$H$29*Inputs!$G$195 | I49: =$I$29*Inputs!$H$195 | J49: =$J$29*Inputs!$I$195
B50: Bear: Operating net working capital | C50: EGP | D50: =$D$45+$D$46+$D$48-$D$47-$D$49 | E50: =$E$45+$E$46+$E$48-$E$47-$E$49 | F50: =$F$45+$F$46+$F$48-$F$47-$F$49 | G50: =$G$45+$G$46+$G$48-$G$47-$G$49 | H50: =$H$45+$H$46+$H$48-$H$47-$H$49 | I50: =$I$45+$I$46+$I$48-$I$47-$I$49 | J50: =$J$45+$J$46+$J$48-$J$47-$J$49
B51: Bear: Change in net working capital | C51: EGP | E51: =$E$50-$D$50 | F51: =$F$50-$E$50 | G51: =$G$50-$F$50 | H51: =$H$50-$G$50 | I51: =$I$50-$H$50 | J51: =$J$50-$I$50
B52: Bear: Net profit (forecast: NOPAT + after-tax net finance income) | C52: EGP | D52: =Inputs!$E$49 | E52: =$E$43+Inputs!$D$202*(1-$E$41) | F52: =$F$43+Inputs!$D$202*(1-$F$41) | G52: =$G$43+Inputs!$D$202*(1-$G$41) | H52: =$H$43+Inputs!$D$202*(1-$H$41) | I52: =$I$43+Inputs!$D$202*(1-$I$41) | J52: =$J$43+Inputs!$D$202*(1-$J$41)
B53: Bear: Employee and board distributions | C53: EGP | E53: =IF(Inputs!$D$200=1,Inputs!$D$201*$D$52,0) | F53: =IF(Inputs!$D$200=1,Inputs!$D$201*$E$52,0) | G53: =IF(Inputs!$D$200=1,Inputs!$D$201*$F$52,0) | H53: =IF(Inputs!$D$200=1,Inputs!$D$201*$G$52,0) | I53: =IF(Inputs!$D$200=1,Inputs!$D$201*$H$52,0) | J53: =IF(Inputs!$D$200=1,Inputs!$D$201*$I$52,0)
B54: Bear: Free cash flow to the firm (FCFF) | C54: EGP | E54: =$E$43+$E$37-$E$38-$E$51-$E$53 | F54: =$F$43+$F$37-$F$38-$F$51-$F$53 | G54: =$G$43+$G$37-$G$38-$G$51-$G$53 | H54: =$H$43+$H$37-$H$38-$H$51-$H$53 | I54: =$I$43+$I$37-$I$38-$I$51-$I$53 | J54: =$J$43+$J$37-$J$38-$J$51-$J$53
B55: Bear: Present value of FCFF | C55: EGP | E55: =$E$54*DCF!$D$10*(1+$D$27)^(-DCF!$D$12) | F55: =$F$54*DCF!$E$10*(1+$D$27)^(-DCF!$E$12) | G55: =$G$54*DCF!$F$10*(1+$D$27)^(-DCF!$F$12) | H55: =$H$54*DCF!$G$10*(1+$D$27)^(-DCF!$G$12) | I55: =$I$54*DCF!$H$10*(1+$D$27)^(-DCF!$H$12)
B56: Bear: Sum of present values | C56: EGP | D56: =SUM($E$55:$I$55)
B57: Bear: Terminal value | C57: EGP | D57: =IF(Inputs!$D$171="gordon",IF($D$28<$D$27,$J$54/($D$27-$D$28),"n/a"),$I$33*Inputs!$D$173)
B58: Bear: Enterprise value | C58: EGP | D58: =IFERROR($D$56+$D$57*(1+$D$27)^(-DCF!$D$21),"n/a")
B59: Bear: Equity value | C59: EGP | D59: =IFERROR($D$58+DCF!$D$51,"n/a")
B60: Bear: Value per share | C60: EGP | D60: =IFERROR($D$59/Inputs!$D$15,"n/a")
B62: Base case: operating model and DCF
C63: Unit | D63: 2025A | E63: 2026E | F63: 2027E | G63: 2028E | H63: 2029E | I63: 2030E | J63: Terminal | K63: Notes
B64: Base: WACC used | C64: % | D64: =WACC!$D$54+Inputs!$E$212
B65: Base: terminal growth used | C65: % | D65: =Inputs!$D$172+Inputs!$E$213
B66: Base: Revenue | C66: EGP | D66: =Inputs!$E$23 | E66: =$D$66*(1+(Inputs!$D$182+Inputs!$E$210)) | F66: =$E$66*(1+(Inputs!$E$182+Inputs!$E$210)) | G66: =$F$66*(1+(Inputs!$F$182+Inputs!$E$210)) | H66: =$G$66*(1+(Inputs!$G$182+Inputs!$E$210)) | I66: =$H$66*(1+(Inputs!$H$182+Inputs!$E$210)) | J66: =$I$66*(1+(Inputs!$D$172+Inputs!$E$213))
B67: Base: Gross profit before D&A | C67: EGP | D67: =$D$66*((Inputs!$E$26+Inputs!$E$51+Inputs!$E$52)/$D$66) | E67: =$E$66*(Inputs!$D$183+Inputs!$E$211) | F67: =$F$66*(Inputs!$E$183+Inputs!$E$211) | G67: =$G$66*(Inputs!$F$183+Inputs!$E$211) | H67: =$H$66*(Inputs!$G$183+Inputs!$E$211) | I67: =$I$66*(Inputs!$H$183+Inputs!$E$211) | J67: =$J$66*(Inputs!$I$183+Inputs!$E$211)
B68: Base: SG&A | C68: EGP | D68: =-(Inputs!$E$29+Inputs!$E$30) | E68: =$E$66*Inputs!$D$184 | F68: =$F$66*Inputs!$E$184 | G68: =$G$66*Inputs!$F$184 | H68: =$H$66*Inputs!$G$184 | I68: =$I$66*Inputs!$H$184 | J68: =$J$66*Inputs!$I$184
B69: Base: Other operating income (net) | C69: EGP | D69: =Normalization!$D$13-Inputs!$E$26-Inputs!$E$29-Inputs!$E$30 | E69: =$E$66*Inputs!$D$185 | F69: =$F$66*Inputs!$E$185 | G69: =$G$66*Inputs!$F$185 | H69: =$H$66*Inputs!$G$185 | I69: =$I$66*Inputs!$H$185 | J69: =$J$66*Inputs!$I$185
B70: Base: EBITDA | C70: EGP | D70: =$D$67-$D$68+$D$69 | E70: =$E$67-$E$68+$E$69 | F70: =$F$67-$F$68+$F$69 | G70: =$G$67-$G$68+$G$69 | H70: =$H$67-$H$68+$H$69 | I70: =$I$67-$I$68+$I$69 | J70: =$J$67-$J$68+$J$69
B71: Base: Opening PP&E | C71: EGP | E71: =Inputs!$E$57 | F71: =$E$76 | G71: =$F$76 | H71: =$G$76 | I71: =$H$76 | J71: =$I$76
B72: Base: Depreciation | C72: EGP | D72: =Inputs!$E$51 | E72: =IF(Inputs!$D$180="ppe_rollforward",Inputs!$D$187*$E$71,$E$66*Inputs!$D$186) | F72: =IF(Inputs!$D$180="ppe_rollforward",Inputs!$E$187*$F$71,$F$66*Inputs!$E$186) | G72: =IF(Inputs!$D$180="ppe_rollforward",Inputs!$F$187*$G$71,$G$66*Inputs!$F$186) | H72: =IF(Inputs!$D$180="ppe_rollforward",Inputs!$G$187*$H$71,$H$66*Inputs!$G$186) | I72: =IF(Inputs!$D$180="ppe_rollforward",Inputs!$H$187*$I$71,$I$66*Inputs!$H$186) | J72: =IF(Inputs!$D$180="ppe_rollforward",Inputs!$I$187*$J$71,$J$66*Inputs!$I$186)
B73: Base: Amortization | C73: EGP | D73: =Inputs!$E$52 | E73: =IF(Inputs!$D$180="ppe_rollforward",$E$66*Inputs!$D$188,0) | F73: =IF(Inputs!$D$180="ppe_rollforward",$F$66*Inputs!$E$188,0) | G73: =IF(Inputs!$D$180="ppe_rollforward",$G$66*Inputs!$F$188,0) | H73: =IF(Inputs!$D$180="ppe_rollforward",$H$66*Inputs!$G$188,0) | I73: =IF(Inputs!$D$180="ppe_rollforward",$I$66*Inputs!$H$188,0) | J73: =IF(Inputs!$D$180="ppe_rollforward",$J$66*Inputs!$I$188,0)
B74: Base: D&A | C74: EGP | D74: =$D$72+$D$73 | E74: =$E$72+$E$73 | F74: =$F$72+$F$73 | G74: =$G$72+$G$73 | H74: =$H$72+$H$73 | I74: =$I$72+$I$73 | J74: =$J$72+$J$73
B75: Base: Capex | C75: EGP | D75: =-Inputs!$E$111 | E75: =IF(Inputs!$D$181="absolute",Inputs!$D$190,$E$66*Inputs!$D$189) | F75: =IF(Inputs!$D$181="absolute",Inputs!$E$190,$F$66*Inputs!$E$189) | G75: =IF(Inputs!$D$181="absolute",Inputs!$F$190,$G$66*Inputs!$F$189) | H75: =IF(Inputs!$D$181="absolute",Inputs!$G$190,$H$66*Inputs!$G$189) | I75: =IF(Inputs!$D$181="absolute",Inputs!$H$190,$I$66*Inputs!$H$189) | J75: =$J$66*Inputs!$I$189
B76: Base: Closing PP&E | C76: EGP | D76: =Inputs!$E$57 | E76: =$E$71+$E$75-$E$72 | F76: =$F$71+$F$75-$F$72 | G76: =$G$71+$G$75-$G$72 | H76: =$H$71+$H$75-$H$72 | I76: =$I$71+$I$75-$I$72 | J76: =$J$71+$J$75-$J$72
B77: Base: EBIT | C77: EGP | D77: =$D$70-$D$74 | E77: =$E$70-$E$74 | F77: =$F$70-$F$74 | G77: =$G$70-$G$74 | H77: =$H$70-$H$74 | I77: =$I$70-$I$74 | J77: =$J$70-$J$74
B78: Base: Tax rate on EBIT | C78: % | D78: =Inputs!$D$133 | E78: =Inputs!$D$196 | F78: =Inputs!$E$196 | G78: =Inputs!$F$196 | H78: =Inputs!$G$196 | I78: =Inputs!$H$196 | J78: =Inputs!$I$196
B79: Base: Tax on EBIT | C79: EGP | D79: =$D$77*$D$78 | E79: =$E$77*$E$78 | F79: =$F$77*$F$78 | G79: =$G$77*$G$78 | H79: =$H$77*$H$78 | I79: =$I$77*$I$78 | J79: =$J$77*$J$78
B80: Base: NOPAT | C80: EGP | D80: =$D$77-$D$79 | E80: =$E$77-$E$79 | F80: =$F$77-$F$79 | G80: =$G$77-$G$79 | H80: =$H$77-$H$79 | I80: =$I$77-$I$79 | J80: =$J$77-$J$79
B81: Base: Cash cost of sales | C81: EGP | D81: =$D$66*(1-((Inputs!$E$26+Inputs!$E$51+Inputs!$E$52)/$D$66)) | E81: =$E$66*(1-(Inputs!$D$183+Inputs!$E$211)) | F81: =$F$66*(1-(Inputs!$E$183+Inputs!$E$211)) | G81: =$G$66*(1-(Inputs!$F$183+Inputs!$E$211)) | H81: =$H$66*(1-(Inputs!$G$183+Inputs!$E$211)) | I81: =$I$66*(1-(Inputs!$H$183+Inputs!$E$211)) | J81: =$J$66*(1-(Inputs!$I$183+Inputs!$E$211))
B82: Base: Accounts receivable | C82: EGP | D82: =Inputs!$E$67 | E82: =$E$66*Inputs!$D$191/Inputs!$D$18 | F82: =$F$66*Inputs!$E$191/Inputs!$D$18 | G82: =$G$66*Inputs!$F$191/Inputs!$D$18 | H82: =$H$66*Inputs!$G$191/Inputs!$D$18 | I82: =$I$66*Inputs!$H$191/Inputs!$D$18 | J82: =$J$66*Inputs!$I$191/Inputs!$D$18
B83: Base: Inventory | C83: EGP | D83: =Inputs!$E$66 | E83: =$E$81*Inputs!$D$192/Inputs!$D$18 | F83: =$F$81*Inputs!$E$192/Inputs!$D$18 | G83: =$G$81*Inputs!$F$192/Inputs!$D$18 | H83: =$H$81*Inputs!$G$192/Inputs!$D$18 | I83: =$I$81*Inputs!$H$192/Inputs!$D$18 | J83: =$J$81*Inputs!$I$192/Inputs!$D$18
B84: Base: Trade payables | C84: EGP | D84: =Inputs!$E$93 | E84: =$E$81*Inputs!$D$193/Inputs!$D$18 | F84: =$F$81*Inputs!$E$193/Inputs!$D$18 | G84: =$G$81*Inputs!$F$193/Inputs!$D$18 | H84: =$H$81*Inputs!$G$193/Inputs!$D$18 | I84: =$I$81*Inputs!$H$193/Inputs!$D$18 | J84: =$J$81*Inputs!$I$193/Inputs!$D$18
B85: Base: Other operating current assets | C85: EGP | D85: =Inputs!$E$70+Inputs!$E$72+Inputs!$E$71 | E85: =$E$66*Inputs!$D$194 | F85: =$F$66*Inputs!$E$194 | G85: =$G$66*Inputs!$F$194 | H85: =$H$66*Inputs!$G$194 | I85: =$I$66*Inputs!$H$194 | J85: =$J$66*Inputs!$I$194
B86: Base: Other operating current liabilities | C86: EGP | D86: =Inputs!$E$94+Inputs!$E$95+Inputs!$E$97+Inputs!$E$98+Inputs!$E$99 | E86: =$E$66*Inputs!$D$195 | F86: =$F$66*Inputs!$E$195 | G86: =$G$66*Inputs!$F$195 | H86: =$H$66*Inputs!$G$195 | I86: =$I$66*Inputs!$H$195 | J86: =$J$66*Inputs!$I$195
B87: Base: Operating net working capital | C87: EGP | D87: =$D$82+$D$83+$D$85-$D$84-$D$86 | E87: =$E$82+$E$83+$E$85-$E$84-$E$86 | F87: =$F$82+$F$83+$F$85-$F$84-$F$86 | G87: =$G$82+$G$83+$G$85-$G$84-$G$86 | H87: =$H$82+$H$83+$H$85-$H$84-$H$86 | I87: =$I$82+$I$83+$I$85-$I$84-$I$86 | J87: =$J$82+$J$83+$J$85-$J$84-$J$86
B88: Base: Change in net working capital | C88: EGP | E88: =$E$87-$D$87 | F88: =$F$87-$E$87 | G88: =$G$87-$F$87 | H88: =$H$87-$G$87 | I88: =$I$87-$H$87 | J88: =$J$87-$I$87
B89: Base: Net profit (forecast: NOPAT + after-tax net finance income) | C89: EGP | D89: =Inputs!$E$49 | E89: =$E$80+Inputs!$D$202*(1-$E$78) | F89: =$F$80+Inputs!$D$202*(1-$F$78) | G89: =$G$80+Inputs!$D$202*(1-$G$78) | H89: =$H$80+Inputs!$D$202*(1-$H$78) | I89: =$I$80+Inputs!$D$202*(1-$I$78) | J89: =$J$80+Inputs!$D$202*(1-$J$78)
B90: Base: Employee and board distributions | C90: EGP | E90: =IF(Inputs!$D$200=1,Inputs!$D$201*$D$89,0) | F90: =IF(Inputs!$D$200=1,Inputs!$D$201*$E$89,0) | G90: =IF(Inputs!$D$200=1,Inputs!$D$201*$F$89,0) | H90: =IF(Inputs!$D$200=1,Inputs!$D$201*$G$89,0) | I90: =IF(Inputs!$D$200=1,Inputs!$D$201*$H$89,0) | J90: =IF(Inputs!$D$200=1,Inputs!$D$201*$I$89,0)
B91: Base: Free cash flow to the firm (FCFF) | C91: EGP | E91: =$E$80+$E$74-$E$75-$E$88-$E$90 | F91: =$F$80+$F$74-$F$75-$F$88-$F$90 | G91: =$G$80+$G$74-$G$75-$G$88-$G$90 | H91: =$H$80+$H$74-$H$75-$H$88-$H$90 | I91: =$I$80+$I$74-$I$75-$I$88-$I$90 | J91: =$J$80+$J$74-$J$75-$J$88-$J$90
B92: Base: Present value of FCFF | C92: EGP | E92: =$E$91*DCF!$D$10*(1+$D$64)^(-DCF!$D$12) | F92: =$F$91*DCF!$E$10*(1+$D$64)^(-DCF!$E$12) | G92: =$G$91*DCF!$F$10*(1+$D$64)^(-DCF!$F$12) | H92: =$H$91*DCF!$G$10*(1+$D$64)^(-DCF!$G$12) | I92: =$I$91*DCF!$H$10*(1+$D$64)^(-DCF!$H$12)
B93: Base: Sum of present values | C93: EGP | D93: =SUM($E$92:$I$92)
B94: Base: Terminal value | C94: EGP | D94: =IF(Inputs!$D$171="gordon",IF($D$65<$D$64,$J$91/($D$64-$D$65),"n/a"),$I$70*Inputs!$D$173)
B95: Base: Enterprise value | C95: EGP | D95: =IFERROR($D$93+$D$94*(1+$D$64)^(-DCF!$D$21),"n/a")
B96: Base: Equity value | C96: EGP | D96: =IFERROR($D$95+DCF!$D$51,"n/a")
B97: Base: Value per share | C97: EGP | D97: =IFERROR($D$96/Inputs!$D$15,"n/a")
B99: Bull case: operating model and DCF
C100: Unit | D100: 2025A | E100: 2026E | F100: 2027E | G100: 2028E | H100: 2029E | I100: 2030E | J100: Terminal | K100: Notes
B101: Bull: WACC used | C101: % | D101: =WACC!$D$54+Inputs!$F$212
B102: Bull: terminal growth used | C102: % | D102: =Inputs!$D$172+Inputs!$F$213
B103: Bull: Revenue | C103: EGP | D103: =Inputs!$E$23 | E103: =$D$103*(1+(Inputs!$D$182+Inputs!$F$210)) | F103: =$E$103*(1+(Inputs!$E$182+Inputs!$F$210)) | G103: =$F$103*(1+(Inputs!$F$182+Inputs!$F$210)) | H103: =$G$103*(1+(Inputs!$G$182+Inputs!$F$210)) | I103: =$H$103*(1+(Inputs!$H$182+Inputs!$F$210)) | J103: =$I$103*(1+(Inputs!$D$172+Inputs!$F$213))
B104: Bull: Gross profit before D&A | C104: EGP | D104: =$D$103*((Inputs!$E$26+Inputs!$E$51+Inputs!$E$52)/$D$103) | E104: =$E$103*(Inputs!$D$183+Inputs!$F$211) | F104: =$F$103*(Inputs!$E$183+Inputs!$F$211) | G104: =$G$103*(Inputs!$F$183+Inputs!$F$211) | H104: =$H$103*(Inputs!$G$183+Inputs!$F$211) | I104: =$I$103*(Inputs!$H$183+Inputs!$F$211) | J104: =$J$103*(Inputs!$I$183+Inputs!$F$211)
B105: Bull: SG&A | C105: EGP | D105: =-(Inputs!$E$29+Inputs!$E$30) | E105: =$E$103*Inputs!$D$184 | F105: =$F$103*Inputs!$E$184 | G105: =$G$103*Inputs!$F$184 | H105: =$H$103*Inputs!$G$184 | I105: =$I$103*Inputs!$H$184 | J105: =$J$103*Inputs!$I$184
B106: Bull: Other operating income (net) | C106: EGP | D106: =Normalization!$D$13-Inputs!$E$26-Inputs!$E$29-Inputs!$E$30 | E106: =$E$103*Inputs!$D$185 | F106: =$F$103*Inputs!$E$185 | G106: =$G$103*Inputs!$F$185 | H106: =$H$103*Inputs!$G$185 | I106: =$I$103*Inputs!$H$185 | J106: =$J$103*Inputs!$I$185
B107: Bull: EBITDA | C107: EGP | D107: =$D$104-$D$105+$D$106 | E107: =$E$104-$E$105+$E$106 | F107: =$F$104-$F$105+$F$106 | G107: =$G$104-$G$105+$G$106 | H107: =$H$104-$H$105+$H$106 | I107: =$I$104-$I$105+$I$106 | J107: =$J$104-$J$105+$J$106
B108: Bull: Opening PP&E | C108: EGP | E108: =Inputs!$E$57 | F108: =$E$113 | G108: =$F$113 | H108: =$G$113 | I108: =$H$113 | J108: =$I$113
...

Sheet Sensitivity
B2: MOPCO: Sensitivity
B3: Value per share, 5 × 5 grids with the base case at the centre. Each cell is a full re-run in formulas: grids 1, 2 and 4 re-discount the model cash flows; grid 3 uses one mini operating model per cell (below).
B4: Blue = hardcoded input | Black = formula
B6: Grid 1 support: terminal-year FCFF by terminal growth
D7: g − 2 steps | E7: g − 1 step | F7: Base | G7: g + 1 step | H7: g + 2 steps | K7: Notes
B8: Terminal growth | C8: % | D8: =Inputs!$D$172+Inputs!$D$237*Inputs!$D$231 | E8: =Inputs!$D$172+Inputs!$E$237*Inputs!$D$231 | F8: =Inputs!$D$172+Inputs!$F$237*Inputs!$D$231 | G8: =Inputs!$D$172+Inputs!$G$237*Inputs!$D$231 | H8: =Inputs!$D$172+Inputs!$H$237*Inputs!$D$231
B9: Terminal-year revenue | C9: EGP | D9: ='Operating Model'!$I$9*(1+$D$8) | E9: ='Operating Model'!$I$9*(1+$E$8) | F9: ='Operating Model'!$I$9*(1+$F$8) | G9: ='Operating Model'!$I$9*(1+$G$8) | H9: ='Operating Model'!$I$9*(1+$H$8)
B10: EBITDA | C10: EGP | D10: =$D$9*(Inputs!$I$183-Inputs!$I$184+Inputs!$I$185) | E10: =$E$9*(Inputs!$I$183-Inputs!$I$184+Inputs!$I$185) | F10: =$F$9*(Inputs!$I$183-Inputs!$I$184+Inputs!$I$185) | G10: =$G$9*(Inputs!$I$183-Inputs!$I$184+Inputs!$I$185) | H10: =$H$9*(Inputs!$I$183-Inputs!$I$184+Inputs!$I$185)
B11: Depreciation | C11: EGP | D11: =IF(Inputs!$D$180="ppe_rollforward",Inputs!$I$187*'Operating Model'!$I$22,$D$9*Inputs!$I$186) | E11: =IF(Inputs!$D$180="ppe_rollforward",Inputs!$I$187*'Operating Model'!$I$22,$E$9*Inputs!$I$186) | F11: =IF(Inputs!$D$180="ppe_rollforward",Inputs!$I$187*'Operating Model'!$I$22,$F$9*Inputs!$I$186) | G11: =IF(Inputs!$D$180="ppe_rollforward",Inputs!$I$187*'Operating Model'!$I$22,$G$9*Inputs!$I$186) | H11: =IF(Inputs!$D$180="ppe_rollforward",Inputs!$I$187*'Operating Model'!$I$22,$H$9*Inputs!$I$186)
B12: Amortization | C12: EGP | D12: =IF(Inputs!$D$180="ppe_rollforward",$D$9*Inputs!$I$188,0) | E12: =IF(Inputs!$D$180="ppe_rollforward",$E$9*Inputs!$I$188,0) | F12: =IF(Inputs!$D$180="ppe_rollforward",$F$9*Inputs!$I$188,0) | G12: =IF(Inputs!$D$180="ppe_rollforward",$G$9*Inputs!$I$188,0) | H12: =IF(Inputs!$D$180="ppe_rollforward",$H$9*Inputs!$I$188,0)
B13: Capex | C13: EGP | D13: =$D$9*Inputs!$I$189 | E13: =$E$9*Inputs!$I$189 | F13: =$F$9*Inputs!$I$189 | G13: =$G$9*Inputs!$I$189 | H13: =$H$9*Inputs!$I$189
B14: NOPAT | C14: EGP | D14: =($D$10-$D$11-$D$12)*(1-Inputs!$I$196) | E14: =($E$10-$E$11-$E$12)*(1-Inputs!$I$196) | F14: =($F$10-$F$11-$F$12)*(1-Inputs!$I$196) | G14: =($G$10-$G$11-$G$12)*(1-Inputs!$I$196) | H14: =($H$10-$H$11-$H$12)*(1-Inputs!$I$196)
B15: Operating net working capital | C15: EGP | D15: =$D$9*Inputs!$I$191/Inputs!$D$18+$D$9*(1-Inputs!$I$183)*Inputs!$I$192/Inputs!$D$18+$D$9*Inputs!$I$194-$D$9*(1-Inputs!$I$183)*Inputs!$I$193/Inputs!$D$18-$D$9*Inputs!$I$195 | E15: =$E$9*Inputs!$I$191/Inputs!$D$18+$E$9*(1-Inputs!$I$183)*Inputs!$I$192/Inputs!$D$18+$E$9*Inputs!$I$194-$E$9*(1-Inputs!$I$183)*Inputs!$I$193/Inputs!$D$18-$E$9*Inputs!$I$195 | F15: =$F$9*Inputs!$I$191/Inputs!$D$18+$F$9*(1-Inputs!$I$183)*Inputs!$I$192/Inputs!$D$18+$F$9*Inputs!$I$194-$F$9*(1-Inputs!$I$183)*Inputs!$I$193/Inputs!$D$18-$F$9*Inputs!$I$195 | G15: =$G$9*Inputs!$I$191/Inputs!$D$18+$G$9*(1-Inputs!$I$183)*Inputs!$I$192/Inputs!$D$18+$G$9*Inputs!$I$194-$G$9*(1-Inputs!$I$183)*Inputs!$I$193/Inputs!$D$18-$G$9*Inputs!$I$195 | H15: =$H$9*Inputs!$I$191/Inputs!$D$18+$H$9*(1-Inputs!$I$183)*Inputs!$I$192/Inputs!$D$18+$H$9*Inputs!$I$194-$H$9*(1-Inputs!$I$183)*Inputs!$I$193/Inputs!$D$18-$H$9*Inputs!$I$195
B16: Distributions | C16: EGP | D16: =IF(Inputs!$D$200=1,Inputs!$D$201*'Operating Model'!$I$40,0) | E16: =IF(Inputs!$D$200=1,Inputs!$D$201*'Operating Model'!$I$40,0) | F16: =IF(Inputs!$D$200=1,Inputs!$D$201*'Operating Model'!$I$40,0) | G16: =IF(Inputs!$D$200=1,Inputs!$D$201*'Operating Model'!$I$40,0) | H16: =IF(Inputs!$D$200=1,Inputs!$D$201*'Operating Model'!$I$40,0)
B17: Terminal-year FCFF | C17: EGP | D17: =$D$14+$D$11+$D$12-$D$13-($D$15-'Operating Model'!$I$38)-$D$16 | E17: =$E$14+$E$11+$E$12-$E$13-($E$15-'Operating Model'!$I$38)-$E$16 | F17: =$F$14+$F$11+$F$12-$F$13-($F$15-'Operating Model'!$I$38)-$F$16 | G17: =$G$14+$G$11+$G$12-$G$13-($G$15-'Operating Model'!$I$38)-$G$16 | H17: =$H$14+$H$11+$H$12-$H$13-($H$15-'Operating Model'!$I$38)-$H$16
B19: Grid 1: WACC × terminal growth (Gordon)
C20: WACC / Terminal growth | D20: =$D$8 | E20: =$E$8 | F20: =$F$8 | G20: =$G$8 | H20: =$H$8 | K20: Notes
C21: =WACC!$D$54+Inputs!$D$237*Inputs!$D$230 | D21: =IF($D$20<$C$21,(SUMPRODUCT(DCF!$D$15:$H$15,(1+$C$21)^(-DCF!$D$12:$H$12))+$D$17/($C$21-$D$20)*(1+$C$21)^(-DCF!$D$21)+DCF!$D$51)/Inputs!$D$15,"n/a") | E21: =IF($E$20<$C$21,(SUMPRODUCT(DCF!$D$15:$H$15,(1+$C$21)^(-DCF!$D$12:$H$12))+$E$17/($C$21-$E$20)*(1+$C$21)^(-DCF!$D$21)+DCF!$D$51)/Inputs!$D$15,"n/a") | F21: =IF($F$20<$C$21,(SUMPRODUCT(DCF!$D$15:$H$15,(1+$C$21)^(-DCF!$D$12:$H$12))+$F$17/($C$21-$F$20)*(1+$C$21)^(-DCF!$D$21)+DCF!$D$51)/Inputs!$D$15,"n/a") | G21: =IF($G$20<$C$21,(SUMPRODUCT(DCF!$D$15:$H$15,(1+$C$21)^(-DCF!$D$12:$H$12))+$G$17/($C$21-$G$20)*(1+$C$21)^(-DCF!$D$21)+DCF!$D$51)/Inputs!$D$15,"n/a") | H21: =IF($H$20<$C$21,(SUMPRODUCT(DCF!$D$15:$H$15,(1+$C$21)^(-DCF!$D$12:$H$12))+$H$17/($C$21-$H$20)*(1+$C$21)^(-DCF!$D$21)+DCF!$D$51)/Inputs!$D$15,"n/a")
C22: =WACC!$D$54+Inputs!$E$237*Inputs!$D$230 | D22: =IF($D$20<$C$22,(SUMPRODUCT(DCF!$D$15:$H$15,(1+$C$22)^(-DCF!$D$12:$H$12))+$D$17/($C$22-$D$20)*(1+$C$22)^(-DCF!$D$21)+DCF!$D$51)/Inputs!$D$15,"n/a") | E22: =IF($E$20<$C$22,(SUMPRODUCT(DCF!$D$15:$H$15,(1+$C$22)^(-DCF!$D$12:$H$12))+$E$17/($C$22-$E$20)*(1+$C$22)^(-DCF!$D$21)+DCF!$D$51)/Inputs!$D$15,"n/a") | F22: =IF($F$20<$C$22,(SUMPRODUCT(DCF!$D$15:$H$15,(1+$C$22)^(-DCF!$D$12:$H$12))+$F$17/($C$22-$F$20)*(1+$C$22)^(-DCF!$D$21)+DCF!$D$51)/Inputs!$D$15,"n/a") | G22: =IF($G$20<$C$22,(SUMPRODUCT(DCF!$D$15:$H$15,(1+$C$22)^(-DCF!$D$12:$H$12))+$G$17/($C$22-$G$20)*(1+$C$22)^(-DCF!$D$21)+DCF!$D$51)/Inputs!$D$15,"n/a") | H22: =IF($H$20<$C$22,(SUMPRODUCT(DCF!$D$15:$H$15,(1+$C$22)^(-DCF!$D$12:$H$12))+$H$17/($C$22-$H$20)*(1+$C$22)^(-DCF!$D$21)+DCF!$D$51)/Inputs!$D$15,"n/a")
C23: =WACC!$D$54+Inputs!$F$237*Inputs!$D$230 | D23: =IF($D$20<$C$23,(SUMPRODUCT(DCF!$D$15:$H$15,(1+$C$23)^(-DCF!$D$12:$H$12))+$D$17/($C$23-$D$20)*(1+$C$23)^(-DCF!$D$21)+DCF!$D$51)/Inputs!$D$15,"n/a") | E23: =IF($E$20<$C$23,(SUMPRODUCT(DCF!$D$15:$H$15,(1+$C$23)^(-DCF!$D$12:$H$12))+$E$17/($C$23-$E$20)*(1+$C$23)^(-DCF!$D$21)+DCF!$D$51)/Inputs!$D$15,"n/a") | F23: =IF($F$20<$C$23,(SUMPRODUCT(DCF!$D$15:$H$15,(1+$C$23)^(-DCF!$D$12:$H$12))+$F$17/($C$23-$F$20)*(1+$C$23)^(-DCF!$D$21)+DCF!$D$51)/Inputs!$D$15,"n/a") | G23: =IF($G$20<$C$23,(SUMPRODUCT(DCF!$D$15:$H$15,(1+$C$23)^(-DCF!$D$12:$H$12))+$G$17/($C$23-$G$20)*(1+$C$23)^(-DCF!$D$21)+DCF!$D$51)/Inputs!$D$15,"n/a") | H23: =IF($H$20<$C$23,(SUMPRODUCT(DCF!$D$15:$H$15,(1+$C$23)^(-DCF!$D$12:$H$12))+$H$17/($C$23-$H$20)*(1+$C$23)^(-DCF!$D$21)+DCF!$D$51)/Inputs!$D$15,"n/a")
C24: =WACC!$D$54+Inputs!$G$237*Inputs!$D$230 | D24: =IF($D$20<$C$24,(SUMPRODUCT(DCF!$D$15:$H$15,(1+$C$24)^(-DCF!$D$12:$H$12))+$D$17/($C$24-$D$20)*(1+$C$24)^(-DCF!$D$21)+DCF!$D$51)/Inputs!$D$15,"n/a") | E24: =IF($E$20<$C$24,(SUMPRODUCT(DCF!$D$15:$H$15,(1+$C$24)^(-DCF!$D$12:$H$12))+$E$17/($C$24-$E$20)*(1+$C$24)^(-DCF!$D$21)+DCF!$D$51)/Inputs!$D$15,"n/a") | F24: =IF($F$20<$C$24,(SUMPRODUCT(DCF!$D$15:$H$15,(1+$C$24)^(-DCF!$D$12:$H$12))+$F$17/($C$24-$F$20)*(1+$C$24)^(-DCF!$D$21)+DCF!$D$51)/Inputs!$D$15,"n/a") | G24: =IF($G$20<$C$24,(SUMPRODUCT(DCF!$D$15:$H$15,(1+$C$24)^(-DCF!$D$12:$H$12))+$G$17/($C$24-$G$20)*(1+$C$24)^(-DCF!$D$21)+DCF!$D$51)/Inputs!$D$15,"n/a") | H24: =IF($H$20<$C$24,(SUMPRODUCT(DCF!$D$15:$H$15,(1+$C$24)^(-DCF!$D$12:$H$12))+$H$17/($C$24-$H$20)*(1+$C$24)^(-DCF!$D$21)+DCF!$D$51)/Inputs!$D$15,"n/a")
C25: =WACC!$D$54+Inputs!$H$237*Inputs!$D$230 | D25: =IF($D$20<$C$25,(SUMPRODUCT(DCF!$D$15:$H$15,(1+$C$25)^(-DCF!$D$12:$H$12))+$D$17/($C$25-$D$20)*(1+$C$25)^(-DCF!$D$21)+DCF!$D$51)/Inputs!$D$15,"n/a") | E25: =IF($E$20<$C$25,(SUMPRODUCT(DCF!$D$15:$H$15,(1+$C$25)^(-DCF!$D$12:$H$12))+$E$17/($C$25-$E$20)*(1+$C$25)^(-DCF!$D$21)+DCF!$D$51)/Inputs!$D$15,"n/a") | F25: =IF($F$20<$C$25,(SUMPRODUCT(DCF!$D$15:$H$15,(1+$C$25)^(-DCF!$D$12:$H$12))+$F$17/($C$25-$F$20)*(1+$C$25)^(-DCF!$D$21)+DCF!$D$51)/Inputs!$D$15,"n/a") | G25: =IF($G$20<$C$25,(SUMPRODUCT(DCF!$D$15:$H$15,(1+$C$25)^(-DCF!$D$12:$H$12))+$G$17/($C$25-$G$20)*(1+$C$25)^(-DCF!$D$21)+DCF!$D$51)/Inputs!$D$15,"n/a") | H25: =IF($H$20<$C$25,(SUMPRODUCT(DCF!$D$15:$H$15,(1+$C$25)^(-DCF!$D$12:$H$12))+$H$17/($C$25-$H$20)*(1+$C$25)^(-DCF!$D$21)+DCF!$D$51)/Inputs!$D$15,"n/a")
B27: Grid 2: WACC × exit multiple
C28: WACC / Exit EV/EBITDA | D28: =Inputs!$D$173+Inputs!$D$237*Inputs!$D$232 | E28: =Inputs!$D$173+Inputs!$E$237*Inputs!$D$232 | F28: =Inputs!$D$173+Inputs!$F$237*Inputs!$D$232 | G28: =Inputs!$D$173+Inputs!$G$237*Inputs!$D$232 | H28: =Inputs!$D$173+Inputs!$H$237*Inputs!$D$232 | K28: Notes
C29: =WACC!$D$54+Inputs!$D$237*Inputs!$D$230 | D29: =(SUMPRODUCT(DCF!$D$15:$H$15,(1+$C$29)^(-DCF!$D$12:$H$12))+'Operating Model'!$I$16*$D$28*(1+$C$29)^(-DCF!$D$21)+DCF!$D$51)/Inputs!$D$15 | E29: =(SUMPRODUCT(DCF!$D$15:$H$15,(1+$C$29)^(-DCF!$D$12:$H$12))+'Operating Model'!$I$16*$E$28*(1+$C$29)^(-DCF!$D$21)+DCF!$D$51)/Inputs!$D$15 | F29: =(SUMPRODUCT(DCF!$D$15:$H$15,(1+$C$29)^(-DCF!$D$12:$H$12))+'Operating Model'!$I$16*$F$28*(1+$C$29)^(-DCF!$D$21)+DCF!$D$51)/Inputs!$D$15 | G29: =(SUMPRODUCT(DCF!$D$15:$H$15,(1+$C$29)^(-DCF!$D$12:$H$12))+'Operating Model'!$I$16*$G$28*(1+$C$29)^(-DCF!$D$21)+DCF!$D$51)/Inputs!$D$15 | H29: =(SUMPRODUCT(DCF!$D$15:$H$15,(1+$C$29)^(-DCF!$D$12:$H$12))+'Operating Model'!$I$16*$H$28*(1+$C$29)^(-DCF!$D$21)+DCF!$D$51)/Inputs!$D$15
C30: =WACC!$D$54+Inputs!$E$237*Inputs!$D$230 | D30: =(SUMPRODUCT(DCF!$D$15:$H$15,(1+$C$30)^(-DCF!$D$12:$H$12))+'Operating Model'!$I$16*$D$28*(1+$C$30)^(-DCF!$D$21)+DCF!$D$51)/Inputs!$D$15 | E30: =(SUMPRODUCT(DCF!$D$15:$H$15,(1+$C$30)^(-DCF!$D$12:$H$12))+'Operating Model'!$I$16*$E$28*(1+$C$30)^(-DCF!$D$21)+DCF!$D$51)/Inputs!$D$15 | F30: =(SUMPRODUCT(DCF!$D$15:$H$15,(1+$C$30)^(-DCF!$D$12:$H$12))+'Operating Model'!$I$16*$F$28*(1+$C$30)^(-DCF!$D$21)+DCF!$D$51)/Inputs!$D$15 | G30: =(SUMPRODUCT(DCF!$D$15:$H$15,(1+$C$30)^(-DCF!$D$12:$H$12))+'Operating Model'!$I$16*$G$28*(1+$C$30)^(-DCF!$D$21)+DCF!$D$51)/Inputs!$D$15 | H30: =(SUMPRODUCT(DCF!$D$15:$H$15,(1+$C$30)^(-DCF!$D$12:$H$12))+'Operating Model'!$I$16*$H$28*(1+$C$30)^(-DCF!$D$21)+DCF!$D$51)/Inputs!$D$15
C31: =WACC!$D$54+Inputs!$F$237*Inputs!$D$230 | D31: =(SUMPRODUCT(DCF!$D$15:$H$15,(1+$C$31)^(-DCF!$D$12:$H$12))+'Operating Model'!$I$16*$D$28*(1+$C$31)^(-DCF!$D$21)+DCF!$D$51)/Inputs!$D$15 | E31: =(SUMPRODUCT(DCF!$D$15:$H$15,(1+$C$31)^(-DCF!$D$12:$H$12))+'Operating Model'!$I$16*$E$28*(1+$C$31)^(-DCF!$D$21)+DCF!$D$51)/Inputs!$D$15 | F31: =(SUMPRODUCT(DCF!$D$15:$H$15,(1+$C$31)^(-DCF!$D$12:$H$12))+'Operating Model'!$I$16*$F$28*(1+$C$31)^(-DCF!$D$21)+DCF!$D$51)/Inputs!$D$15 | G31: =(SUMPRODUCT(DCF!$D$15:$H$15,(1+$C$31)^(-DCF!$D$12:$H$12))+'Operating Model'!$I$16*$G$28*(1+$C$31)^(-DCF!$D$21)+DCF!$D$51)/Inputs!$D$15 | H31: =(SUMPRODUCT(DCF!$D$15:$H$15,(1+$C$31)^(-DCF!$D$12:$H$12))+'Operating Model'!$I$16*$H$28*(1+$C$31)^(-DCF!$D$21)+DCF!$D$51)/Inputs!$D$15
C32: =WACC!$D$54+Inputs!$G$237*Inputs!$D$230 | D32: =(SUMPRODUCT(DCF!$D$15:$H$15,(1+$C$32)^(-DCF!$D$12:$H$12))+'Operating Model'!$I$16*$D$28*(1+$C$32)^(-DCF!$D$21)+DCF!$D$51)/Inputs!$D$15 | E32: =(SUMPRODUCT(DCF!$D$15:$H$15,(1+$C$32)^(-DCF!$D$12:$H$12))+'Operating Model'!$I$16*$E$28*(1+$C$32)^(-DCF!$D$21)+DCF!$D$51)/Inputs!$D$15 | F32: =(SUMPRODUCT(DCF!$D$15:$H$15,(1+$C$32)^(-DCF!$D$12:$H$12))+'Operating Model'!$I$16*$F$28*(1+$C$32)^(-DCF!$D$21)+DCF!$D$51)/Inputs!$D$15 | G32: =(SUMPRODUCT(DCF!$D$15:$H$15,(1+$C$32)^(-DCF!$D$12:$H$12))+'Operating Model'!$I$16*$G$28*(1+$C$32)^(-DCF!$D$21)+DCF!$D$51)/Inputs!$D$15 | H32: =(SUMPRODUCT(DCF!$D$15:$H$15,(1+$C$32)^(-DCF!$D$12:$H$12))+'Operating Model'!$I$16*$H$28*(1+$C$32)^(-DCF!$D$21)+DCF!$D$51)/Inputs!$D$15
C33: =WACC!$D$54+Inputs!$H$237*Inputs!$D$230 | D33: =(SUMPRODUCT(DCF!$D$15:$H$15,(1+$C$33)^(-DCF!$D$12:$H$12))+'Operating Model'!$I$16*$D$28*(1+$C$33)^(-DCF!$D$21)+DCF!$D$51)/Inputs!$D$15 | E33: =(SUMPRODUCT(DCF!$D$15:$H$15,(1+$C$33)^(-DCF!$D$12:$H$12))+'Operating Model'!$I$16*$E$28*(1+$C$33)^(-DCF!$D$21)+DCF!$D$51)/Inputs!$D$15 | F33: =(SUMPRODUCT(DCF!$D$15:$H$15,(1+$C$33)^(-DCF!$D$12:$H$12))+'Operating Model'!$I$16*$F$28*(1+$C$33)^(-DCF!$D$21)+DCF!$D$51)/Inputs!$D$15 | G33: =(SUMPRODUCT(DCF!$D$15:$H$15,(1+$C$33)^(-DCF!$D$12:$H$12))+'Operating Model'!$I$16*$G$28*(1+$C$33)^(-DCF!$D$21)+DCF!$D$51)/Inputs!$D$15 | H33: =(SUMPRODUCT(DCF!$D$15:$H$15,(1+$C$33)^(-DCF!$D$12:$H$12))+'Operating Model'!$I$16*$H$28*(1+$C$33)^(-DCF!$D$21)+DCF!$D$51)/Inputs!$D$15
B35: Grid 3: revenue growth delta (rows) × gross margin delta (columns)
C36: Growth / Margin | D36: =Inputs!$D$237*Inputs!$D$234 | E36: =Inputs!$E$237*Inputs!$D$234 | F36: =Inputs!$F$237*Inputs!$D$234 | G36: =Inputs!$G$237*Inputs!$D$234 | H36: =Inputs!$H$237*Inputs!$D$234 | K36: Notes
C37: =Inputs!$D$237*Inputs!$D$233 | D37: =Sensitivity!$D$86 | E37: =Sensitivity!$D$120 | F37: =Sensitivity!$D$154 | G37: =Sensitivity!$D$188 | H37: =Sensitivity!$D$222
C38: =Inputs!$E$237*Inputs!$D$233 | D38: =Sensitivity!$D$256 | E38: =Sensitivity!$D$290 | F38: =Sensitivity!$D$324 | G38: =Sensitivity!$D$358 | H38: =Sensitivity!$D$392
C39: =Inputs!$F$237*Inputs!$D$233 | D39: =Sensitivity!$D$426 | E39: =Sensitivity!$D$460 | F39: =Sensitivity!$D$494 | G39: =Sensitivity!$D$528 | H39: =Sensitivity!$D$562
C40: =Inputs!$G$237*Inputs!$D$233 | D40: =Sensitivity!$D$596 | E40: =Sensitivity!$D$630 | F40: =Sensitivity!$D$664 | G40: =Sensitivity!$D$698 | H40: =Sensitivity!$D$732
C41: =Inputs!$H$237*Inputs!$D$233 | D41: =Sensitivity!$D$766 | E41: =Sensitivity!$D$800 | F41: =Sensitivity!$D$834 | G41: =Sensitivity!$D$868 | H41: =Sensitivity!$D$902
B44: Grid 4: risk-free rate × levered beta
C45: Risk-free rate / Levered beta | D45: =WACC!$D$21+Inputs!$D$237*Inputs!$D$236 | E45: =WACC!$D$21+Inputs!$E$237*Inputs!$D$236 | F45: =WACC!$D$21+Inputs!$F$237*Inputs!$D$236 | G45: =WACC!$D$21+Inputs!$G$237*Inputs!$D$236 | H45: =WACC!$D$21+Inputs!$H$237*Inputs!$D$236 | K45: Notes
C46: =WACC!$D$12+Inputs!$D$237*Inputs!$D$235 | D46: =IF(Inputs!$D$171="gordon",IF(Inputs!$D$172<(WACC!$D$52*($C$46+$D$45*WACC!$D$28+WACC!$D$29)+WACC!$D$53*(WACC!$D$47*$C$46+WACC!$D$48)*(1-WACC!$D$44)),(SUMPRODUCT(DCF!$D$15:$H$15,(1+(WACC!$D$52*($C$46+$D$45*WACC!$D$28+WACC!$D$29)+WACC!$D$53*(WACC!$D$47*$C$46+WACC!$D$48)*(1-WACC!$D$44)))^(-DCF!$D$12:$H$12))+'Operating Model'!$J$42/((WACC!$D$52*($C$46+$D$45*WACC!$D$28+WACC!$D$29)+WACC!$D$53*(WACC!$D$47*$C$46+WACC!$D$48)*(1-WACC!$D$44))-Inputs!$D$172)*(1+(WACC!$D$52*($C$46+$D$45*WACC!$D$28+WACC!$D$29)+WACC!$D$53*(WACC!$D$47*$C$46+WACC!$D$48)*(1-WACC!$D$44)))^(-DCF!$D$21)+DCF!$D$51)/Inputs!$D$15,"n/a"),(SUMPRODUCT(DCF!$D$15:$H$15,(1+(WACC!$D$52*($C$46+$D$45*WACC!$D$28+WACC!$D$29)+WACC!$D$53*(WACC!$D$47*$C$46+WACC!$D$48)*(1-WACC!$D$44)))^(-DCF!$D$12:$H$12))+'Operating Model'!$I$16*Inputs!$D$173*(1+(WACC!$D$52*($C$46+$D$45*WACC!$D$28+WACC!$D$29)+WACC!$D$53*(WACC!$D$47*$C$46+WACC!$D$48)*(1-WACC!$D$44)))^(-DCF!$D$21)+DCF!$D$51)/Inputs!$D$15) | E46: =IF(Inputs!$D$171="gordon",IF(Inputs!$D$172<(WACC!$D$52*($C$46+$E$45*WACC!$D$28+WACC!$D$29)+WACC!$D$53*(WACC!$D$47*$C$46+WACC!$D$48)*(1-WACC!$D$44)),(SUMPRODUCT(DCF!$D$15:$H$15,(1+(WACC!$D$52*($C$46+$E$45*WACC!$D$28+WACC!$D$29)+WACC!$D$53*(WACC!$D$47*$C$46+WACC!$D$48)*(1-WACC!$D$44)))^(-DCF!$D$12:$H$12))+'Operating Model'!$J$42/((WACC!$D$52*($C$46+$E$45*WACC!$D$28+WACC!$D$29)+WACC!$D$53*(WACC!$D$47*$C$46+WACC!$D$48)*(1-WACC!$D$44))-Inputs!$D$172)*(1+(WACC!$D$52*($C$46+$E$45*WACC!$D$28+WACC!$D$29)+WACC!$D$53*(WACC!$D$47*$C$46+WACC!$D$48)*(1-WACC!$D$44)))^(-DCF!$D$21)+DCF!$D$51)/Inputs!$D$15,"n/a"),(SUMPRODUCT(DCF!$D$15:$H$15,(1+(WACC!$D$52*($C$46+$E$45*WACC!$D$28+WACC!$D$29)+WACC!$D$53*(WACC!$D$47*$C$46+WACC!$D$48)*(1-WACC!$D$44)))^(-DCF!$D$12:$H$12))+'Operating Model'!$I$16*Inputs!$D$173*(1+(WACC!$D$52*($C$46+$E$45*WACC!$D$28+WACC!$D$29)+WACC!$D$53*(WACC!$D$47*$C$46+WACC!$D$48)*(1-WACC!$D$44)))^(-DCF!$D$21)+DCF!$D$51)/Inputs!$D$15) | F46: =IF(Inputs!$D$171="gordon",IF(Inputs!$D$172<(WACC!$D$52*($C$46+$F$45*WACC!$D$28+WACC!$D$29)+WACC!$D$53*(WACC!$D$47*$C$46+WACC!$D$48)*(1-WACC!$D$44)),(SUMPRODUCT(DCF!$D$15:$H$15,(1+(WACC!$D$52*($C$46+$F$45*WACC!$D$28+WACC!$D$29)+WACC!$D$53*(WACC!$D$47*$C$46+WACC!$D$48)*(1-WACC!$D$44)))^(-DCF!$D$12:$H$12))+'Operating Model'!$J$42/((WACC!$D$52*($C$46+$F$45*WACC!$D$28+WACC!$D$29)+WACC!$D$53*(WACC!$D$47*$C$46+WACC!$D$48)*(1-WACC!$D$44))-Inputs!$D$172)*(1+(WACC!$D$52*($C$46+$F$45*WACC!$D$28+WACC!$D$29)+WACC!$D$53*(WACC!$D$47*$C$46+WACC!$D$48)*(1-WACC!$D$44)))^(-DCF!$D$21)+DCF!$D$51)/Inputs!$D$15,"n/a"),(SUMPRODUCT(DCF!$D$15:$H$15,(1+(WACC!$D$52*($C$46+$F$45*WACC!$D$28+WACC!$D$29)+WACC!$D$53*(WACC!$D$47*$C$46+WACC!$D$48)*(1-WACC!$D$44)))^(-DCF!$D$12:$H$12))+'Operating Model'!$I$16*Inputs!$D$173*(1+(WACC!$D$52*($C$46+$F$45*WACC!$D$28+WACC!$D$29)+WACC!$D$53*(WACC!$D$47*$C$46+WACC!$D$48)*(1-WACC!$D$44)))^(-DCF!$D$21)+DCF!$D$51)/Inputs!$D$15) | G46: =IF(Inputs!$D$171="gordon",IF(Inputs!$D$172<(WACC!$D$52*($C$46+$G$45*WACC!$D$28+WACC!$D$29)+WACC!$D$53*(WACC!$D$47*$C$46+WACC!$D$48)*(1-WACC!$D$44)),(SUMPRODUCT(DCF!$D$15:$H$15,(1+(WACC!$D$52*($C$46+$G$45*WACC!$D$28+WACC!$D$29)+WACC!$D$53*(WACC!$D$47*$C$46+WACC!$D$48)*(1-WACC!$D$44)))^(-DCF!$D$12:$H$12))+'Operating Model'!$J$42/((WACC!$D$52*($C$46+$G$45*WACC!$D$28+WACC!$D$29)+WACC!$D$53*(WACC!$D$47*$C$46+WACC!$D$48)*(1-WACC!$D$44))-Inputs!$D$172)*(1+(WACC!$D$52*($C$46+$G$45*WACC!$D$28+WACC!$D$29)+WACC!$D$53*(WACC!$D$47*$C$46+WACC!$D$48)*(1-WACC!$D$44)))^(-DCF!$D$21)+DCF!$D$51)/Inputs!$D$15,"n/a"),(SUMPRODUCT(DCF!$D$15:$H$15,(1+(WACC!$D$52*($C$46+$G$45*WACC!$D$28+WACC!$D$29)+WACC!$D$53*(WACC!$D$47*$C$46+WACC!$D$48)*(1-WACC!$D$44)))^(-DCF!$D$12:$H$12))+'Operating Model'!$I$16*Inputs!$D$173*(1+(WACC!$D$52*($C$46+$G$45*WACC!$D$28+WACC!$D$29)+WACC!$D$53*(WACC!$D$47*$C$46+WACC!$D$48)*(1-WACC!$D$44)))^(-DCF!$D$21)+DCF!$D$51)/Inputs!$D$15) | H46: =IF(Inputs!$D$171="gordon",IF(Inputs!$D$172<(WACC!$D$52*($C$46+$H$45*WACC!$D$28+WACC!$D$29)+WACC!$D$53*(WACC!$D$47*$C$46+WACC!$D$48)*(1-WACC!$D$44)),(SUMPRODUCT(DCF!$D$15:$H$15,(1+(WACC!$D$52*($C$46+$H$45*WACC!$D$28+WACC!$D$29)+WACC!$D$53*(WACC!$D$47*$C$46+WACC!$D$48)*(1-WACC!$D$44)))^(-DCF!$D$12:$H$12))+'Operating Model'!$J$42/((WACC!$D$52*($C$46+$H$45*WACC!$D$28+WACC!$D$29)+WACC!$D$53*(WACC!$D$47*$C$46+WACC!$D$48)*(1-WACC!$D$44))-Inputs!$D$172)*(1+(WACC!$D$52*($C$46+$H$45*WACC!$D$28+WACC!$D$29)+WACC!$D$53*(WACC!$D$47*$C$46+WACC!$D$48)*(1-WACC!$D$44)))^(-DCF!$D$21)+DCF!$D$51)/Inputs!$D$15,"n/a"),(SUMPRODUCT(DCF!$D$15:$H$15,(1+(WACC!$D$52*($C$46+$H$45*WACC!$D$28+WACC!$D$29)+WACC!$D$53*(WACC!$D$47*$C$46+WACC!$D$48)*(1-WACC!$D$44)))^(-DCF!$D$12:$H$12))+'Operating Model'!$I$16*Inputs!$D$173*(1+(WACC!$D$52*($C$46+$H$45*WACC!$D$28+WACC!$D$29)+WACC!$D$53*(WACC!$D$47*$C$46+WACC!$D$48)*(1-WACC!$D$44)))^(-DCF!$D$21)+DCF!$D$51)/Inputs!$D$15)
C47: =WACC!$D$12+Inputs!$E$237*Inputs!$D$235 | D47: =IF(Inputs!$D$171="gordon",IF(Inputs!$D$172<(WACC!$D$52*($C$47+$D$45*WACC!$D$28+WACC!$D$29)+WACC!$D$53*(WACC!$D$47*$C$47+WACC!$D$48)*(1-WACC!$D$44)),(SUMPRODUCT(DCF!$D$15:$H$15,(1+(WACC!$D$52*($C$47+$D$45*WACC!$D$28+WACC!$D$29)+WACC!$D$53*(WACC!$D$47*$C$47+WACC!$D$48)*(1-WACC!$D$44)))^(-DCF!$D$12:$H$12))+'Operating Model'!$J$42/((WACC!$D$52*($C$47+$D$45*WACC!$D$28+WACC!$D$29)+WACC!$D$53*(WACC!$D$47*$C$47+WACC!$D$48)*(1-WACC!$D$44))-Inputs!$D$172)*(1+(WACC!$D$52*($C$47+$D$45*WACC!$D$28+WACC!$D$29)+WACC!$D$53*(WACC!$D$47*$C$47+WACC!$D$48)*(1-WACC!$D$44)))^(-DCF!$D$21)+DCF!$D$51)/Inputs!$D$15,"n/a"),(SUMPRODUCT(DCF!$D$15:$H$15,(1+(WACC!$D$52*($C$47+$D$45*WACC!$D$28+WACC!$D$29)+WACC!$D$53*(WACC!$D$47*$C$47+WACC!$D$48)*(1-WACC!$D$44)))^(-DCF!$D$12:$H$12))+'Operating Model'!$I$16*Inputs!$D$173*(1+(WACC!$D$52*($C$47+$D$45*WACC!$D$28+WACC!$D$29)+WACC!$D$53*(WACC!$D$47*$C$47+WACC!$D$48)*(1-WACC!$D$44)))^(-DCF!$D$21)+DCF!$D$51)/Inputs!$D$15) | E47: =IF(Inputs!$D$171="gordon",IF(Inputs!$D$172<(WACC!$D$52*($C$47+$E$45*WACC!$D$28+WACC!$D$29)+WACC!$D$53*(WACC!$D$47*$C$47+WACC!$D$48)*(1-WACC!$D$44)),(SUMPRODUCT(DCF!$D$15:$H$15,(1+(WACC!$D$52*($C$47+$E$45*WACC!$D$28+WACC!$D$29)+WACC!$D$53*(WACC!$D$47*$C$47+WACC!$D$48)*(1-WACC!$D$44)))^(-DCF!$D$12:$H$12))+'Operating Model'!$J$42/((WACC!$D$52*($C$47+$E$45*WACC!$D$28+WACC!$D$29)+WACC!$D$53*(WACC!$D$47*$C$47+WACC!$D$48)*(1-WACC!$D$44))-Inputs!$D$172)*(1+(WACC!$D$52*($C$47+$E$45*WACC!$D$28+WACC!$D$29)+WACC!$D$53*(WACC!$D$47*$C$47+WACC!$D$48)*(1-WACC!$D$44)))^(-DCF!$D$21)+DCF!$D$51)/Inputs!$D$15,"n/a"),(SUMPRODUCT(DCF!$D$15:$H$15,(1+(WACC!$D$52*($C$47+$E$45*WACC!$D$28+WACC!$D$29)+WACC!$D$53*(WACC!$D$47*$C$47+WACC!$D$48)*(1-WACC!$D$44)))^(-DCF!$D$12:$H$12))+'Operating Model'!$I$16*Inputs!$D$173*(1+(WACC!$D$52*($C$47+$E$45*WACC!$D$28+WACC!$D$29)+WACC!$D$53*(WACC!$D$47*$C$47+WACC!$D$48)*(1-WACC!$D$44)))^(-DCF!$D$21)+DCF!$D$51)/Inputs!$D$15) | F47: =IF(Inputs!$D$171="gordon",IF(Inputs!$D$172<(WACC!$D$52*($C$47+$F$45*WACC!$D$28+WACC!$D$29)+WACC!$D$53*(WACC!$D$47*$C$47+WACC!$D$48)*(1-WACC!$D$44)),(SUMPRODUCT(DCF!$D$15:$H$15,(1+(WACC!$D$52*($C$47+$F$45*WACC!$D$28+WACC!$D$29)+WACC!$D$53*(WACC!$D$47*$C$47+WACC!$D$48)*(1-WACC!$D$44)))^(-DCF!$D$12:$H$12))+'Operating Model'!$J$42/((WACC!$D$52*($C$47+$F$45*WACC!$D$28+WACC!$D$29)+WACC!$D$53*(WACC!$D$47*$C$47+WACC!$D$48)*(1-WACC!$D$44))-Inputs!$D$172)*(1+(WACC!$D$52*($C$47+$F$45*WACC!$D$28+WACC!$D$29)+WACC!$D$53*(WACC!$D$47*$C$47+WACC!$D$48)*(1-WACC!$D$44)))^(-DCF!$D$21)+DCF!$D$51)/Inputs!$D$15,"n/a"),(SUMPRODUCT(DCF!$D$15:$H$15,(1+(WACC!$D$52*($C$47+$F$45*WACC!$D$28+WACC!$D$29)+WACC!$D$53*(WACC!$D$47*$C$47+WACC!$D$48)*(1-WACC!$D$44)))^(-DCF!$D$12:$H$12))+'Operating Model'!$I$16*Inputs!$D$173*(1+(WACC!$D$52*($C$47+$F$45*WACC!$D$28+WACC!$D$29)+WACC!$D$53*(WACC!$D$47*$C$47+WACC!$D$48)*(1-WACC!$D$44)))^(-DCF!$D$21)+DCF!$D$51)/Inputs!$D$15) | G47: =IF(Inputs!$D$171="gordon",IF(Inputs!$D$172<(WACC!$D$52*($C$47+$G$45*WACC!$D$28+WACC!$D$29)+WACC!$D$53*(WACC!$D$47*$C$47+WACC!$D$48)*(1-WACC!$D$44)),(SUMPRODUCT(DCF!$D$15:$H$15,(1+(WACC!$D$52*($C$47+$G$45*WACC!$D$28+WACC!$D$29)+WACC!$D$53*(WACC!$D$47*$C$47+WACC!$D$48)*(1-WACC!$D$44)))^(-DCF!$D$12:$H$12))+'Operating Model'!$J$42/((WACC!$D$52*($C$47+$G$45*WACC!$D$28+WACC!$D$29)+WACC!$D$53*(WACC!$D$47*$C$47+WACC!$D$48)*(1-WACC!$D$44))-Inputs!$D$172)*(1+(WACC!$D$52*($C$47+$G$45*WACC!$D$28+WACC!$D$29)+WACC!$D$53*(WACC!$D$47*$C$47+WACC!$D$48)*(1-WACC!$D$44)))^(-DCF!$D$21)+DCF!$D$51)/Inputs!$D$15,"n/a"),(SUMPRODUCT(DCF!$D$15:$H$15,(1+(WACC!$D$52*($C$47+$G$45*WACC!$D$28+WACC!$D$29)+WACC!$D$53*(WACC!$D$47*$C$47+WACC!$D$48)*(1-WACC!$D$44)))^(-DCF!$D$12:$H$12))+'Operating Model'!$I$16*Inputs!$D$173*(1+(WACC!$D$52*($C$47+$G$45*WACC!$D$28+WACC!$D$29)+WACC!$D$53*(WACC!$D$47*$C$47+WACC!$D$48)*(1-WACC!$D$44)))^(-DCF!$D$21)+DCF!$D$51)/Inputs!$D$15) | H47: =IF(Inputs!$D$171="gordon",IF(Inputs!$D$172<(WACC!$D$52*($C$47+$H$45*WACC!$D$28+WACC!$D$29)+WACC!$D$53*(WACC!$D$47*$C$47+WACC!$D$48)*(1-WACC!$D$44)),(SUMPRODUCT(DCF!$D$15:$H$15,(1+(WACC!$D$52*($C$47+$H$45*WACC!$D$28+WACC!$D$29)+WACC!$D$53*(WACC!$D$47*$C$47+WACC!$D$48)*(1-WACC!$D$44)))^(-DCF!$D$12:$H$12))+'Operating Model'!$J$42/((WACC!$D$52*($C$47+$H$45*WACC!$D$28+WACC!$D$29)+WACC!$D$53*(WACC!$D$47*$C$47+WACC!$D$48)*(1-WACC!$D$44))-Inputs!$D$172)*(1+(WACC!$D$52*($C$47+$H$45*WACC!$D$28+WACC!$D$29)+WACC!$D$53*(WACC!$D$47*$C$47+WACC!$D$48)*(1-WACC!$D$44)))^(-DCF!$D$21)+DCF!$D$51)/Inputs!$D$15,"n/a"),(SUMPRODUCT(DCF!$D$15:$H$15,(1+(WACC!$D$52*($C$47+$H$45*WACC!$D$28+WACC!$D$29)+WACC!$D$53*(WACC!$D$47*$C$47+WACC!$D$48)*(1-WACC!$D$44)))^(-DCF!$D$12:$H$12))+'Operating Model'!$I$16*Inputs!$D$173*(1+(WACC!$D$52*($C$47+$H$45*WACC!$D$28+WACC!$D$29)+WACC!$D$53*(WACC!$D$47*$C$47+WACC!$D$48)*(1-WACC!$D$44)))^(-DCF!$D$21)+DCF!$D$51)/Inputs!$D$15)
C48: =WACC!$D$12+Inputs!$F$237*Inputs!$D$235 | D48: =IF(Inputs!$D$171="gordon",IF(Inputs!$D$172<(WACC!$D$52*($C$48+$D$45*WACC!$D$28+WACC!$D$29)+WACC!$D$53*(WACC!$D$47*$C$48+WACC!$D$48)*(1-WACC!$D$44)),(SUMPRODUCT(DCF!$D$15:$H$15,(1+(WACC!$D$52*($C$48+$D$45*WACC!$D$28+WACC!$D$29)+WACC!$D$53*(WACC!$D$47*$C$48+WACC!$D$48)*(1-WACC!$D$44)))^(-DCF!$D$12:$H$12))+'Operating Model'!$J$42/((WACC!$D$52*($C$48+$D$45*WACC!$D$28+WACC!$D$29)+WACC!$D$53*(WACC!$D$47*$C$48+WACC!$D$48)*(1-WACC!$D$44))-Inputs!$D$172)*(1+(WACC!$D$52*($C$48+$D$45*WACC!$D$28+WACC!$D$29)+WACC!$D$53*(WACC!$D$47*$C$48+WACC!$D$48)*(1-WACC!$D$44)))^(-DCF!$D$21)+DCF!$D$51)/Inputs!$D$15,"n/a"),(SUMPRODUCT(DCF!$D$15:$H$15,(1+(WACC!$D$52*($C$48+$D$45*WACC!$D$28+WACC!$D$29)+WACC!$D$53*(WACC!$D$47*$C$48+WACC!$D$48)*(1-WACC!$D$44)))^(-DCF!$D$12:$H$12))+'Operating Model'!$I$16*Inputs!$D$173*(1+(WACC!$D$52*($C$48+$D$45*WACC!$D$28+WACC!$D$29)+WACC!$D$53*(WACC!$D$47*$C$48+WACC!$D$48)*(1-WACC!$D$44)))^(-DCF!$D$21)+DCF!$D$51)/Inputs!$D$15) | E48: =IF(Inputs!$D$171="gordon",IF(Inputs!$D$172<(WACC!$D$52*($C$48+$E$45*WACC!$D$28+WACC!$D$29)+WACC!$D$53*(WACC!$D$47*$C$48+WACC!$D$48)*(1-WACC!$D$44)),(SUMPRODUCT(DCF!$D$15:$H$15,(1+(WACC!$D$52*($C$48+$E$45*WACC!$D$28+WACC!$D$29)+WACC!$D$53*(WACC!$D$47*$C$48+WACC!$D$48)*(1-WACC!$D$44)))^(-DCF!$D$12:$H$12))+'Operating Model'!$J$42/((WACC!$D$52*($C$48+$E$45*WACC!$D$28+WACC!$D$29)+WACC!$D$53*(WACC!$D$47*$C$48+WACC!$D$48)*(1-WACC!$D$44))-Inputs!$D$172)*(1+(WACC!$D$52*($C$48+$E$45*WACC!$D$28+WACC!$D$29)+WACC!$D$53*(WACC!$D$47*$C$48+WACC!$D$48)*(1-WACC!$D$44)))^(-DCF!$D$21)+DCF!$D$51)/Inputs!$D$15,"n/a"),(SUMPRODUCT(DCF!$D$15:$H$15,(1+(WACC!$D$52*($C$48+$E$45*WACC!$D$28+WACC!$D$29)+WACC!$D$53*(WACC!$D$47*$C$48+WACC!$D$48)*(1-WACC!$D$44)))^(-DCF!$D$12:$H$12))+'Operating Model'!$I$16*Inputs!$D$173*(1+(WACC!$D$52*($C$48+$E$45*WACC!$D$28+WACC!$D$29)+WACC!$D$53*(WACC!$D$47*$C$48+WACC!$D$48)*(1-WACC!$D$44)))^(-DCF!$D$21)+DCF!$D$51)/Inputs!$D$15) | F48: =IF(Inputs!$D$171="gordon",IF(Inputs!$D$172<(WACC!$D$52*($C$48+$F$45*WACC!$D$28+WACC!$D$29)+WACC!$D$53*(WACC!$D$47*$C$48+WACC!$D$48)*(1-WACC!$D$44)),(SUMPRODUCT(DCF!$D$15:$H$15,(1+(WACC!$D$52*($C$48+$F$45*WACC!$D$28+WACC!$D$29)+WACC!$D$53*(WACC!$D$47*$C$48+WACC!$D$48)*(1-WACC!$D$44)))^(-DCF!$D$12:$H$12))+'Operating Model'!$J$42/((WACC!$D$52*($C$48+$F$45*WACC!$D$28+WACC!$D$29)+WACC!$D$53*(WACC!$D$47*$C$48+WACC!$D$48)*(1-WACC!$D$44))-Inputs!$D$172)*(1+(WACC!$D$52*($C$48+$F$45*WACC!$D$28+WACC!$D$29)+WACC!$D$53*(WACC!$D$47*$C$48+WACC!$D$48)*(1-WACC!$D$44)))^(-DCF!$D$21)+DCF!$D$51)/Inputs!$D$15,"n/a"),(SUMPRODUCT(DCF!$D$15:$H$15,(1+(WACC!$D$52*($C$48+$F$45*WACC!$D$28+WACC!$D$29)+WACC!$D$53*(WACC!$D$47*$C$48+WACC!$D$48)*(1-WACC!$D$44)))^(-DCF!$D$12:$H$12))+'Operating Model'!$I$16*Inputs!$D$173*(1+(WACC!$D$52*($C$48+$F$45*WACC!$D$28+WACC!$D$29)+WACC!$D$53*(WACC!$D$47*$C$48+WACC!$D$48)*(1-WACC!$D$44)))^(-DCF!$D$21)+DCF!$D$51)/Inputs!$D$15) | G48: =IF(Inputs!$D$171="gordon",IF(Inputs!$D$172<(WACC!$D$52*($C$48+$G$45*WACC!$D$28+WACC!$D$29)+WACC!$D$53*(WACC!$D$47*$C$48+WACC!$D$48)*(1-WACC!$D$44)),(SUMPRODUCT(DCF!$D$15:$H$15,(1+(WACC!$D$52*($C$48+$G$45*WACC!$D$28+WACC!$D$29)+WACC!$D$53*(WACC!$D$47*$C$48+WACC!$D$48)*(1-WACC!$D$44)))^(-DCF!$D$12:$H$12))+'Operating Model'!$J$42/((WACC!$D$52*($C$48+$G$45*WACC!$D$28+WACC!$D$29)+WACC!$D$53*(WACC!$D$47*$C$48+WACC!$D$48)*(1-WACC!$D$44))-Inputs!$D$172)*(1+(WACC!$D$52*($C$48+$G$45*WACC!$D$28+WACC!$D$29)+WACC!$D$53*(WACC!$D$47*$C$48+WACC!$D$48)*(1-WACC!$D$44)))^(-DCF!$D$21)+DCF!$D$51)/Inputs!$D$15,"n/a"),(SUMPRODUCT(DCF!$D$15:$H$15,(1+(WACC!$D$52*($C$48+$G$45*WACC!$D$28+WACC!$D$29)+WACC!$D$53*(WACC!$D$47*$C$48+WACC!$D$48)*(1-WACC!$D$44)))^(-DCF!$D$12:$H$12))+'Operating Model'!$I$16*Inputs!$D$173*(1+(WACC!$D$52*($C$48+$G$45*WACC!$D$28+WACC!$D$29)+WACC!$D$53*(WACC!$D$47*$C$48+WACC!$D$48)*(1-WACC!$D$44)))^(-DCF!$D$21)+DCF!$D$51)/Inputs!$D$15) | H48: =IF(Inputs!$D$171="gordon",IF(Inputs!$D$172<(WACC!$D$52*($C$48+$H$45*WACC!$D$28+WACC!$D$29)+WACC!$D$53*(WACC!$D$47*$C$48+WACC!$D$48)*(1-WACC!$D$44)),(SUMPRODUCT(DCF!$D$15:$H$15,(1+(WACC!$D$52*($C$48+$H$45*WACC!$D$28+WACC!$D$29)+WACC!$D$53*(WACC!$D$47*$C$48+WACC!$D$48)*(1-WACC!$D$44)))^(-DCF!$D$12:$H$12))+'Operating Model'!$J$42/((WACC!$D$52*($C$48+$H$45*WACC!$D$28+WACC!$D$29)+WACC!$D$53*(WACC!$D$47*$C$48+WACC!$D$48)*(1-WACC!$D$44))-Inputs!$D$172)*(1+(WACC!$D$52*($C$48+$H$45*WACC!$D$28+WACC!$D$29)+WACC!$D$53*(WACC!$D$47*$C$48+WACC!$D$48)*(1-WACC!$D$44)))^(-DCF!$D$21)+DCF!$D$51)/Inputs!$D$15,"n/a"),(SUMPRODUCT(DCF!$D$15:$H$15,(1+(WACC!$D$52*($C$48+$H$45*WACC!$D$28+WACC!$D$29)+WACC!$D$53*(WACC!$D$47*$C$48+WACC!$D$48)*(1-WACC!$D$44)))^(-DCF!$D$12:$H$12))+'Operating Model'!$I$16*Inputs!$D$173*(1+(WACC!$D$52*($C$48+$H$45*WACC!$D$28+WACC!$D$29)+WACC!$D$53*(WACC!$D$47*$C$48+WACC!$D$48)*(1-WACC!$D$44)))^(-DCF!$D$21)+DCF!$D$51)/Inputs!$D$15)
C49: =WACC!$D$12+Inputs!$G$237*Inputs!$D$235 | D49: =IF(Inputs!$D$171="gordon",IF(Inputs!$D$172<(WACC!$D$52*($C$49+$D$45*WACC!$D$28+WACC!$D$29)+WACC!$D$53*(WACC!$D$47*$C$49+WACC!$D$48)*(1-WACC!$D$44)),(SUMPRODUCT(DCF!$D$15:$H$15,(1+(WACC!$D$52*($C$49+$D$45*WACC!$D$28+WACC!$D$29)+WACC!$D$53*(WACC!$D$47*$C$49+WACC!$D$48)*(1-WACC!$D$44)))^(-DCF!$D$12:$H$12))+'Operating Model'!$J$42/((WACC!$D$52*($C$49+$D$45*WACC!$D$28+WACC!$D$29)+WACC!$D$53*(WACC!$D$47*$C$49+WACC!$D$48)*(1-WACC!$D$44))-Inputs!$D$172)*(1+(WACC!$D$52*($C$49+$D$45*WACC!$D$28+WACC!$D$29)+WACC!$D$53*(WACC!$D$47*$C$49+WACC!$D$48)*(1-WACC!$D$44)))^(-DCF!$D$21)+DCF!$D$51)/Inputs!$D$15,"n/a"),(SUMPRODUCT(DCF!$D$15:$H$15,(1+(WACC!$D$52*($C$49+$D$45*WACC!$D$28+WACC!$D$29)+WACC!$D$53*(WACC!$D$47*$C$49+WACC!$D$48)*(1-WACC!$D$44)))^(-DCF!$D$12:$H$12))+'Operating Model'!$I$16*Inputs!$D$173*(1+(WACC!$D$52*($C$49+$D$45*WACC!$D$28+WACC!$D$29)+WACC!$D$53*(WACC!$D$47*$C$49+WACC!$D$48)*(1-WACC!$D$44)))^(-DCF!$D$21)+DCF!$D$51)/Inputs!$D$15) | E49: =IF(Inputs!$D$171="gordon",IF(Inputs!$D$172<(WACC!$D$52*($C$49+$E$45*WACC!$D$28+WACC!$D$29)+WACC!$D$53*(WACC!$D$47*$C$49+WACC!$D$48)*(1-WACC!$D$44)),(SUMPRODUCT(DCF!$D$15:$H$15,(1+(WACC!$D$52*($C$49+$E$45*WACC!$D$28+WACC!$D$29)+WACC!$D$53*(WACC!$D$47*$C$49+WACC!$D$48)*(1-WACC!$D$44)))^(-DCF!$D$12:$H$12))+'Operating Model'!$J$42/((WACC!$D$52*($C$49+$E$45*WACC!$D$28+WACC!$D$29)+WACC!$D$53*(WACC!$D$47*$C$49+WACC!$D$48)*(1-WACC!$D$44))-Inputs!$D$172)*(1+(WACC!$D$52*($C$49+$E$45*WACC!$D$28+WACC!$D$29)+WACC!$D$53*(WACC!$D$47*$C$49+WACC!$D$48)*(1-WACC!$D$44)))^(-DCF!$D$21)+DCF!$D$51)/Inputs!$D$15,"n/a"),(SUMPRODUCT(DCF!$D$15:$H$15,(1+(WACC!$D$52*($C$49+$E$45*WACC!$D$28+WACC!$D$29)+WACC!$D$53*(WACC!$D$47*$C$49+WACC!$D$48)*(1-WACC!$D$44)))^(-DCF!$D$12:$H$12))+'Operating Model'!$I$16*Inputs!$D$173*(1+(WACC!$D$52*($C$49+$E$45*WACC!$D$28+WACC!$D$29)+WACC!$D$53*(WACC!$D$47*$C$49+WACC!$D$48)*(1-WACC!$D$44)))^(-DCF!$D$21)+DCF!$D$51)/Inputs!$D$15) | F49: =IF(Inputs!$D$171="gordon",IF(Inputs!$D$172<(WACC!$D$52*($C$49+$F$45*WACC!$D$28+WACC!$D$29)+WACC!$D$53*(WACC!$D$47*$C$49+WACC!$D$48)*(1-WACC!$D$44)),(SUMPRODUCT(DCF!$D$15:$H$15,(1+(WACC!$D$52*($C$49+$F$45*WACC!$D$28+WACC!$D$29)+WACC!$D$53*(WACC!$D$47*$C$49+WACC!$D$48)*(1-WACC!$D$44)))^(-DCF!$D$12:$H$12))+'Operating Model'!$J$42/((WACC!$D$52*($C$49+$F$45*WACC!$D$28+WACC!$D$29)+WACC!$D$53*(WACC!$D$47*$C$49+WACC!$D$48)*(1-WACC!$D$44))-Inputs!$D$172)*(1+(WACC!$D$52*($C$49+$F$45*WACC!$D$28+WACC!$D$29)+WACC!$D$53*(WACC!$D$47*$C$49+WACC!$D$48)*(1-WACC!$D$44)))^(-DCF!$D$21)+DCF!$D$51)/Inputs!$D$15,"n/a"),(SUMPRODUCT(DCF!$D$15:$H$15,(1+(WACC!$D$52*($C$49+$F$45*WACC!$D$28+WACC!$D$29)+WACC!$D$53*(WACC!$D$47*$C$49+WACC!$D$48)*(1-WACC!$D$44)))^(-DCF!$D$12:$H$12))+'Operating Model'!$I$16*Inputs!$D$173*(1+(WACC!$D$52*($C$49+$F$45*WACC!$D$28+WACC!$D$29)+WACC!$D$53*(WACC!$D$47*$C$49+WACC!$D$48)*(1-WACC!$D$44)))^(-DCF!$D$21)+DCF!$D$51)/Inputs!$D$15) | G49: =IF(Inputs!$D$171="gordon",IF(Inputs!$D$172<(WACC!$D$52*($C$49+$G$45*WACC!$D$28+WACC!$D$29)+WACC!$D$53*(WACC!$D$47*$C$49+WACC!$D$48)*(1-WACC!$D$44)),(SUMPRODUCT(DCF!$D$15:$H$15,(1+(WACC!$D$52*($C$49+$G$45*WACC!$D$28+WACC!$D$29)+WACC!$D$53*(WACC!$D$47*$C$49+WACC!$D$48)*(1-WACC!$D$44)))^(-DCF!$D$12:$H$12))+'Operating Model'!$J$42/((WACC!$D$52*($C$49+$G$45*WACC!$D$28+WACC!$D$29)+WACC!$D$53*(WACC!$D$47*$C$49+WACC!$D$48)*(1-WACC!$D$44))-Inputs!$D$172)*(1+(WACC!$D$52*($C$49+$G$45*WACC!$D$28+WACC!$D$29)+WACC!$D$53*(WACC!$D$47*$C$49+WACC!$D$48)*(1-WACC!$D$44)))^(-DCF!$D$21)+DCF!$D$51)/Inputs!$D$15,"n/a"),(SUMPRODUCT(DCF!$D$15:$H$15,(1+(WACC!$D$52*($C$49+$G$45*WACC!$D$28+WACC!$D$29)+WACC!$D$53*(WACC!$D$47*$C$49+WACC!$D$48)*(1-WACC!$D$44)))^(-DCF!$D$12:$H$12))+'Operating Model'!$I$16*Inputs!$D$173*(1+(WACC!$D$52*($C$49+$G$45*WACC!$D$28+WACC!$D$29)+WACC!$D$53*(WACC!$D$47*$C$49+WACC!$D$48)*(1-WACC!$D$44)))^(-DCF!$D$21)+DCF!$D$51)/Inputs!$D$15) | H49: =IF(Inputs!$D$171="gordon",IF(Inputs!$D$172<(WACC!$D$52*($C$49+$H$45*WACC!$D$28+WACC!$D$29)+WACC!$D$53*(WACC!$D$47*$C$49+WACC!$D$48)*(1-WACC!$D$44)),(SUMPRODUCT(DCF!$D$15:$H$15,(1+(WACC!$D$52*($C$49+$H$45*WACC!$D$28+WACC!$D$29)+WACC!$D$53*(WACC!$D$47*$C$49+WACC!$D$48)*(1-WACC!$D$44)))^(-DCF!$D$12:$H$12))+'Operating Model'!$J$42/((WACC!$D$52*($C$49+$H$45*WACC!$D$28+WACC!$D$29)+WACC!$D$53*(WACC!$D$47*$C$49+WACC!$D$48)*(1-WACC!$D$44))-Inputs!$D$172)*(1+(WACC!$D$52*($C$49+$H$45*WACC!$D$28+WACC!$D$29)+WACC!$D$53*(WACC!$D$47*$C$49+WACC!$D$48)*(1-WACC!$D$44)))^(-DCF!$D$21)+DCF!$D$51)/Inputs!$D$15,"n/a"),(SUMPRODUCT(DCF!$D$15:$H$15,(1+(WACC!$D$52*($C$49+$H$45*WACC!$D$28+WACC!$D$29)+WACC!$D$53*(WACC!$D$47*$C$49+WACC!$D$48)*(1-WACC!$D$44)))^(-DCF!$D$12:$H$12))+'Operating Model'!$I$16*Inputs!$D$173*(1+(WACC!$D$52*($C$49+$H$45*WACC!$D$28+WACC!$D$29)+WACC!$D$53*(WACC!$D$47*$C$49+WACC!$D$48)*(1-WACC!$D$44)))^(-DCF!$D$21)+DCF!$D$51)/Inputs!$D$15)
C50: =WACC!$D$12+Inputs!$H$237*Inputs!$D$235 | D50: =IF(Inputs!$D$171="gordon",IF(Inputs!$D$172<(WACC!$D$52*($C$50+$D$45*WACC!$D$28+WACC!$D$29)+WACC!$D$53*(WACC!$D$47*$C$50+WACC!$D$48)*(1-WACC!$D$44)),(SUMPRODUCT(DCF!$D$15:$H$15,(1+(WACC!$D$52*($C$50+$D$45*WACC!$D$28+WACC!$D$29)+WACC!$D$53*(WACC!$D$47*$C$50+WACC!$D$48)*(1-WACC!$D$44)))^(-DCF!$D$12:$H$12))+'Operating Model'!$J$42/((WACC!$D$52*($C$50+$D$45*WACC!$D$28+WACC!$D$29)+WACC!$D$53*(WACC!$D$47*$C$50+WACC!$D$48)*(1-WACC!$D$44))-Inputs!$D$172)*(1+(WACC!$D$52*($C$50+$D$45*WACC!$D$28+WACC!$D$29)+WACC!$D$53*(WACC!$D$47*$C$50+WACC!$D$48)*(1-WACC!$D$44)))^(-DCF!$D$21)+DCF!$D$51)/Inputs!$D$15,"n/a"),(SUMPRODUCT(DCF!$D$15:$H$15,(1+(WACC!$D$52*($C$50+$D$45*WACC!$D$28+WACC!$D$29)+WACC!$D$53*(WACC!$D$47*$C$50+WACC!$D$48)*(1-WACC!$D$44)))^(-DCF!$D$12:$H$12))+'Operating Model'!$I$16*Inputs!$D$173*(1+(WACC!$D$52*($C$50+$D$45*WACC!$D$28+WACC!$D$29)+WACC!$D$53*(WACC!$D$47*$C$50+WACC!$D$48)*(1-WACC!$D$44)))^(-DCF!$D$21)+DCF!$D$51)/Inputs!$D$15) | E50: =IF(Inputs!$D$171="gordon",IF(Inputs!$D$172<(WACC!$D$52*($C$50+$E$45*WACC!$D$28+WACC!$D$29)+WACC!$D$53*(WACC!$D$47*$C$50+WACC!$D$48)*(1-WACC!$D$44)),(SUMPRODUCT(DCF!$D$15:$H$15,(1+(WACC!$D$52*($C$50+$E$45*WACC!$D$28+WACC!$D$29)+WACC!$D$53*(WACC!$D$47*$C$50+WACC!$D$48)*(1-WACC!$D$44)))^(-DCF!$D$12:$H$12))+'Operating Model'!$J$42/((WACC!$D$52*($C$50+$E$45*WACC!$D$28+WACC!$D$29)+WACC!$D$53*(WACC!$D$47*$C$50+WACC!$D$48)*(1-WACC!$D$44))-Inputs!$D$172)*(1+(WACC!$D$52*($C$50+$E$45*WACC!$D$28+WACC!$D$29)+WACC!$D$53*(WACC!$D$47*$C$50+WACC!$D$48)*(1-WACC!$D$44)))^(-DCF!$D$21)+DCF!$D$51)/Inputs!$D$15,"n/a"),(SUMPRODUCT(DCF!$D$15:$H$15,(1+(WACC!$D$52*($C$50+$E$45*WACC!$D$28+WACC!$D$29)+WACC!$D$53*(WACC!$D$47*$C$50+WACC!$D$48)*(1-WACC!$D$44)))^(-DCF!$D$12:$H$12))+'Operating Model'!$I$16*Inputs!$D$173*(1+(WACC!$D$52*($C$50+$E$45*WACC!$D$28+WACC!$D$29)+WACC!$D$53*(WACC!$D$47*$C$50+WACC!$D$48)*(1-WACC!$D$44)))^(-DCF!$D$21)+DCF!$D$51)/Inputs!$D$15) | F50: =IF(Inputs!$D$171="gordon",IF(Inputs!$D$172<(WACC!$D$52*($C$50+$F$45*WACC!$D$28+WACC!$D$29)+WACC!$D$53*(WACC!$D$47*$C$50+WACC!$D$48)*(1-WACC!$D$44)),(SUMPRODUCT(DCF!$D$15:$H$15,(1+(WACC!$D$52*($C$50+$F$45*WACC!$D$28+WACC!$D$29)+WACC!$D$53*(WACC!$D$47*$C$50+WACC!$D$48)*(1-WACC!$D$44)))^(-DCF!$D$12:$H$12))+'Operating Model'!$J$42/((WACC!$D$52*($C$50+$F$45*WACC!$D$28+WACC!$D$29)+WACC!$D$53*(WACC!$D$47*$C$50+WACC!$D$48)*(1-WACC!$D$44))-Inputs!$D$172)*(1+(WACC!$D$52*($C$50+$F$45*WACC!$D$28+WACC!$D$29)+WACC!$D$53*(WACC!$D$47*$C$50+WACC!$D$48)*(1-WACC!$D$44)))^(-DCF!$D$21)+DCF!$D$51)/Inputs!$D$15,"n/a"),(SUMPRODUCT(DCF!$D$15:$H$15,(1+(WACC!$D$52*($C$50+$F$45*WACC!$D$28+WACC!$D$29)+WACC!$D$53*(WACC!$D$47*$C$50+WACC!$D$48)*(1-WACC!$D$44)))^(-DCF!$D$12:$H$12))+'Operating Model'!$I$16*Inputs!$D$173*(1+(WACC!$D$52*($C$50+$F$45*WACC!$D$28+WACC!$D$29)+WACC!$D$53*(WACC!$D$47*$C$50+WACC!$D$48)*(1-WACC!$D$44)))^(-DCF!$D$21)+DCF!$D$51)/Inputs!$D$15) | G50: =IF(Inputs!$D$171="gordon",IF(Inputs!$D$172<(WACC!$D$52*($C$50+$G$45*WACC!$D$28+WACC!$D$29)+WACC!$D$53*(WACC!$D$47*$C$50+WACC!$D$48)*(1-WACC!$D$44)),(SUMPRODUCT(DCF!$D$15:$H$15,(1+(WACC!$D$52*($C$50+$G$45*WACC!$D$28+WACC!$D$29)+WACC!$D$53*(WACC!$D$47*$C$50+WACC!$D$48)*(1-WACC!$D$44)))^(-DCF!$D$12:$H$12))+'Operating Model'!$J$42/((WACC!$D$52*($C$50+$G$45*WACC!$D$28+WACC!$D$29)+WACC!$D$53*(WACC!$D$47*$C$50+WACC!$D$48)*(1-WACC!$D$44))-Inputs!$D$172)*(1+(WACC!$D$52*($C$50+$G$45*WACC!$D$28+WACC!$D$29)+WACC!$D$53*(WACC!$D$47*$C$50+WACC!$D$48)*(1-WACC!$D$44)))^(-DCF!$D$21)+DCF!$D$51)/Inputs!$D$15,"n/a"),(SUMPRODUCT(DCF!$D$15:$H$15,(1+(WACC!$D$52*($C$50+$G$45*WACC!$D$28+WACC!$D$29)+WACC!$D$53*(WACC!$D$47*$C$50+WACC!$D$48)*(1-WACC!$D$44)))^(-DCF!$D$12:$H$12))+'Operating Model'!$I$16*Inputs!$D$173*(1+(WACC!$D$52*($C$50+$G$45*WACC!$D$28+WACC!$D$29)+WACC!$D$53*(WACC!$D$47*$C$50+WACC!$D$48)*(1-WACC!$D$44)))^(-DCF!$D$21)+DCF!$D$51)/Inputs!$D$15) | H50: =IF(Inputs!$D$171="gordon",IF(Inputs!$D$172<(WACC!$D$52*($C$50+$H$45*WACC!$D$28+WACC!$D$29)+WACC!$D$53*(WACC!$D$47*$C$50+WACC!$D$48)*(1-WACC!$D$44)),(SUMPRODUCT(DCF!$D$15:$H$15,(1+(WACC!$D$52*($C$50+$H$45*WACC!$D$28+WACC!$D$29)+WACC!$D$53*(WACC!$D$47*$C$50+WACC!$D$48)*(1-WACC!$D$44)))^(-DCF!$D$12:$H$12))+'Operating Model'!$J$42/((WACC!$D$52*($C$50+$H$45*WACC!$D$28+WACC!$D$29)+WACC!$D$53*(WACC!$D$47*$C$50+WACC!$D$48)*(1-WACC!$D$44))-Inputs!$D$172)*(1+(WACC!$D$52*($C$50+$H$45*WACC!$D$28+WACC!$D$29)+WACC!$D$53*(WACC!$D$47*$C$50+WACC!$D$48)*(1-WACC!$D$44)))^(-DCF!$D$21)+DCF!$D$51)/Inputs!$D$15,"n/a"),(SUMPRODUCT(DCF!$D$15:$H$15,(1+(WACC!$D$52*($C$50+$H$45*WACC!$D$28+WACC!$D$29)+WACC!$D$53*(WACC!$D$47*$C$50+WACC!$D$48)*(1-WACC!$D$44)))^(-DCF!$D$12:$H$12))+'Operating Model'!$I$16*Inputs!$D$173*(1+(WACC!$D$52*($C$50+$H$45*WACC!$D$28+WACC!$D$29)+WACC!$D$53*(WACC!$D$47*$C$50+WACC!$D$48)*(1-WACC!$D$44)))^(-DCF!$D$21)+DCF!$D$51)/Inputs!$D$15)
B53: Grid 3 support: one mini operating model per cell (revenue growth delta × gross margin delta)
B54: Cell (1,1): revenue growth delta | gross margin delta | C54: pp | D54: =Inputs!$D$237*Inputs!$D$233 | E54: =Inputs!$D$237*Inputs!$D$234
B55: (1,1) Revenue | C55: EGP | D55: =Inputs!$E$23 | E55: =$D$55*(1+(Inputs!$D$182+$D$54)) | F55: =$E$55*(1+(Inputs!$E$182+$D$54)) | G55: =$F$55*(1+(Inputs!$F$182+$D$54)) | H55: =$G$55*(1+(Inputs!$G$182+$D$54)) | I55: =$H$55*(1+(Inputs!$H$182+$D$54)) | J55: =$I$55*(1+Inputs!$D$172)
B56: (1,1) Gross profit before D&A | C56: EGP | D56: =$D$55*((Inputs!$E$26+Inputs!$E$51+Inputs!$E$52)/$D$55) | E56: =$E$55*(Inputs!$D$183+$E$54) | F56: =$F$55*(Inputs!$E$183+$E$54) | G56: =$G$55*(Inputs!$F$183+$E$54) | H56: =$H$55*(Inputs!$G$183+$E$54) | I56: =$I$55*(Inputs!$H$183+$E$54) | J56: =$J$55*(Inputs!$I$183+$E$54)
B57: (1,1) SG&A | C57: EGP | D57: =-(Inputs!$E$29+Inputs!$E$30) | E57: =$E$55*Inputs!$D$184 | F57: =$F$55*Inputs!$E$184 | G57: =$G$55*Inputs!$F$184 | H57: =$H$55*Inputs!$G$184 | I57: =$I$55*Inputs!$H$184 | J57: =$J$55*Inputs!$I$184
B58: (1,1) Other operating income (net) | C58: EGP | D58: =Normalization!$D$13-Inputs!$E$26-Inputs!$E$29-Inputs!$E$30 | E58: =$E$55*Inputs!$D$185 | F58: =$F$55*Inputs!$E$185 | G58: =$G$55*Inputs!$F$185 | H58: =$H$55*Inputs!$G$185 | I58: =$I$55*Inputs!$H$185 | J58: =$J$55*Inputs!$I$185
B59: (1,1) EBITDA | C59: EGP | D59: =$D$56-$D$57+$D$58 | E59: =$E$56-$E$57+$E$58 | F59: =$F$56-$F$57+$F$58 | G59: =$G$56-$G$57+$G$58 | H59: =$H$56-$H$57+$H$58 | I59: =$I$56-$I$57+$I$58 | J59: =$J$56-$J$57+$J$58
B60: (1,1) Opening PP&E | C60: EGP | E60: =Inputs!$E$57 | F60: =$E$65 | G60: =$F$65 | H60: =$G$65 | I60: =$H$65 | J60: =$I$65
B61: (1,1) Depreciation | C61: EGP | D61: =Inputs!$E$51 | E61: =IF(Inputs!$D$180="ppe_rollforward",Inputs!$D$187*$E$60,$E$55*Inputs!$D$186) | F61: =IF(Inputs!$D$180="ppe_rollforward",Inputs!$E$187*$F$60,$F$55*Inputs!$E$186) | G61: =IF(Inputs!$D$180="ppe_rollforward",Inputs!$F$187*$G$60,$G$55*Inputs!$F$186) | H61: =IF(Inputs!$D$180="ppe_rollforward",Inputs!$G$187*$H$60,$H$55*Inputs!$G$186) | I61: =IF(Inputs!$D$180="ppe_rollforward",Inputs!$H$187*$I$60,$I$55*Inputs!$H$186) | J61: =IF(Inputs!$D$180="ppe_rollforward",Inputs!$I$187*$J$60,$J$55*Inputs!$I$186)
B62: (1,1) Amortization | C62: EGP | D62: =Inputs!$E$52 | E62: =IF(Inputs!$D$180="ppe_rollforward",$E$55*Inputs!$D$188,0) | F62: =IF(Inputs!$D$180="ppe_rollforward",$F$55*Inputs!$E$188,0) | G62: =IF(Inputs!$D$180="ppe_rollforward",$G$55*Inputs!$F$188,0) | H62: =IF(Inputs!$D$180="ppe_rollforward",$H$55*Inputs!$G$188,0) | I62: =IF(Inputs!$D$180="ppe_rollforward",$I$55*Inputs!$H$188,0) | J62: =IF(Inputs!$D$180="ppe_rollforward",$J$55*Inputs!$I$188,0)
B63: (1,1) D&A | C63: EGP | D63: =$D$61+$D$62 | E63: =$E$61+$E$62 | F63: =$F$61+$F$62 | G63: =$G$61+$G$62 | H63: =$H$61+$H$62 | I63: =$I$61+$I$62 | J63: =$J$61+$J$62
B64: (1,1) Capex | C64: EGP | D64: =-Inputs!$E$111 | E64: =IF(Inputs!$D$181="absolute",Inputs!$D$190,$E$55*Inputs!$D$189) | F64: =IF(Inputs!$D$181="absolute",Inputs!$E$190,$F$55*Inputs!$E$189) | G64: =IF(Inputs!$D$181="absolute",Inputs!$F$190,$G$55*Inputs!$F$189) | H64: =IF(Inputs!$D$181="absolute",Inputs!$G$190,$H$55*Inputs!$G$189) | I64: =IF(Inputs!$D$181="absolute",Inputs!$H$190,$I$55*Inputs!$H$189) | J64: =$J$55*Inputs!$I$189
B65: (1,1) Closing PP&E | C65: EGP | D65: =Inputs!$E$57 | E65: =$E$60+$E$64-$E$61 | F65: =$F$60+$F$64-$F$61 | G65: =$G$60+$G$64-$G$61 | H65: =$H$60+$H$64-$H$61 | I65: =$I$60+$I$64-$I$61 | J65: =$J$60+$J$64-$J$61
B66: (1,1) EBIT | C66: EGP | D66: =$D$59-$D$63 | E66: =$E$59-$E$63 | F66: =$F$59-$F$63 | G66: =$G$59-$G$63 | H66: =$H$59-$H$63 | I66: =$I$59-$I$63 | J66: =$J$59-$J$63
B67: (1,1) Tax rate on EBIT | C67: % | D67: =Inputs!$D$133 | E67: =Inputs!$D$196 | F67: =Inputs!$E$196 | G67: =Inputs!$F$196 | H67: =Inputs!$G$196 | I67: =Inputs!$H$196 | J67: =Inputs!$I$196
B68: (1,1) Tax on EBIT | C68: EGP | D68: =$D$66*$D$67 | E68: =$E$66*$E$67 | F68: =$F$66*$F$67 | G68: =$G$66*$G$67 | H68: =$H$66*$H$67 | I68: =$I$66*$I$67 | J68: =$J$66*$J$67
B69: (1,1) NOPAT | C69: EGP | D69: =$D$66-$D$68 | E69: =$E$66-$E$68 | F69: =$F$66-$F$68 | G69: =$G$66-$G$68 | H69: =$H$66-$H$68 | I69: =$I$66-$I$68 | J69: =$J$66-$J$68
B70: (1,1) Cash cost of sales | C70: EGP | D70: =$D$55*(1-((Inputs!$E$26+Inputs!$E$51+Inputs!$E$52)/$D$55)) | E70: =$E$55*(1-(Inputs!$D$183+$E$54)) | F70: =$F$55*(1-(Inputs!$E$183+$E$54)) | G70: =$G$55*(1-(Inputs!$F$183+$E$54)) | H70: =$H$55*(1-(Inputs!$G$183+$E$54)) | I70: =$I$55*(1-(Inputs!$H$183+$E$54)) | J70: =$J$55*(1-(Inputs!$I$183+$E$54))
B71: (1,1) Accounts receivable | C71: EGP | D71: =Inputs!$E$67 | E71: =$E$55*Inputs!$D$191/Inputs!$D$18 | F71: =$F$55*Inputs!$E$191/Inputs!$D$18 | G71: =$G$55*Inputs!$F$191/Inputs!$D$18 | H71: =$H$55*Inputs!$G$191/Inputs!$D$18 | I71: =$I$55*Inputs!$H$191/Inputs!$D$18 | J71: =$J$55*Inputs!$I$191/Inputs!$D$18
B72: (1,1) Inventory | C72: EGP | D72: =Inputs!$E$66 | E72: =$E$70*Inputs!$D$192/Inputs!$D$18 | F72: =$F$70*Inputs!$E$192/Inputs!$D$18 | G72: =$G$70*Inputs!$F$192/Inputs!$D$18 | H72: =$H$70*Inputs!$G$192/Inputs!$D$18 | I72: =$I$70*Inputs!$H$192/Inputs!$D$18 | J72: =$J$70*Inputs!$I$192/Inputs!$D$18
B73: (1,1) Trade payables | C73: EGP | D73: =Inputs!$E$93 | E73: =$E$70*Inputs!$D$193/Inputs!$D$18 | F73: =$F$70*Inputs!$E$193/Inputs!$D$18 | G73: =$G$70*Inputs!$F$193/Inputs!$D$18 | H73: =$H$70*Inputs!$G$193/Inputs!$D$18 | I73: =$I$70*Inputs!$H$193/Inputs!$D$18 | J73: =$J$70*Inputs!$I$193/Inputs!$D$18
B74: (1,1) Other operating current assets | C74: EGP | D74: =Inputs!$E$70+Inputs!$E$72+Inputs!$E$71 | E74: =$E$55*Inputs!$D$194 | F74: =$F$55*Inputs!$E$194 | G74: =$G$55*Inputs!$F$194 | H74: =$H$55*Inputs!$G$194 | I74: =$I$55*Inputs!$H$194 | J74: =$J$55*Inputs!$I$194
B75: (1,1) Other operating current liabilities | C75: EGP | D75: =Inputs!$E$94+Inputs!$E$95+Inputs!$E$97+Inputs!$E$98+Inputs!$E$99 | E75: =$E$55*Inputs!$D$195 | F75: =$F$55*Inputs!$E$195 | G75: =$G$55*Inputs!$F$195 | H75: =$H$55*Inputs!$G$195 | I75: =$I$55*Inputs!$H$195 | J75: =$J$55*Inputs!$I$195
B76: (1,1) Operating net working capital | C76: EGP | D76: =$D$71+$D$72+$D$74-$D$73-$D$75 | E76: =$E$71+$E$72+$E$74-$E$73-$E$75 | F76: =$F$71+$F$72+$F$74-$F$73-$F$75 | G76: =$G$71+$G$72+$G$74-$G$73-$G$75 | H76: =$H$71+$H$72+$H$74-$H$73-$H$75 | I76: =$I$71+$I$72+$I$74-$I$73-$I$75 | J76: =$J$71+$J$72+$J$74-$J$73-$J$75
B77: (1,1) Change in net working capital | C77: EGP | E77: =$E$76-$D$76 | F77: =$F$76-$E$76 | G77: =$G$76-$F$76 | H77: =$H$76-$G$76 | I77: =$I$76-$H$76 | J77: =$J$76-$I$76
B78: (1,1) Net profit (forecast: NOPAT + after-tax net finance income) | C78: EGP | D78: =Inputs!$E$49 | E78: =$E$69+Inputs!$D$202*(1-$E$67) | F78: =$F$69+Inputs!$D$202*(1-$F$67) | G78: =$G$69+Inputs!$D$202*(1-$G$67) | H78: =$H$69+Inputs!$D$202*(1-$H$67) | I78: =$I$69+Inputs!$D$202*(1-$I$67) | J78: =$J$69+Inputs!$D$202*(1-$J$67)
B79: (1,1) Employee and board distributions | C79: EGP | E79: =IF(Inputs!$D$200=1,Inputs!$D$201*$D$78,0) | F79: =IF(Inputs!$D$200=1,Inputs!$D$201*$E$78,0) | G79: =IF(Inputs!$D$200=1,Inputs!$D$201*$F$78,0) | H79: =IF(Inputs!$D$200=1,Inputs!$D$201*$G$78,0) | I79: =IF(Inputs!$D$200=1,Inputs!$D$201*$H$78,0) | J79: =IF(Inputs!$D$200=1,Inputs!$D$201*$I$78,0)
B80: (1,1) Free cash flow to the firm (FCFF) | C80: EGP | E80: =$E$69+$E$63-$E$64-$E$77-$E$79 | F80: =$F$69+$F$63-$F$64-$F$77-$F$79 | G80: =$G$69+$G$63-$G$64-$G$77-$G$79 | H80: =$H$69+$H$63-$H$64-$H$77-$H$79 | I80: =$I$69+$I$63-$I$64-$I$77-$I$79 | J80: =$J$69+$J$63-$J$64-$J$77-$J$79
B81: (1,1) Present value of FCFF | C81: EGP | E81: =$E$80*DCF!$D$10*(1+WACC!$D$54)^(-DCF!$D$12) | F81: =$F$80*DCF!$E$10*(1+WACC!$D$54)^(-DCF!$E$12) | G81: =$G$80*DCF!$F$10*(1+WACC!$D$54)^(-DCF!$F$12) | H81: =$H$80*DCF!$G$10*(1+WACC!$D$54)^(-DCF!$G$12) | I81: =$I$80*DCF!$H$10*(1+WACC!$D$54)^(-DCF!$H$12)
B82: (1,1) Sum of present values | C82: EGP | D82: =SUM($E$81:$I$81)
B83: (1,1) Terminal value | C83: EGP | D83: =IF(Inputs!$D$171="gordon",IF(Inputs!$D$172<WACC!$D$54,$J$80/(WACC!$D$54-Inputs!$D$172),"n/a"),$I$59*Inputs!$D$173)
B84: (1,1) Enterprise value | C84: EGP | D84: =IFERROR($D$82+$D$83*(1+WACC!$D$54)^(-DCF!$D$21),"n/a")
B85: (1,1) Equity value | C85: EGP | D85: =IFERROR($D$84+DCF!$D$51,"n/a")
B86: (1,1) Value per share | C86: EGP | D86: =IFERROR($D$85/Inputs!$D$15,"n/a")
B88: Cell (1,2): revenue growth delta | gross margin delta | C88: pp | D88: =Inputs!$D$237*Inputs!$D$233 | E88: =Inputs!$E$237*Inputs!$D$234
B89: (1,2) Revenue | C89: EGP | D89: =Inputs!$E$23 | E89: =$D$89*(1+(Inputs!$D$182+$D$88)) | F89: =$E$89*(1+(Inputs!$E$182+$D$88)) | G89: =$F$89*(1+(Inputs!$F$182+$D$88)) | H89: =$G$89*(1+(Inputs!$G$182+$D$88)) | I89: =$H$89*(1+(Inputs!$H$182+$D$88)) | J89: =$I$89*(1+Inputs!$D$172)
B90: (1,2) Gross profit before D&A | C90: EGP | D90: =$D$89*((Inputs!$E$26+Inputs!$E$51+Inputs!$E$52)/$D$89) | E90: =$E$89*(Inputs!$D$183+$E$88) | F90: =$F$89*(Inputs!$E$183+$E$88) | G90: =$G$89*(Inputs!$F$183+$E$88) | H90: =$H$89*(Inputs!$G$183+$E$88) | I90: =$I$89*(Inputs!$H$183+$E$88) | J90: =$J$89*(Inputs!$I$183+$E$88)
B91: (1,2) SG&A | C91: EGP | D91: =-(Inputs!$E$29+Inputs!$E$30) | E91: =$E$89*Inputs!$D$184 | F91: =$F$89*Inputs!$E$184 | G91: =$G$89*Inputs!$F$184 | H91: =$H$89*Inputs!$G$184 | I91: =$I$89*Inputs!$H$184 | J91: =$J$89*Inputs!$I$184
B92: (1,2) Other operating income (net) | C92: EGP | D92: =Normalization!$D$13-Inputs!$E$26-Inputs!$E$29-Inputs!$E$30 | E92: =$E$89*Inputs!$D$185 | F92: =$F$89*Inputs!$E$185 | G92: =$G$89*Inputs!$F$185 | H92: =$H$89*Inputs!$G$185 | I92: =$I$89*Inputs!$H$185 | J92: =$J$89*Inputs!$I$185
B93: (1,2) EBITDA | C93: EGP | D93: =$D$90-$D$91+$D$92 | E93: =$E$90-$E$91+$E$92 | F93: =$F$90-$F$91+$F$92 | G93: =$G$90-$G$91+$G$92 | H93: =$H$90-$H$91+$H$92 | I93: =$I$90-$I$91+$I$92 | J93: =$J$90-$J$91+$J$92
B94: (1,2) Opening PP&E | C94: EGP | E94: =Inputs!$E$57 | F94: =$E$99 | G94: =$F$99 | H94: =$G$99 | I94: =$H$99 | J94: =$I$99
B95: (1,2) Depreciation | C95: EGP | D95: =Inputs!$E$51 | E95: =IF(Inputs!$D$180="ppe_rollforward",Inputs!$D$187*$E$94,$E$89*Inputs!$D$186) | F95: =IF(Inputs!$D$180="ppe_rollforward",Inputs!$E$187*$F$94,$F$89*Inputs!$E$186) | G95: =IF(Inputs!$D$180="ppe_rollforward",Inputs!$F$187*$G$94,$G$89*Inputs!$F$186) | H95: =IF(Inputs!$D$180="ppe_rollforward",Inputs!$G$187*$H$94,$H$89*Inputs!$G$186) | I95: =IF(Inputs!$D$180="ppe_rollforward",Inputs!$H$187*$I$94,$I$89*Inputs!$H$186) | J95: =IF(Inputs!$D$180="ppe_rollforward",Inputs!$I$187*$J$94,$J$89*Inputs!$I$186)
B96: (1,2) Amortization | C96: EGP | D96: =Inputs!$E$52 | E96: =IF(Inputs!$D$180="ppe_rollforward",$E$89*Inputs!$D$188,0) | F96: =IF(Inputs!$D$180="ppe_rollforward",$F$89*Inputs!$E$188,0) | G96: =IF(Inputs!$D$180="ppe_rollforward",$G$89*Inputs!$F$188,0) | H96: =IF(Inputs!$D$180="ppe_rollforward",$H$89*Inputs!$G$188,0) | I96: =IF(Inputs!$D$180="ppe_rollforward",$I$89*Inputs!$H$188,0) | J96: =IF(Inputs!$D$180="ppe_rollforward",$J$89*Inputs!$I$188,0)
B97: (1,2) D&A | C97: EGP | D97: =$D$95+$D$96 | E97: =$E$95+$E$96 | F97: =$F$95+$F$96 | G97: =$G$95+$G$96 | H97: =$H$95+$H$96 | I97: =$I$95+$I$96 | J97: =$J$95+$J$96
B98: (1,2) Capex | C98: EGP | D98: =-Inputs!$E$111 | E98: =IF(Inputs!$D$181="absolute",Inputs!$D$190,$E$89*Inputs!$D$189) | F98: =IF(Inputs!$D$181="absolute",Inputs!$E$190,$F$89*Inputs!$E$189) | G98: =IF(Inputs!$D$181="absolute",Inputs!$F$190,$G$89*Inputs!$F$189) | H98: =IF(Inputs!$D$181="absolute",Inputs!$G$190,$H$89*Inputs!$G$189) | I98: =IF(Inputs!$D$181="absolute",Inputs!$H$190,$I$89*Inputs!$H$189) | J98: =$J$89*Inputs!$I$189
B99: (1,2) Closing PP&E | C99: EGP | D99: =Inputs!$E$57 | E99: =$E$94+$E$98-$E$95 | F99: =$F$94+$F$98-$F$95 | G99: =$G$94+$G$98-$G$95 | H99: =$H$94+$H$98-$H$95 | I99: =$I$94+$I$98-$I$95 | J99: =$J$94+$J$98-$J$95
B100: (1,2) EBIT | C100: EGP | D100: =$D$93-$D$97 | E100: =$E$93-$E$97 | F100: =$F$93-$F$97 | G100: =$G$93-$G$97 | H100: =$H$93-$H$97 | I100: =$I$93-$I$97 | J100: =$J$93-$J$97
B101: (1,2) Tax rate on EBIT | C101: % | D101: =Inputs!$D$133 | E101: =Inputs!$D$196 | F101: =Inputs!$E$196 | G101: =Inputs!$F$196 | H101: =Inputs!$G$196 | I101: =Inputs!$H$196 | J101: =Inputs!$I$196
B102: (1,2) Tax on EBIT | C102: EGP | D102: =$D$100*$D$101 | E102: =$E$100*$E$101 | F102: =$F$100*$F$101 | G102: =$G$100*$G$101 | H102: =$H$100*$H$101 | I102: =$I$100*$I$101 | J102: =$J$100*$J$101
B103: (1,2) NOPAT | C103: EGP | D103: =$D$100-$D$102 | E103: =$E$100-$E$102 | F103: =$F$100-$F$102 | G103: =$G$100-$G$102 | H103: =$H$100-$H$102 | I103: =$I$100-$I$102 | J103: =$J$100-$J$102
B104: (1,2) Cash cost of sales | C104: EGP | D104: =$D$89*(1-((Inputs!$E$26+Inputs!$E$51+Inputs!$E$52)/$D$89)) | E104: =$E$89*(1-(Inputs!$D$183+$E$88)) | F104: =$F$89*(1-(Inputs!$E$183+$E$88)) | G104: =$G$89*(1-(Inputs!$F$183+$E$88)) | H104: =$H$89*(1-(Inputs!$G$183+$E$88)) | I104: =$I$89*(1-(Inputs!$H$183+$E$88)) | J104: =$J$89*(1-(Inputs!$I$183+$E$88))
B105: (1,2) Accounts receivable | C105: EGP | D105: =Inputs!$E$67 | E105: =$E$89*Inputs!$D$191/Inputs!$D$18 | F105: =$F$89*Inputs!$E$191/Inputs!$D$18 | G105: =$G$89*Inputs!$F$191/Inputs!$D$18 | H105: =$H$89*Inputs!$G$191/Inputs!$D$18 | I105: =$I$89*Inputs!$H$191/Inputs!$D$18 | J105: =$J$89*Inputs!$I$191/Inputs!$D$18
B106: (1,2) Inventory | C106: EGP | D106: =Inputs!$E$66 | E106: =$E$104*Inputs!$D$192/Inputs!$D$18 | F106: =$F$104*Inputs!$E$192/Inputs!$D$18 | G106: =$G$104*Inputs!$F$192/Inputs!$D$18 | H106: =$H$104*Inputs!$G$192/Inputs!$D$18 | I106: =$I$104*Inputs!$H$192/Inputs!$D$18 | J106: =$J$104*Inputs!$I$192/Inputs!$D$18
B107: (1,2) Trade payables | C107: EGP | D107: =Inputs!$E$93 | E107: =$E$104*Inputs!$D$193/Inputs!$D$18 | F107: =$F$104*Inputs!$E$193/Inputs!$D$18 | G107: =$G$104*Inputs!$F$193/Inputs!$D$18 | H107: =$H$104*Inputs!$G$193/Inputs!$D$18 | I107: =$I$104*Inputs!$H$193/Inputs!$D$18 | J107: =$J$104*Inputs!$I$193/Inputs!$D$18
B108: (1,2) Other operating current assets | C108: EGP | D108: =Inputs!$E$70+Inputs!$E$72+Inputs!$E$71 | E108: =$E$89*Inputs!$D$194 | F108: =$F$89*Inputs!$E$194 | G108: =$G$89*Inputs!$F$194 | H108: =$H$89*Inputs!$G$194 | I108: =$I$89*Inputs!$H$194 | J108: =$J$89*Inputs!$I$194
B109: (1,2) Other operating current liabilities | C109: EGP | D109: =Inputs!$E$94+Inputs!$E$95+Inputs!$E$97+Inputs!$E$98+Inputs!$E$99 | E109: =$E$89*Inputs!$D$195 | F109: =$F$89*Inputs!$E$195 | G109: =$G$89*Inputs!$F$195 | H109: =$H$89*Inputs!$G$195 | I109: =$I$89*Inputs!$H$195 | J109: =$J$89*Inputs!$I$195
B110: (1,2) Operating net working capital | C110: EGP | D110: =$D$105+$D$106+$D$108-$D$107-$D$109 | E110: =$E$105+$E$106+$E$108-$E$107-$E$109 | F110: =$F$105+$F$106+$F$108-$F$107-$F$109 | G110: =$G$105+$G$106+$G$108-$G$107-$G$109 | H110: =$H$105+$H$106+$H$108-$H$107-$H$109 | I110: =$I$105+$I$106+$I$108-$I$107-$I$109 | J110: =$J$105+$J$106+$J$108-$J$107-$J$109
...

Sheet Checks
B2: MOPCO: Checks
B3: Every check must be TRUE. The master check on the Cover is the AND of all checks below.
B4: Blue = hardcoded input | Black = formula
B6: Checks
D7: Result | E7: Value | F7: Compared with | G7: Notes
B8: FY2024 balance sheet balances | D8: =ABS(Inputs!$D$75-Inputs!$D$83-Inputs!$D$100)<Inputs!$D$250
B9: FY2024 operating profit recomputes | D9: =ABS(Inputs!$D$36-(Inputs!$D$26+Inputs!$D$27+Inputs!$D$29+Inputs!$D$30+Inputs!$D$31+Inputs!$D$32+Inputs!$D$33+Inputs!$D$34+Inputs!$D$35))<Inputs!$D$250
B10: FY2024 net profit recomputes | D10: =ABS(Inputs!$D$49-(Inputs!$D$36+Inputs!$D$37+Inputs!$D$38+Inputs!$D$39+Inputs!$D$40+Inputs!$D$41+Inputs!$D$42+Inputs!$D$43+Inputs!$D$44+Inputs!$D$48))<Inputs!$D$250
B11: FY2025 balance sheet balances | D11: =ABS(Inputs!$E$75-Inputs!$E$83-Inputs!$E$100)<Inputs!$D$250
B12: FY2025 operating profit recomputes | D12: =ABS(Inputs!$E$36-(Inputs!$E$26+Inputs!$E$27+Inputs!$E$29+Inputs!$E$30+Inputs!$E$31+Inputs!$E$32+Inputs!$E$33+Inputs!$E$34+Inputs!$E$35))<Inputs!$D$250
B13: FY2025 net profit recomputes | D13: =ABS(Inputs!$E$49-(Inputs!$E$36+Inputs!$E$37+Inputs!$E$38+Inputs!$E$39+Inputs!$E$40+Inputs!$E$41+Inputs!$E$42+Inputs!$E$43+Inputs!$E$44+Inputs!$E$48))<Inputs!$D$250
B14: Forecast year 1: NWC ties to its components | D14: =ABS('Operating Model'!$E$38-('Operating Model'!$E$29+'Operating Model'!$E$31+'Operating Model'!$E$35-'Operating Model'!$E$33-'Operating Model'!$E$37))<Inputs!$D$250
B15: Forecast year 1: PP&E roll-forward ties | D15: =ABS('Operating Model'!$E$22-('Operating Model'!$E$17+'Operating Model'!$E$21-'Operating Model'!$E$18))<Inputs!$D$250
B16: Forecast year 2: NWC ties to its components | D16: =ABS('Operating Model'!$F$38-('Operating Model'!$F$29+'Operating Model'!$F$31+'Operating Model'!$F$35-'Operating Model'!$F$33-'Operating Model'!$F$37))<Inputs!$D$250
B17: Forecast year 2: PP&E roll-forward ties | D17: =ABS('Operating Model'!$F$22-('Operating Model'!$F$17+'Operating Model'!$F$21-'Operating Model'!$F$18))<Inputs!$D$250
B18: Forecast year 3: NWC ties to its components | D18: =ABS('Operating Model'!$G$38-('Operating Model'!$G$29+'Operating Model'!$G$31+'Operating Model'!$G$35-'Operating Model'!$G$33-'Operating Model'!$G$37))<Inputs!$D$250
B19: Forecast year 3: PP&E roll-forward ties | D19: =ABS('Operating Model'!$G$22-('Operating Model'!$G$17+'Operating Model'!$G$21-'Operating Model'!$G$18))<Inputs!$D$250
B20: Forecast year 4: NWC ties to its components | D20: =ABS('Operating Model'!$H$38-('Operating Model'!$H$29+'Operating Model'!$H$31+'Operating Model'!$H$35-'Operating Model'!$H$33-'Operating Model'!$H$37))<Inputs!$D$250
B21: Forecast year 4: PP&E roll-forward ties | D21: =ABS('Operating Model'!$H$22-('Operating Model'!$H$17+'Operating Model'!$H$21-'Operating Model'!$H$18))<Inputs!$D$250
B22: Forecast year 5: NWC ties to its components | D22: =ABS('Operating Model'!$I$38-('Operating Model'!$I$29+'Operating Model'!$I$31+'Operating Model'!$I$35-'Operating Model'!$I$33-'Operating Model'!$I$37))<Inputs!$D$250
B23: Forecast year 5: PP&E roll-forward ties | D23: =ABS('Operating Model'!$I$22-('Operating Model'!$I$17+'Operating Model'!$I$21-'Operating Model'!$I$18))<Inputs!$D$250
B24: Forecast terminal year: NWC ties to its components | D24: =ABS('Operating Model'!$J$38-('Operating Model'!$J$29+'Operating Model'!$J$31+'Operating Model'!$J$35-'Operating Model'!$J$33-'Operating Model'!$J$37))<Inputs!$D$250
B25: Forecast terminal year: PP&E roll-forward ties | D25: =ABS('Operating Model'!$J$22-('Operating Model'!$J$17+'Operating Model'!$J$21-'Operating Model'!$J$18))<Inputs!$D$250
B26: Bridge sums: equity = EV + bridge lines | D26: =ABS(DCF!$D$52-(DCF!$D$30+DCF!$D$40+DCF!$D$41+DCF!$D$42+DCF!$D$43+DCF!$D$44+DCF!$D$45+DCF!$D$46+DCF!$D$47+DCF!$D$48+DCF!$D$49))<Inputs!$D$250
B27: Scenario probabilities sum to 100% | D27: =ABS(Scenarios!$D$19-1)<Inputs!$D$252 | E27: =Scenarios!$D$19
B28: Blend weights sum to 100% | D28: =ABS(Summary!$E$13-1)<Inputs!$D$252 | E28: =Summary!$E$13
B29: Terminal growth below WACC | D29: =Inputs!$D$172<WACC!$D$54 | E29: =Inputs!$D$172 | F29: =WACC!$D$54
B30: Sensitivity centre equals DCF value (wacc_g) | D30: =ABS(Sensitivity!$F$23-DCF!$D$54)<Inputs!$D$251 | E30: =Sensitivity!$F$23 | F30: =DCF!$D$54
B31: Sensitivity centre equals DCF value (growth_margin) | D31: =ABS(Sensitivity!$F$39-DCF!$D$54)<Inputs!$D$251 | E31: =Sensitivity!$F$39 | F31: =DCF!$D$54
B32: Sensitivity centre equals DCF value (rf_beta) | D32: =ABS(Sensitivity!$F$48-DCF!$D$54)<Inputs!$D$251 | E32: =Sensitivity!$F$48 | F32: =DCF!$D$54
B33: Excel DCF per share equals engine (Inputs) | D33: =ABS(DCF!$D$54-Inputs!$D$286)<Inputs!$D$251 | E33: =DCF!$D$54 | F33: =Inputs!$D$286
B34: Excel enterprise value equals engine | D34: =ABS(DCF!$D$30-Inputs!$D$287)<Inputs!$D$250 | E34: =DCF!$D$30 | F34: =Inputs!$D$287
B35: Excel WACC equals engine | D35: =ABS(WACC!$D$54-Inputs!$D$289)<Inputs!$D$252 | E35: =WACC!$D$54 | F35: =Inputs!$D$289
B36: Excel DDM per share equals engine | D36: =ABS(DDM!$D$25-Inputs!$D$291)<Inputs!$D$251 | E36: =DDM!$D$25 | F36: =Inputs!$D$291
B37: Excel blended value equals engine | D37: =ABS(Summary!$D$14-Inputs!$D$292)<Inputs!$D$251 | E37: =Summary!$D$14 | F37: =Inputs!$D$292
B38: Excel probability-weighted scenario value equals engine | D38: =ABS(Scenarios!$D$20-Inputs!$D$293)<Inputs!$D$251 | E38: =Scenarios!$D$20 | F38: =Inputs!$D$293
B39: No stale or unconfirmed rate used without a flag | D39: =COUNTIFS(Sources!$M$22:$M$57,"Yes",Sources!$L$22:$L$57,"<>ok")=COUNTIF(Sources!$N$22:$N$57,"Flagged*")
B40: Master check | D40: =AND($D$8:$D$39)
